Workbook
Name BoxPlot: "BoxPlot"
Name Bubble: "Bubble"
Name Candlestick: "Candlestick"
Name Chart: "Chart"
Name ChartImage: "ChartImage"
Name ColumnRange: "ColumnRange"
Name Dumbbell: "Dumbbell"
Name Heatmap: "Heatmap"
Name Histogram: "Histogram"
Name Map: "Map"
Name OHLC: "OHLC"
Name PieChart: "PieChart"
Name Scatter: "Scatter"
Name Series: "Series"
Name Stripe: "Stripe"
Name Table: "Table"
Name TreeMap: "TreeMap"
Name Waterfall: "Waterfall"

Sheet CDM - Q
C1: Australia | M1: Japan | R1: New Zealand | X1: Korea | AF1: United States | AZ1: Singapore | BE1: Taiwan | BI1: Thailand
C2: =_xll.CEIC.Link("db12b970-86df-4fa8-906a-ca6887c09ca1", "Series", "GDP: 2023-24p: sa") -> GDP: 2023-24p: sa | D2: =_xll.CEIC.Link("916583cc-7d50-45d0-ad3d-65ca48018c4b", "Series", "GDP: sa: 2023-24p: Non Farm") -> GDP: sa: 2023-24p: Non Farm | E2: =_xll.CEIC.Link("71555d41-89ca-4b68-9556-cc3f5c7281bc", "Series", "Unit Labour Cost: Nominal: sa") -> Unit Labour Cost: Nominal: sa | F2: Consumer Price Index (CPI): All Groups | G2: Consumer Price Index: sa | H2: Consumer Price Index: sa: Trimmed Mean | I2: =_xll.CEIC.Link("3d5dbfd6-9152-4fd7-94d1-97980d6f5dfe", "Series", "GDP: sa: Imports of Goods & Services") -> GDP: sa: Imports of Goods & Services | J2: =_xll.CEIC.Link("7bd74527-1990-4c4f-8ce7-18521f70f717", "Series", "GDP: 2023-24p: sa: Imports of Goods & Services") -> GDP: 2023-24p: sa: Imports of Goods & Services | K2: =_xll.CEIC.Link("2c48606c-97cc-4390-8424-197283ff7ffd", "Series", "Unit Labour Cost: Nominal: Non Farm: sa") -> Unit Labour Cost: Nominal: Non Farm: sa | M2: =_xll.CEIC.Link("a7e6e1a1-06e5-48f5-8ced-c20d9948b62a", "Series", "Gross Domestic Product: 2020 Market Price (2020p: sa)") -> Gross Domestic Product: 2020 Market Price (2020p: sa) | N2: (DC)GDP: 2000p: sa | O2: =_xll.CEIC.Link("cad01b68-64a4-4e9b-a447-006e4d8a3e3b", "Series", "GDP: 2020p: sa: Imports") -> GDP: 2020p: sa: Imports | P2: =_xll.CEIC.Link("05026f9c-d747-436f-953a-bb7ee8fe1c76", "Series", "GDP: sa: Imports") -> GDP: sa: Imports | R2: =_xll.CEIC.Link("7a8f9b32-6770-4612-bfec-8ad7c844272b", "Series", "Consumer Price Index (CPI)") -> Consumer Price Index (CPI) | S2: Labour Cost Index | T2: GDP: 2009-10p: Chain-Volume: sa: Imports of Goods and Services | U2: GDP: sa: Imports of Goods and Services | V2: Unemployment Rate: sa | X2: Gross Domestic Product (GDP): 2015p: sa | Y2: =_xll.CEIC.Link("9f78fb79-2d68-4e02-9c2f-6d3412befcc0", "Series", "Gross Domestic Product (GDP): 2020p: sa") -> Gross Domestic Product (GDP): 2020p: sa | Z2: Unit Labour Cost Index (ULI): Manufacturing | AA2: Unit Labour Cost Index (ULI): Manufacturing | AB2: =_xll.CEIC.Link("0f0ec87c-d4da-4cbb-acbd-0b1830eccdc7", "Series", "Unit Labour Cost Index (ULI): Manufacturing") -> Unit Labour Cost Index (ULI): Manufacturing | AC2: GDP: 2020p: sa: Imports of Goods & Services | AD2: GDP: sa: Imports of Goods & Services | AF2: =_xll.CEIC.Link("f9fc37fa-7721-42ca-b29f-ada83ba9916e", "Series", "Gross Domestic Product: 2017p: saar") -> Gross Domestic Product: 2017p: saar | AH2: =_xll.CEIC.Link("32aabc4e-80eb-46a0-a426-452304a785aa", "Series", "GDP: saar: NE: Imports: Goods") -> GDP: saar: NE: Imports: Goods | AI2: FT: saar: Imports: Nonpetroleum Goods | AJ2: FT: saar: Imp: Gds: CPG: Computers, Peripherals & Parts (CP) | AK2: FT: saar: Imp: Gds: CPG: Others | AL2: FT: saar: Imp: Gds: CPG: Oth: Semiconductors & Related Devices | AN2: =_xll.CEIC.Link("54c3e2be-9d5c-4cce-9b9c-4c0ff2a672be", "Series", "GDP: PI: sa: Import: Goods") -> GDP: PI: sa: Import: Goods | AO2: FT: PI: sa: Imports: Nonpetroleum Goods | AP2: FT: PI: sa: Imports: Goods: CPG: Computers, Peripherals & Parts (CP) | AQ2: FT: PI: sa: Imports: Goods: CPG: Other | AR2: FT: PI: sa: Imports: Goods: CPG: Oth: Semiconductors & Rel Devices | AT2: =_xll.CEIC.Link("68084f10-ff53-4932-bcea-941ae142a918", "Series", "FT: PI: sa: Imports: Goods: IS: ND: Petroleum & Pdts") -> FT: PI: sa: Imports: Goods: IS: ND: Petroleum & Pdts | AV2: =_xll.CEIC.Link("2981f81c-fa0e-4c5d-a6da-4d789f3c9bef", "Series", "Productivity & Cost Index: saar: Business: Unit Labour Costs") -> Productivity & Cost Index: saar: Business: Unit Labour Costs | AW2: GDP: 2017p: saar: NE: Imports | AX2: GDP: saar: NE: Imports | AZ2: =_xll.CEIC.Link("20cb9d9b-9ead-43bc-b9aa-b5274e445e15", "Series", "GDP: Imports of Goods & Services") -> GDP: Imports of Goods & Services | BA2: GDP: 2015p: Import of Goods & Services | BB2: GDP: 2015p: sa: Import of Goods & Services | BC2: Unit Labour Cost of Overall Economy: 2015=100 | BE2: =_xll.CEIC.Link("9c397ca4-8e13-430f-96d9-508786a53bb0", "Series", "GDP: 2021p: sa") -> GDP: 2021p: sa | BF2: =_xll.CEIC.Link("610f759b-14fd-4389-b6ed-6980afa3ce95", "Series", "Unemployment Rate: Quarterly: sa: Taiwan") -> Unemployment Rate: Quarterly: sa: Taiwan | BG2: =_xll.CEIC.Link("7b4f32e2-bec8-4fee-a506-1864ee9a3291", "Series", "GDP: Deflator: Imports") -> GDP: Deflator: Imports | BI2: =_xll.CEIC.Link("f545662e-a93f-4d0a-815b-c1bfdae740a0", "Series", "Gross Domestic Product: 2002p: Chain Volume Measures (CVM)") -> Gross Domestic Product: 2002p: Chain Volume Measures (CVM)
B3: Date | C3: 576159347 | D3: 576355377 | E3: 584492247 | F3: Linked | G3: Linked | H3: Linked | I3: 262451801 | J3: 576159327 | K3: 584492307 | M3: 676288387 (JAYAIDAAAABKZF) | N3: 81204101 (JAKX) | O3: 676290657 (JAYAIDAAAABLIX) | P3: 676290437 (JAYAIDAAAABLHH) | R3: 399976317 | S3: 227871202 | T3: 360405607 | U3: 360405487 | V3: 197638902 | X3: 401451117 (KAZAJKBAAAARGK) | Y3: 528868767 (KAZAJKBAAAATPK) | Z3: 193656302 (KGYCAF) | AA3: 353772902 (KGYEAC) | AB3: 537033597 (KGYEACXAAAARDE) | AC3: 528868727 (KAZAJKBAAAATTI) | AD3: 354239117 (KAZAJKBAAAAAGA) | AF3: 511279457 (UAZCSDBAAADDME) | AH3: 511278707 (UAZCSDBAAADEIA) | AI3: 511478117 (UAZCSDBAAADKFE) | AJ3: 511477397 (UAZCSDBAAADKCK) | AK3: 511477427 (UAZCSDBAAADKCN) | AL3: 511477467 (UAZCSDBAAADKCR) | AN3: 511278087 (UAZCSDBAAADEFQ) | AO3: 511476107 (UAZCSDBAAADJXV) | AP3: 511475387 (UAZCSDBAAADJVB) | AQ3: 511475417 (UAZCSDBAAADJVE) | AR3: 511475457 (UAZCSDBAAADJVI) | AT3: 511475277 (UAZCSDBAAADJUQ) | AV3: 521985837 (UGTEWBAAAABBJO) | AW3: 511279937 (UAZCSDBAAADDOA) | AX3: 511278697 (UAZCSDBAAADEHZ) | AZ3: 383937127 (SAZGAAAAAAAALZ) | BA3: 414324517 (SAZGAAAAAAABMX) | BB3: 414337237 (SAZGAAAAAAABQZ) | BC3: 479914577 (SAZGAAAAAAACOB) | BE3: 530108807 (WABNAA) | BF3: 409151467 | BG3: 530154257 (WABRAAE) | BI3: 367505847 (TAZZNAAAAAAACP)
A4: 1948 | B4: 17593 | R4: 26.849028 | AF4: 2239.682 | AH4: 7.34 | AN4: 17.505 | AV4: 17.043 | AW4: 57.862 | AX4: 9.624
B5: 17685 | R5: 27.159541 | AF5: 2276.69 | AH5: 7.644 | AN5: 17.561 | AV5: 16.89 | AW5: 60.156 | AX5: 10.036
B6: 17777 | R6: 27.345849 | AF6: 2289.77 | AH6: 7.708 | AN6: 17.341 | AV6: 17.44 | AW6: 63.297 | AX6: 10.456
B7: 17868 | R7: 27.407952 | AF7: 2292.364 | AH7: 7.536 | AN7: 17.004 | AV7: 17.704 | AW7: 62.27 | AX7: 10.124
A8: 1949 | B8: 17958 | R8: 27.407952 | AF8: 2260.807 | AH8: 7.164 | AN8: 16.592 | AV8: 17.403 | AW8: 60.402 | AX8: 9.604
B9: 18050 | R9: 27.462768 | AF9: 2253.128 | AH9: 6.852 | AN9: 16.397 | AV9: 17.167 | AW9: 59.521 | AX9: 9.364
B10: 18142 | R10: 27.791663 | AF10: 2276.424 | AH10: 6.62 | AN10: 16.316 | AV10: 16.913 | AW10: 57.095 | AX10: 8.936
B11: 18233 | R11: 27.901294 | AF11: 2257.352 | AH11: 6.86 | AN11: 16.403 | AV11: 17.03 | AW11: 57.955 | AX11: 9.092
A12: 1950 | B12: 18323 | R12: 27.956111 | AF12: 2346.104 | AH12: 7.184 | AN12: 16.861 | AV12: 16.867 | AW12: 59.575 | AX12: 9.501
B13: 18415 | R13: 28.833165 | AF13: 2417.682 | AH13: 7.808 | AN13: 17.299 | AV13: 16.878 | AW13: 62.863 | AX13: 10.229
B14: 18507 | R14: 29.792444 | AF14: 2511.127 | AH14: 10.464 | AN14: 17.966 | AV14: 16.91 | AW14: 77.573 | AX14: 13.033
B15: 18598 | R15: 30.285786 | AF15: 2559.214 | AH15: 10.868 | AN15: 18.95 | AV15: 17.137 | AW15: 77.719 | AX15: 13.685
A16: 1951 | B16: 18688 | R16: 30.724314 | AF16: 2593.967 | AH16: 11.772 | AN16: 20.811 | AV16: 17.741 | AW16: 77.724 | AX16: 14.866
B17: 18780 | R17: 32.039896 | AF17: 2638.898 | AH17: 12.04 | AN17: 22.188 | AV17: 18.176 | AW17: 75.148 | AX17: 15.178
B18: 18872 | R18: 33.081397 | AF18: 2693.259 | AH18: 10.808 | AN18: 23.025 | AV18: 17.932 | AW18: 68.784 | AX18: 14.31
B19: 18963 | R19: 33.903636 | AF19: 2699.156 | AH19: 10.084 | AN19: 23.21 | AV19: 18.215 | AW19: 66.985 | AX19: 13.99
A20: 1952 | B20: 19054 | R20: 34.342163 | AF20: 2727.954 | AH20: 10.696 | AN20: 21.79 | AV20: 18.266 | AW20: 74.757 | AX20: 14.958
B21: 19146 | R21: 34.808099 | AF21: 2733.8 | AH21: 10.604 | AN21: 21.412 | AV21: 18.467 | AW21: 74.371 | AX21: 14.63
B22: 19238 | R22: 35.19181 | AF22: 2753.517 | AH22: 10.768 | AN22: 20.999 | AV22: 18.73 | AW22: 78.921 | AX22: 15.25
B23: 19329 | R23: 35.465889 | AF23: 2843.941 | AH23: 11.284 | AN23: 20.631 | AV23: 18.855 | AW23: 85.997 | AX23: 16.342
A24: 1953 | B24: 19419 | R24: 35.822192 | AF24: 2896.811 | AH24: 10.988 | AN24: 20.453 | AV24: 18.881 | AW24: 83.877 | AX24: 15.795
B25: 19511 | R25: 36.233312 | AF25: 2919.206 | AH25: 11.516 | AN25: 20.265 | AV25: 18.907 | AW25: 88.227 | AX25: 16.447
B26: 19603 | R26: 36.644431 | AF26: 2902.785 | AH26: 11.152 | AN26: 20.211 | AV26: 19.196 | AW26: 87.891 | AX26: 16.307
B27: 19694 | R27: 37.439262 | AF27: 2858.845 | AH27: 10.244 | AN27: 20.268 | AV27: 19.232 | AW27: 83.568 | AX27: 15.507
A28: 1954 | B28: 19784 | R28: 37.74075 | AF28: 2845.192 | AH28: 9.976 | AN28: 20.521 | AV28: 19.35 | AW28: 78.742 | AX28: 14.78
B29: 19876 | R29: 38.371132 | AF29: 2848.305 | AH29: 11.048 | AN29: 20.665 | AV29: 19.37 | AW29: 85.824 | AX29: 16.184
B30: 19968 | R30: 38.425948 | AF30: 2880.482 | AH30: 10.224 | AN30: 20.862 | AV30: 19.116 | AW30: 80.647 | AX30: 15.304
B31: 20059 | R31: 38.343724 | AF31: 2936.852 | AH31: 10.164 | AN31: 20.892 | AV31: 19.114 | AW31: 81.412 | AX31: 15.46
A32: 1955 | B32: 20149 | R32: 38.864476 | AF32: 3020.746 | AH32: 11.104 | AN32: 20.611 | AV32: 18.73 | AW32: 86.223 | AX32: 16.169
B33: 20241 | M33: 43911.243 | O33: 1553.4254 | P33: 843.73748 | R33: 39.248187 | AF33: 3069.91 | AH33: 11.232 | AN33: 20.644 | AV33: 18.791 | AW33: 91.112 | AX33: 17.097
B34: 20333 | M34: 45736.018 | O34: 1557.3409 | P34: 871.55075 | R34: 39.303002 | AF34: 3111.379 | AH34: 11.296 | AN34: 20.698 | AV34: 18.923 | AW34: 92.645 | AX34: 17.421
B35: 20424 | M35: 46456.716 | O35: 1861.2878 | P35: 1028.8856 | R35: 39.303002 | AF35: 3130.068 | AH35: 12.476 | AN35: 20.764 | AV35: 19.213 | AW35: 96.002 | AX35: 18.109
A36: 1956 | B36: 20515 | M36: 48191.969 | O36: 1806.927 | P36: 1020.9829 | R36: 39.702884 | AF36: 3117.922 | AH36: 13.02 | AN36: 20.829 | AV36: 19.784 | AW36: 100.032 | AX36: 18.925
B37: 20607 | M37: 48392.168 | O37: 1947.6094 | P37: 1115.0964 | R37: 40.251591 | AF37: 3143.694 | AH37: 12.692 | AN37: 21.009 | AV37: 20.064 | AW37: 99.511 | AX37: 18.973
B38: 20699 | M38: 48708.622 | O38: 2179.7127 | P38: 1267.6075 | R38: 41.113846 | AF38: 3140.874 | AH38: 12.62 | AN38: 21.13 | AV38: 20.271 | AW38: 100.376 | AX38: 19.253
B39: 20790 | M39: 49250.66 | O39: 2392.603 | P39: 1432.9477 | R39: 41.113846 | AF39: 3192.57 | AH39: 12.88 | AN39: 21.373 | AV39: 20.31 | AW39: 95.771 | AX39: 18.541
A40: 1957 | B40: 20880 | M40: 50651.766 | O40: 2586.8267 | P40: 1617.3773 | R40: 40.800299 | AF40: 3213.011 | AH40: 13.188 | AN40: 21.408 | AV40: 20.582 | AW40: 103.391 | AX40: 20.1
B41: 20972 | M41: 51958.062 | O41: 2759.7432 | P41: 1703.4856 | R41: 41.3882 | AF41: 3205.97 | AH41: 13.376 | AN41: 21.423 | AV41: 20.781 | AW41: 104.198 | AX41: 20.27
B42: 21064 | M42: 53074.447 | O42: 2523.3603 | P42: 1515.669 | R42: 41.662553 | AF42: 3237.386 | AH42: 13.06 | AN42: 21.262 | AV42: 20.755 | AW42: 102.186 | AX42: 19.762
B43: 21155 | M43: 53822.742 | O43: 2291.257 | P43: 1304.0419 | R43: 41.85852 | AF43: 3203.894 | AH43: 13.54 | AN43: 20.999 | AV43: 20.904 | AW43: 102.531 | AX43: 19.634
A44: 1958 | B44: 21245 | M44: 53860.628 | O44: 2219.2312 | P44: 1176.6756 | R44: 41.897714 | AF44: 3120.724 | AH44: 12.58 | AN44: 20.381 | AV44: 21.189 | AW44: 104.048 | AX44: 19.455
B45: 21337 | M45: 55527.513 | O45: 2103.1341 | P45: 1087.2832 | R45: 42.32884 | AF45: 3141.224 | AH45: 12.668 | AN45: 20.106 | AV45: 20.962 | AW45: 108.497 | AX45: 20.075
B46: 21429 | M46: 56316.868 | O46: 2199.6541 | P46: 1121.0491 | R46: 44.288509 | AF46: 3213.884 | AH46: 12.78 | AN46: 20.064 | AV46: 21.143 | AW46: 106.863 | AX46: 19.739
B47: 21520 | M47: 57040.547 | O47: 2313.4748 | P47: 1161.2808 | R47: 44.562862 | AF47: 3289.032 | AH47: 13.78 | AN47: 20.097 | AV47: 20.954 | AW47: 112.484 | AX47: 20.823
A48: 1959 | B48: 21610 | M48: 58031.254 | O48: 2437.3118 | P48: 1214.7521 | R48: 44.64125 | AF48: 3352.129 | AH48: 14.484 | AN48: 20.011 | AV48: 21.087 | AW48: 115.44 | AX48: 21.396
B49: 21702 | M49: 59944.975 | O49: 2676.7906 | P49: 1357.4105 | R49: 44.75883 | AF49: 3427.667 | AH49: 15.532 | AN49: 20.18 | AV49: 21.024 | AW49: 121.057 | AX49: 22.544
B50: 21794 | C50: 80842 | D50: 70717 | I50: 532 | J50: 4230 | M50: 63010.947 | O50: 2748.4522 | P50: 1380.708 | R50: 45.22915 | AF50: 3430.057 | AH50: 15.796 | AN50: 20.324 | AV50: 21.136 | AW50: 122.212 | AX50: 22.868
B51: 21885 | C51: 81602 | D51: 71383 | I51: 577 | J51: 4480 | M51: 62483.333 | O51: 2982.6497 | P51: 1542.7639 | R51: 45.072376 | AF51: 3439.832 | AH51: 15.428 | AN51: 20.598 | AV51: 21.389 | AW51: 119.109 | AX51: 22.504
A52: 1960 | B52: 21976 | C52: 82016 | D52: 71736 | I52: 591 | J52: 4617 | M52: 66900.506 | O52: 3185.0685 | P52: 1638.7248 | R52: 44.876409 | X52: 7059.6 | Y52: 7530.1 | AC52: 397.1 | AD52: 8.06 | AF52: 3517.181 | AH52: 15.7 | AN52: 20.541 | AV52: 21.367 | AW52: 123.608 | AX52: 23.288
B53: 22068 | C53: 84257 | D53: 74042 | I53: 633 | J53: 4975 | M53: 66998.009 | O53: 3178.1482 | P53: 1618.8142 | R53: 44.954796 | X53: 7377 | Y53: 7878.4 | AC53: 349.8 | AD53: 7.2 | AF53: 3498.246 | AH53: 15.888 | AN53: 20.506 | AV53: 21.736 | AW53: 124.527 | AX53: 23.455
B54: 22160 | C54: 84438 | D54: 75837 | I54: 670 | J54: 5236 | M54: 69280.012 | O54: 3464.248 | P54: 1727.3988 | R54: 45.34673 | X54: 7295 | Y54: 7788.8 | AC54: 277.4 | AD54: 6.96 | AF54: 3515.385 | AH54: 15.056 | AN54: 20.537 | AV54: 21.595 | AW54: 120.857 | AX54: 22.879
B55: 22251 | C55: 84286 | D55: 74904 | I55: 684 | J55: 5410 | M55: 71942.797 | O55: 3517.6982 | P55: 1750.7989 | R55: 45.777857 | X55: 7338.5 | Y55: 7834.3 | AC55: 307.4 | AD55: 7.71 | AF55: 3470.278 | AH55: 14.236 | AN55: 20.392 | AV55: 21.974 | AW55: 115.156 | AX55: 21.742
A56: 1961 | B56: 22341 | C56: 84539 | D56: 75052 | I56: 683 | J56: 5305 | M56: 74168.74 | O56: 3783.0371 | P56: 1903.8232 | R56: 45.58189 | X56: 7573.4 | Y56: 8081.8 | AC56: 311.1 | AD56: 10.48 | AF56: 3493.703 | AH56: 14.064 | AN56: 20.358 | AV56: 21.933 | AW56: 114.599 | AX56: 21.658
B57: 22433 | C57: 83609 | D57: 74293 | I57: 598 | J57: 4642 | M57: 75729.66 | O57: 4101.0978 | P57: 2118.1187 | R57: 45.58189 | X57: 7900.3 | Y57: 8431.4 | AC57: 352 | AD57: 11.86 | AF57: 3553.021 | AH57: 14.256 | AN57: 20.288 | AV57: 21.719 | AW57: 115.998 | AX57: 21.899
B58: 22525 | C58: 83006 | D58: 73907 | I58: 532 | J58: 4151 | M58: 77170.191 | O58: 4457.4933 | P58: 2291.1562 | R58: 46.287371 | X58: 7756.1 | Y58: 8279.5 | AC58: 255.7 | AD58: 9.11 | AF58: 3621.252 | AH58: 15.76 | AN58: 20.281 | AV58: 21.576 | AW58: 123.682 | AX58: 23.326
B59: 22616 | C59: 83959 | D59: 74655 | I59: 522 | J59: 4096 | M59: 80710.795 | O59: 4529.7012 | P59: 2310.9642 | R59: 46.757692 | X59: 7856.7 | Y59: 8386.2 | AC59: 298.1 | AD59: 10.68 | AF59: 3692.289 | AH59: 16.132 | AN59: 20.268 | AV59: 21.616 | AW59: 126.623 | AX59: 23.87
A60: 1962 | B60: 22706 | C60: 86308 | D60: 77094 | I60: 577 | J60: 4557 | M60: 81815.834 | O60: 4258.1704 | P60: 2155.7847 | R60: 46.914465 | X60: 8013.2 | Y60: 8551.1 | AC60: 366.6 | AD60: 12.62 | AF60: 3758.147 | AH60: 16.44 | AN60: 19.931 | AV60: 21.622 | AW60: 130.476 | AX60: 24.314
B61: 22798 | C61: 87969 | D61: 78361 | I61: 614 | J61: 4853 | M61: 82950.777 | O61: 4144.9871 | P61: 2080.6581 | R61: 47.071238 | X61: 7863.5 | Y61: 8387.5 | AC61: 349.7 | AD61: 12.05 | AF61: 3792.149 | AH61: 16.92 | AN61: 19.89 | AV61: 21.81 | AW61: 133.323 | AX61: 24.884
B62: 22890 | C62: 88673 | D62: 78916 | I62: 648 | J62: 5039 | M62: 83958.12 | O62: 4120.675 | P62: 2040.4263 | R62: 47.423979 | X62: 8093.7 | Y62: 8640.8 | AC62: 442.8 | AD62: 15.28 | AF62: 3838.776 | AH62: 17.084 | AN62: 19.73 | AV62: 21.595 | AW62: 135.014 | AX62: 25.111
B63: 22981 | C63: 90263 | D63: 80543 | I63: 667 | J63: 5191 | M63: 85707.989 | O63: 4132.6945 | P63: 2049.7658 | R63: 47.737525 | X63: 8326.8 | Y63: 8900.8 | AC63: 494.3 | AD63: 17.11 | AF63: 3851.421 | AH63: 17.032 | AN63: 19.705 | AV63: 21.663 | AW63: 136.664 | AX63: 25.55
A64: 1963 | B64: 23071 | C64: 92352 | D64: 82882 | I64: 659 | J64: 5159 | M64: 86894.857 | O64: 4400.8561 | P64: 2217.3639 | R64: 47.776719 | X64: 8814.7 | Y64: 9407.9 | AC64: 488 | AD64: 18.8 | AF64: 3893.482 | AH64: 16.916 | AN64: 19.832 | AV64: 21.694 | AW64: 133.501 | AX64: 25.185
B65: 23163 | C65: 91159 | D65: 81477 | I65: 685 | J65: 5328 | M65: 89446.1 | O65: 4767.2678 | P65: 2416.9831 | R65: 47.972686 | X65: 8606.8 | Y65: 9176.4 | AC65: 516 | AD65: 19.29 | AF65: 3937.183 | AH65: 17.568 | AN65: 19.918 | AV65: 21.685 | AW65: 136.644 | AX65: 25.89
B66: 23255 | C66: 94901 | D66: 85041 | I66: 684 | J66: 5442 | M66: 92066.48 | O66: 5230.6548 | P66: 2655.9103 | R66: 48.325426 | X66: 8890.4 | Y66: 9492.5 | AC66: 554.3 | AD66: 19.99 | AF66: 4023.755 | AH66: 18.152 | AN66: 20.057 | AV66: 21.464 | AW66: 140.113 | AX66: 26.704
B67: 23346 | C67: 96925 | D67: 87267 | I67: 693 | J67: 5475 | M67: 95237.552 | O67: 5543.7984 | P67: 2861.4821 | R67: 48.795746 | X67: 8898.7 | Y67: 9509.9 | AC67: 505.5 | AD67: 17.9 | AF67: 4050.147 | AH67: 18.216 | AN67: 20.177 | AV67: 21.649 | AW67: 139.654 | AX67: 26.764
A68: 1964 | B68: 23437 | C68: 96758 | D68: 86849 | I68: 743 | J68: 5866 | M68: 98279.389 | O68: 5730.1002 | P68: 2957.3404 | R68: 48.991714 | X68: 9430 | Y68: 10057.1 | AC68: 410.4 | AD68: 19.17 | AF68: 4135.553 | AH68: 18.344 | AN68: 20.479 | AV68: 21.525 | AW68: 139.523 | AX68: 26.978
B69: 23529 | C69: 99153 | D69: 89107 | I69: 803 | J69: 6262 | M69: 100649.95 | O69: 5640.5916 | P69: 2901.6112 | R69: 49.42284 | X69: 9158.9 | Y69: 9762.3 | AC69: 354.1 | AD69: 20.94 | AF69: 4180.592 | AH69: 19.08 | AN69: 20.591 | AV69: 21.659 | AW69: 142.663 | AX69: 27.726
B70: 23621 | C70: 99760 | D70: 90659 | I70: 826 | J70: 6518 | M70: 102203.47 | O70: 5558.8228 | P70: 2873.798 | R70: 50.167515 | X70: 9782.2 | Y70: 10436.9 | AC70: 368 | AD70: 24.08 | AF70: 4245.918 | AH70: 19.72 | AN70: 20.512 | AV70: 21.674 | AW70: 146.492 | AX70: 28.429
B71: 23712 | C71: 102593 | D71: 93155 | I71: 882 | J71: 6919 | M71: 103479.19 | O71: 5714.3474 | P71: 2963.1904 | R71: 50.990575 | X71: 10175.4 | Y71: 10873.6 | AC71: 417.9 | AD71: 27.38 | AF71: 4259.046 | AH71: 20.424 | AN71: 20.56 | AV71: 21.977 | AW71: 150.454 | AX71: 29.285
A72: 1965 | B72: 23802 | C72: 103470 | D72: 93422 | I72: 896 | J72: 6867 | M72: 104323.54 | O72: 5872.7859 | P72: 2990.6958 | R72: 51.108156 | X72: 10305.5 | Y72: 10988 | AC72: 390.5 | AD72: 25.13 | AF72: 4362.111 | AH72: 19.552 | AN72: 20.632 | AV72: 21.801 | AW72: 145.038 | AX72: 28.457
B73: 23894 | C73: 105090 | D73: 95981 | I73: 936 | J73: 7138 | M73: 105626.18 | O73: 6018.2033 | P73: 3082.3462 | R73: 51.186542 | X73: 10328.8 | Y73: 11002.3 | AC73: 407.1 | AD73: 27.26 | AF73: 4417.225 | AH73: 22.436 | AN73: 20.459 | AV73: 21.918 | AW73: 162.154 | AX73: 31.679
B74: 23986 | C74: 104774 | D74: 96203 | I74: 983 | J74: 7591 | M74: 108020.11 | O74: 5964.662 | P74: 3076.3935 | R74: 51.85283 | X74: 10247.1 | Y74: 10936 | AC74: 430.3 | AD74: 29.82 | AF74: 4515.427 | AH74: 22.808 | AN74: 20.614 | AV74: 21.635 | AW74: 162.819 | AX74: 32.03
B75: 24077 | C75: 105032 | D75: 96513 | I75: 952 | J75: 7358 | M75: 109695.94 | O75: 6046.9772 | P75: 3116.9331 | R75: 52.20557 | X75: 10486.1 | Y75: 11211.8 | AC75: 533.5 | AD75: 36.93 | AF75: 4619.458 | AH75: 24.192 | AN75: 20.844 | AV75: 21.579 | AW75: 170.763 | AX75: 33.948
A76: 1966 | B76: 24167 | C76: 104732 | D76: 96681 | I76: 878 | J76: 6672 | M76: 112633.74 | O76: 6272.5243 | P76: 3284.1206 | R76: 52.558467 | X76: 11128.8 | Y76: 11868.1 | AC76: 561.1 | AD76: 42.16 | AF76: 4731.888 | AH76: 24.852 | AN76: 20.866 | AV76: 21.705 | AW76: 175.164 | AX76: 34.99
B77: 24259 | C77: 106160 | D77: 96969 | I77: 870 | J77: 6576 | M77: 117040.91 | O77: 6537.5901 | P77: 3436.7344 | R77: 52.867938 | X77: 11818.1 | Y77: 12604.9 | AC77: 593.5 | AD77: 43.94 | AF77: 4748.046 | AH77: 25.612 | AN77: 21.177 | AV77: 22.225 | AW77: 179.52 | AX77: 36.24
B78: 24351 | C78: 109160 | D78: 99990 | I78: 888 | J78: 6793 | M78: 119887.16 | O78: 6811.3973 | P78: 3588.5271 | R78: 53.177409 | X78: 11613.8 | Y78: 12400.5 | AC78: 631.7 | AD78: 46.06 | AF78: 4788.254 | AH78: 27.16 | AN78: 21.096 | AV78: 22.507 | AW78: 189.589 | AX78: 38.171
B79: 24442 | C79: 109881 | D79: 100363 | I79: 903 | J79: 6989 | M79: 122280.9 | O79: 7197.3861 | P79: 3774.8041 | R79: 53.435301 | X79: 11768.4 | Y79: 12564.7 | AC79: 848.5 | AD79: 62.05 | AF79: 4827.537 | AH79: 27.712 | AN79: 21.269 | AV79: 22.694 | AW79: 191.724 | AX79: 38.829
A80: 1967 | B80: 24532 | C80: 114174 | D80: 103475 | I80: 989 | J80: 7431 | M80: 125522.26 | O80: 7523.6419 | P80: 3947.0206 | R80: 54.776342 | X80: 12165 | Y80: 12971.7 | AC80: 700.1 | AD80: 54.96 | AF80: 4870.299 | AH80: 27.704 | AI80: 25.572 | AJ80: 0 | AK80: 2.256 | AN80: 21.195 | AO80: 31.131 | AQ80: 78.692 | AT80: 4.763 | AV80: 22.69 | AW80: 194.717 | AX80: 39.432
B81: 24624 | C81: 114016 | D81: 103674 | I81: 994 | J81: 7460 | M81: 128899.98 | O81: 8263.0214 | P81: 4305.4114 | R81: 56.272117 | X81: 12419 | Y81: 13256.5 | AC81: 664.6 | AD81: 49.2 | AF81: 4873.287 | AH81: 26.796 | AI81: 24.592 | AJ81: 0 | AK81: 2.216 | AN81: 21.111 | AO81: 30.958 | AQ81: 78.896 | AT81: 4.834 | AV81: 22.91 | AW81: 193.17 | AX81: 39.02
B82: 24716 | C82: 116153 | D82: 106808 | I82: 984 | J82: 7247 | M82: 133369.65 | O82: 8375.4763 | P82: 4386.696 | R82: 56.891059 | X82: 12933.1 | Y82: 13823 | AC82: 1059.3 | AD82: 78.6 | AF82: 4919.392 | AH82: 27.012 | AI82: 25.148 | AJ82: 0 | AK82: 2.268 | AN82: 21.109 | AO82: 30.882 | AQ82: 78.885 | AT82: 4.977 | AV82: 23.112 | AW82: 195.707 | AX82: 39.543
B83: 24807 | C83: 117162 | D83: 106826 | I83: 1014 | J83: 7589 | M83: 135947.24 | O83: 8754.3628 | P83: 4625.11 | R83: 56.942637 | X83: 13018.5 | Y83: 13911.3 | AC83: 1011.3 | AD83: 75.75 | AF83: 4956.477 | AH83: 29.532 | AI83: 27.368 | AJ83: 0 | AK83: 2.256 | AN83: 21.115 | AO83: 30.927 | AQ83: 78.85 | AT83: 4.907 | AV83: 23.332 | AW83: 206.028 | AX83: 41.652
A84: 1968 | B84: 24898 | C84: 116120 | D84: 109051 | I84: 1148 | J84: 8593 | M84: 139190.33 | O84: 8818.8309 | P84: 4711.1156 | R84: 57.510001 | X84: 13846.9 | Y84: 14750.8 | AC84: 1112.3 | AD84: 89.53 | AF84: 5057.553 | AH84: 32.116 | AI84: 29.868 | AJ84: 0 | AK84: 2.408 | AN84: 21.26 | AO84: 31.228 | AQ84: 79.873 | AT84: 4.766 | AV84: 23.51 | AW84: 218.167 | AX84: 44.399
B85: 24990 | C85: 120583 | D85: 110601 | I85: 1084 | J85: 8078 | M85: 143940.98 | O85: 9086.9015 | P85: 4788.5001 | R85: 58.283678 | X85: 14050.7 | Y85: 15011.8 | AC85: 1138.8 | AD85: 88.97 | AF85: 5142.033 | AH85: 33.152 | AI85: 30.88 | AJ85: 0 | AK85: 2.428 | AN85: 21.422 | AO85: 31.449 | AQ85: 79.826 | AT85: 4.84 | AV85: 23.678 | AW85: 221.494 | AX85: 45.416
B86: 25082 | C86: 122177 | D86: 112548 | I86: 1092 | J86: 8126 | M86: 147199.36 | O86: 9323.6486 | P86: 4903.1401 | R86: 58.954198 | X86: 14771.8 | Y86: 15831.9 | AC86: 1232.5 | AD86: 96.43 | AF86: 5181.859 | AH86: 35.408 | AI86: 32.908 | AJ86: 0 | AK86: 2.672 | AN86: 21.403 | AO86: 31.454 | AQ86: 79.804 | AT86: 4.769 | AV86: 24.075 | AW86: 234.806 | AX86: 48.24
B87: 25173 | C87: 126736 | D87: 114921 | I87: 1085 | J87: 8269 | M87: 155585.91 | O87: 9712.7334 | P87: 5111.2777 | R87: 59.831032 | X87: 14519.7 | Y87: 15503.5 | AC87: 1389.2 | AD87: 108.26 | AF87: 5202.212 | AH87: 35.108 | AI87: 32.592 | AJ87: 0 | AK87: 2.74 | AN87: 21.58 | AO87: 31.661 | AQ87: 79.773 | AT87: 4.912 | AV87: 24.6 | AW87: 232.828 | AX87: 48.17
A88: 1969 | B88: 25263 | C88: 125871 | D88: 117012 | I88: 1068 | J88: 8081 | M88: 156953.17 | O88: 9672.6685 | P88: 5188.8675 | R88: 60.656288 | X88: 15261.8 | Y88: 16266.5 | AC88: 1332.7 | AD88: 108.17 | AF88: 5283.597 | AH88: 30.772 | AI88: 28.296 | AJ88: 0 | AK88: 2.52 | AN88: 21.71 | AO88: 31.904 | AQ88: 82.209 | AT88: 4.839 | AV88: 24.645 | AW88: 210.867 | AX88: 43.804
B89: 25355 | C89: 128360 | D89: 118107 | I89: 1114 | J89: 8118 | M89: 161524.67 | O89: 9940.557 | P89: 5408.8078 | R89: 61.326808 | X89: 15788.7 | Y89: 16883.4 | AC89: 1473.2 | AD89: 118.67 | AF89: 5299.625 | AH89: 39.116 | AI89: 36.412 | AJ89: 0 | AK89: 3.32 | AN89: 21.794 | AO89: 32.037 | AQ89: 82.141 | AT89: 4.838 | AV89: 25.301 | AW89: 252.469 | AX89: 52.671
B90: 25447 | C90: 130479 | D90: 120350 | I90: 1173 | J90: 8525 | M90: 165393.56 | O90: 10938.628 | P90: 6002.7391 | R90: 61.94575 | X90: 17061.5 | Y90: 18296.3 | AC90: 1592.2 | AD90: 128.79 | AF90: 5334.6 | AH90: 38.536 | AI90: 35.928 | AJ90: 0 | AK90: 3.32 | AN90: 21.918 | AO90: 32.269 | AQ90: 82.01 | AT90: 4.766 | AV90: 25.758 | AW90: 249.198 | AX90: 52.365
B91: 25538 | C91: 133488 | D91: 122466 | I91: 1209 | J91: 8888 | M91: 171848.69 | O91: 11473.95 | P91: 6239.511 | R91: 62.203642 | X91: 17404.6 | Y91: 18566.2 | AC91: 1747.1 | AD91: 141.12 | AF91: 5308.556 | AH91: 38.828 | AI91: 36.02 | AJ91: 0 | AK91: 3.28 | AN91: 22.658 | AO91: 33.443 | AQ91: 81.799 | AT91: 4.765 | AV91: 26.376 | AW91: 246.46 | AX91: 53.126
A92: 1970 | B92: 25628 | C92: 136256 | D92: 123815 | I92: 1218 | J92: 8876 | M92: 177113.48 | O92: 11900.368 | P92: 6636.7994 | R92: 63.544683 | X92: 17109.7 | Y92: 18254.5 | AC92: 1679.3 | AD92: 137.1 | AF92: 5300.652 | AH92: 39.348 | AI92: 36.388 | AJ92: 0 | AK92: 3.48 | AN92: 22.919 | AO92: 33.821 | AQ92: 83.426 | AT92: 4.836 | AV92: 26.754 | AW92: 245.653 | AX92: 53.517
B93: 25720 | C93: 139020 | D93: 126942 | I93: 1273 | J93: 9023 | M93: 179262.31 | O93: 12612.886 | P93: 7038.1931 | R93: 64.524674 | X93: 17797.7 | Y93: 19063.7 | AC93: 1573.4 | AD93: 131.6 | AF93: 5308.164 | AH93: 40.068 | AI93: 37.216 | AJ93: 0 | AK93: 3.508 | AN93: 23.149 | AO93: 34.189 | AQ93: 86.392 | AT93: 4.838 | AV93: 26.778 | AW93: 250.508 | AX93: 55.204
B94: 25812 | C94: 138729 | D94: 128270 | I94: 1269 | J94: 9015 | M94: 184067.77 | O94: 13400.89 | P94: 7520.4607 | R94: 65.710978 | X94: 17907.8 | Y94: 19213.8 | AC94: 1671.1 | AD94: 148.5 | AF94: 5357.077 | AH94: 41.18 | AI94: 38.42 | AJ94: 0 | AK94: 3.652 | AN94: 23.861 | AO94: 35.28 | AQ94: 100.578 | AT94: 4.913 | AV94: 26.776 | AW94: 249.933 | AX94: 56.431
B95: 25903 | C95: 139334 | D95: 129985 | I95: 1277 | J95: 9177 | M95: 183474.86 | O95: 13616.876 | P95: 7482.3843 | R95: 68.393059 | X95: 19287.5 | Y95: 20598.7 | AC95: 1774.3 | AD95: 173.6 | AF95: 5299.672 | AH95: 42.824 | AI95: 39.688 | AJ95: 0 | AK95: 3.748 | AN95: 24.136 | AO95: 35.637 | AQ95: 101.565 | AT95: 5.061 | AV95: 27.274 | AW95: 253.809 | AX95: 57.888
A96: 1971 | B96: 25993 | C96: 141069 | D96: 130674 | I96: 1297 | J96: 9087 | M96: 185145.88 | O96: 14517.334 | P96: 7572.1872 | R96: 70.095148 | X96: 19395.7 | Y96: 20739.9 | AC96: 1916.2 | AD96: 170.1 | AF96: 5443.619 | AH96: 43.376 | AI96: 40.544 | AJ96: 0 | AK96: 3.808 | AN96: 24.565 | AO96: 36.256 | AQ96: 109.642 | AT96: 5.177 | AV96: 27.009 | AW96: 250.817 | AX96: 58.651
B97: 26085 | C97: 141684 | D97: 131101 | I97: 1375 | J97: 9115 | M97: 188133.2 | O97: 14033.369 | P97: 7619.5006 | R97: 71.642503 | X97: 20027.5 | Y97: 21485.5 | AC97: 2119 | AD97: 194.1 | AF97: 5473.059 | AH97: 47.44 | AI97: 43.948 | AJ97: 0 | AK97: 3.964 | AN97: 24.501 | AO97: 36.077 | AQ97: 102.95 | AT97: 5.323 | AV97: 27.295 | AW97: 269.738 | AX97: 63.296
B98: 26177 | C98: 146103 | D98: 134540 | I98: 1381 | J98: 9039 | M98: 190425.39 | O98: 13393.241 | P98: 7333.0547 | R98: 73.035122 | X98: 20066.2 | Y98: 21525.4 | AC98: 2058.7 | AD98: 219.5 | AF98: 5518.072 | AH98: 49.64 | AI98: 45.668 | AJ98: 0 | AK98: 4.012 | AN98: 24.767 | AO98: 36.413 | AQ98: 104.361 | AT98: 5.466 | AV98: 27.434 | AW98: 275.701 | AX98: 65.482
B99: 26268 | C99: 145631 | D99: 135134 | I99: 1363 | J99: 8453 | M99: 192160.07 | O99: 13247.277 | P99: 7255.6702 | R99: 74.634055 | X99: 20216.9 | Y99: 21595.4 | AC99: 1946.4 | AD99: 207.8 | AF99: 5531.032 | AH99: 45.744 | AI99: 41.44 | AJ99: 0 | AK99: 3.768 | AN99: 25.053 | AO99: 36.867 | AQ99: 99.321 | AT99: 5.459 | AV99: 27.865 | AW99: 257.013 | AX99: 61.939
A100: 1972 | B100: 26359 | C100: 143895 | D100: 133170 | I100: 1336 | J100: 8409 | M100: 198420.38 | O100: 14716.839 | P100: 7324.0231 | R100: 76.026674 | X100: 20507.5 | Y100: 22003.9 | AC100: 1928.1 | AD100: 207.8 | AF100: 5632.649 | AH100: 55.092 | AI100: 50.816 | AJ100: 0.296 | AK100: 5.02 | AN100: 25.68 | AO100: 37.869 | AP100: 8818.966 | AQ100: 104.997 | AT100: 5.448 | AV100: 28.278 | AW100: 294.575 | AX100: 72.173
...

Sheet CDM - M
C1: Australia | E1: Japan | G1: United States | J1: Korea | M1: Taiwan | Q1: India
C2: =_xll.CEIC.Link("c129f249-dc89-4599-a62a-d354b1877a9e", "Series", "Unemployment Rate: Monthly: sa: Australia") -> Unemployment Rate: Monthly: sa: Australia | E2: Labour Productivity Index (LPI): Manufacturing (Mfg) | G2: Policy Rate: Month End: United States: Federal Funds Rate | H2: PCE: PI: sa: excl Food & Energy | J2: Policy Rate: Month End: Base Rate: Bank of Korea | K2: Unemployment Rate | M2: =_xll.CEIC.Link("ea131218-bb06-4e5d-9f7f-ee7c6ad9a92e", "Series", "Consumer Price Index: Seasonally Adjusted") -> Consumer Price Index: Seasonally Adjusted | N2: =_xll.CEIC.Link("f3f1afd8-7e0b-4e66-bcdc-ee7d884dbe2a", "Series", "Unit Output Labor Cost Index: Industry (ID)") -> Unit Output Labor Cost Index: Industry (ID) | O2: =_xll.CEIC.Link("993ca365-589c-4708-81cc-64bd9ddf66ce", "Series", "Policy Rate: Month End: Discount Rate") -> Policy Rate: Month End: Discount Rate | Q2: =_xll.CEIC.Link("feac2130-cfdd-45b8-8d57-2d7cf9b8a97d", "Series", "SPF: CPI Combined: Headline: Current Fiscal Year: Mean") -> SPF: CPI Combined: Headline: Current Fiscal Year: Mean
B3: Date | C3: 450248027 | E3: 509218357 (JGXCAZJAAAASBF) | G3: 456107507 | H3: 511285287 (UIKBACHAAAAMKM) | J3: 30189201 (KMFC) | K3: 224917301 | M3: 503425687 (WIHJA) | N3: 508773667 (WGVTAA) | O3: 45972101 (WMAD) | Q3: %
A4: 1948 | B4: 17533 | Q4: 413887677 (ISAAAALNAAAAYX)
B5: 17564 | Q5: 4.3
B6: 17593
B7: 17624 | Q7: 3.4
B8: 17654
B9: 17685 | Q9: 3.6
B10: 17715
B11: 17746 | Q11: 3.5
B12: 17777
B13: 17807 | Q13: 3.8
B14: 17838
B15: 17868 | Q15: 3.7
A16: 1949 | B16: 17899
B17: 17930 | Q17: 4.7
B18: 17958
B19: 17989 | Q19: 4.7
B20: 18019
B21: 18050 | Q21: 4.5
B22: 18080
B23: 18111 | Q23: 4.1
B24: 18142
B25: 18172 | Q25: 3.6
B26: 18203
B27: 18233 | Q27: 3.5
A28: 1950 | B28: 18264
B29: 18295 | Q29: 3.8
B30: 18323
B31: 18354 | Q31: 3.6
B32: 18384
B33: 18415 | Q33: 3.6
B34: 18445
B35: 18476 | Q35: 3.9
B36: 18507
B37: 18537 | Q37: 4.6
B38: 18568
B39: 18598 | Q39: 4.8
A40: 1951 | B40: 18629
B41: 18660 | Q41: 4.1
B42: 18688
B43: 18719 | Q43: 4.5
B44: 18749
B45: 18780 | Q45: 5.5
B46: 18810
B47: 18841 | Q47: 6.3
B48: 18872
B49: 18902 | Q49: 6.2
B50: 18933
B51: 18963 | Q51: 6.2
A52: 1952 | B52: 18994
B53: 19025 | Q53: 4.9
B54: 19054
B55: 19085 | Q55: 5.6
B56: 19115
B57: 19146 | Q57: 5.4
B58: 19176
B59: 19207 | Q59: 5.4
B60: 19238
B61: 19268 | Q61: 5.4
B62: 19299
B63: 19329 | Q63: 5.4
A64: 1953 | B64: 19360
B65: 19391 | Q65: 6.5
B66: 19419
B67: 19450 | Q67: 6.7
B68: 19480
B69: 19511 | Q69: 6.7
B70: 19541
B71: 19572 | Q71: 6.7
B72: 19603
B73: 19633 | Q73: 6.5
B74: 19664
B75: 19694 | Q75: 6.6
A76: 1954 | B76: 19725
B77: 19756 | Q77: 5
B78: 19784
B79: 19815 | Q79: 5.2
B80: 19845
B81: 19876 | Q81: 5.5
B82: 19906 | G82: 0.25
B83: 19937 | G83: 1.44 | Q83: 5.4
B84: 19968 | G84: 1.44
B85: 19998 | G85: 1.13 | Q85: 5.4
B86: 20029 | G86: 1.38
B87: 20059 | G87: 1.44 | Q87: 5.4
A88: 1955 | B88: 20090 | G88: 1.44
B89: 20121 | G89: 1.44 | Q89: 4.5
B90: 20149 | G90: 1.44
B91: 20180 | G91: 1.69 | Q91: 4.6
B92: 20210 | G92: 1.69
B93: 20241 | G93: 1.69 | Q93: 4.5
B94: 20271 | G94: 1.75
B95: 20302 | G95: 2 | Q95: 4.8
B96: 20333 | G96: 2.19
B97: 20363 | G97: 2.25 | Q97: 4.8
B98: 20394 | G98: 2.44
B99: 20424 | G99: 2.5 | Q99: 4.7
A100: 1956 | B100: 20455 | G100: 2.5
...

Sheet CDM - D
C1: =_xll.CEIC.Link("dc6f7b84-d40a-4805-8f1e-5277c5dd5bd8", "Series", "(DC)OxCGRT: Stringency Index: Australia") -> (DC)OxCGRT: Stringency Index: Australia | D1: (DC)OxCGRT: Stringency Index: New Zealand | E1: (DC)OxCGRT: Stringency Index: Japan | F1: (DC)OxCGRT: Stringency Index: South Korea | G1: (DC)OxCGRT: Stringency Index: United States | H1: (DC)OxCGRT: Stringency Index: Singapore | I1: =_xll.CEIC.Link("98505fdc-78bf-42eb-b555-64f4b111ac39", "Series", "(DC)OxCGRT: Stringency Index: Taiwan") -> (DC)OxCGRT: Stringency Index: Taiwan | J1: =_xll.CEIC.Link("d2abc0ae-0a0b-4457-bd27-0edb6530f53b", "Series", "(DC)OxCGRT: Stringency Index: Thailand") -> (DC)OxCGRT: Stringency Index: Thailand
B2: Date | C2: 450498717 | D2: 450499727 | E2: 450499427 | F2: 450500047 | G2: 450500267 | H2: 450499987 | I2: 450500137 | J2: Index
A3: =YEAR(B3) -> 2020 | B3: 43831 | C3: 0 | D3: 0 | E3: 0 | F3: 0 | G3: 0 | H3: 0 | I3: 2.78 | J3: 450500167
B4: 43832 | C4: 0 | D4: 0 | E4: 0 | F4: 0 | G4: 0 | H4: 13.89 | I4: 8.33 | J4: 0
B5: 43833 | C5: 0 | D5: 0 | E5: 0 | F5: 0 | G5: 0 | H5: 13.89 | I5: 8.33 | J5: 0
B6: 43834 | C6: 0 | D6: 0 | E6: 0 | F6: 0 | G6: 0 | H6: 13.89 | I6: 8.33 | J6: 0
B7: 43835 | C7: 0 | D7: 0 | E7: 0 | F7: 0 | G7: 0 | H7: 13.89 | I7: 8.33 | J7: 0
B8: 43836 | C8: 0 | D8: 0 | E8: 0 | F8: 0 | G8: 0 | H8: 13.89 | I8: 8.33 | J8: 0
B9: 43837 | C9: 0 | D9: 0 | E9: 2.78 | F9: 0 | G9: 0 | H9: 13.89 | I9: 8.33 | J9: 0
B10: 43838 | C10: 0 | D10: 0 | E10: 2.78 | F10: 0 | G10: 0 | H10: 13.89 | I10: 8.33 | J10: 0
B11: 43839 | C11: 0 | D11: 0 | E11: 2.78 | F11: 0 | G11: 0 | H11: 13.89 | I11: 8.33 | J11: 0
B12: 43840 | C12: 0 | D12: 0 | E12: 2.78 | F12: 0 | G12: 0 | H12: 13.89 | I12: 8.33 | J12: 0
B13: 43841 | C13: 0 | D13: 0 | E13: 2.78 | F13: 0 | G13: 0 | H13: 13.89 | I13: 8.33 | J13: 0
B14: 43842 | C14: 0 | D14: 0 | E14: 2.78 | F14: 0 | G14: 0 | H14: 13.89 | I14: 8.33 | J14: 0
B15: 43843 | C15: 0 | D15: 0 | E15: 2.78 | F15: 0 | G15: 0 | H15: 13.89 | I15: 8.33 | J15: 0
... B368: 44196 | C368: 70.83 | D368: 22.22 | E368: 45.37 | F368: 68.98 | G368: 71.76 | H368: 50.93 | I368: 19.44 | J368: 63.89
A369: =YEAR(B369) -> 2021 | B369: 44197 | C369: 70.83 | D369: 22.22 | E369: 48.15 | F369: 60.65 | G369: 71.76 | H369: 50.93 | I369: 19.44 | J369: 63.89
B370: 44198 | C370: 70.83 | D370: 22.22 | E370: 48.15 | F370: 62.04 | G370: 71.76 | H370: 50.93 | I370: 19.44 | J370: 63.89
B371: 44199 | C371: 70.83 | D371: 22.22 | E371: 48.15 | F371: 62.04 | G371: 71.76 | H371: 50.93 | I371: 19.44 | J371: 63.89
B372: 44200 | C372: 70.83 | D372: 22.22 | E372: 48.15 | F372: 62.04 | G372: 71.76 | H372: 50.93 | I372: 19.44 | J372: 63.89
B373: 44201 | C373: 70.83 | D373: 22.22 | E373: 49.54 | F373: 67.59 | G373: 71.76 | H373: 50.93 | I373: 19.44 | J373: 63.89
B374: 44202 | C374: 70.83 | D374: 22.22 | E374: 49.54 | F374: 67.59 | G374: 71.76 | H374: 50.93 | I374: 19.44 | J374: 63.89
B375: 44203 | C375: 70.83 | D375: 22.22 | E375: 49.54 | F375: 63.89 | G375: 71.76 | H375: 50.93 | I375: 19.44 | J375: 63.89
B376: 44204 | C376: 70.83 | D376: 22.22 | E376: 49.54 | F376: 63.89 | G376: 71.76 | H376: 50.93 | I376: 19.44 | J376: 63.89
B377: 44205 | C377: 70.83 | D377: 22.22 | E377: 49.54 | F377: 63.89 | G377: 71.76 | H377: 50.93 | I377: 19.44 | J377: 63.89
B378: 44206 | C378: 70.83 | D378: 22.22 | E378: 49.54 | F378: 63.89 | G378: 71.76 | H378: 50.93 | I378: 19.44 | J378: 63.89
B379: 44207 | C379: 55.09 | D379: 22.22 | E379: 49.54 | F379: 63.89 | G379: 71.76 | H379: 50.93 | I379: 19.44 | J379: 63.89
B380: 44208 | C380: 55.09 | D380: 22.22 | E380: 49.54 | F380: 63.89 | G380: 71.76 | H380: 50.93 | I380: 19.44 | J380: 63.89
B381: 44209 | C381: 55.09 | D381: 22.22 | E381: 49.54 | F381: 63.89 | G381: 71.76 | H381: 50.93 | I381: 19.44 | J381: 63.89
... B733: 44561 | C733: 56.94 | D733: 62.96 | E733: 47.22 | F733: 50.93 | G733: 58.8 | H733: 48.15 | I733: 20.37 | J733: 43.52
A734: =YEAR(B734) -> 2022 | B734: 44562 | C734: 56.94 | D734: 62.96 | E734: 47.22 | F734: 50.93 | G734: 58.8 | H734: 53.7 | I734: 20.37 | J734: 43.52
B735: 44563 | C735: 56.94 | D735: 62.96 | E735: 47.22 | F735: 50.93 | G735: 58.8 | H735: 53.7 | I735: 20.37 | J735: 43.52
B736: 44564 | C736: 56.94 | D736: 62.96 | E736: 47.22 | F736: 50.93 | G736: 58.8 | H736: 53.7 | I736: 20.37 | J736: 43.52
B737: 44565 | C737: 56.94 | D737: 62.96 | E737: 47.22 | F737: 50.93 | G737: 58.8 | H737: 53.7 | I737: 20.37 | J737: 50.93
B738: 44566 | C738: 56.94 | D738: 62.96 | E738: 47.22 | F738: 50.93 | G738: 58.8 | H738: 53.7 | I738: 20.37 | J738: 50.93
B739: 44567 | C739: 62.5 | D739: 62.96 | E739: 47.22 | F739: 50.93 | G739: 58.8 | H739: 53.7 | I739: 20.37 | J739: 50.93
B740: 44568 | C740: 62.5 | D740: 62.96 | E740: 47.22 | F740: 50.93 | G740: 58.8 | H740: 53.7 | I740: 20.37 | J740: 50.93
B741: 44569 | C741: 62.5 | D741: 62.96 | E741: 47.22 | F741: 50.93 | G741: 58.8 | H741: 53.7 | I741: 20.37 | J741: 50.93
B742: 44570 | C742: 62.5 | D742: 62.96 | E742: 47.22 | F742: 50.93 | G742: 58.8 | H742: 53.7 | I742: 20.37 | J742: 50.93
B743: 44571 | C743: 62.5 | D743: 62.96 | E743: 47.22 | F743: 50.93 | G743: 58.8 | H743: 53.7 | I743: 20.37 | J743: 50.93
B744: 44572 | C744: 56.94 | D744: 62.96 | E744: 47.22 | F744: 50.93 | G744: 58.8 | H744: 53.7 | I744: 20.37 | J744: 50.93
B745: 44573 | C745: 56.94 | D745: 62.96 | E745: 47.22 | F745: 50.93 | G745: 58.8 | H745: 53.7 | I745: 20.37 | J745: 48.15
B746: 44574 | C746: 62.5 | D746: 62.96 | E746: 47.22 | F746: 50.93 | G746: 58.8 | H746: 53.7 | I746: 20.37 | J746: 48.15
... B1098: 44926 | C1098: 11.11 | D1098: 11.11 | E1098: 33.33 | F1098: 11.11 | G1098: 37.04 | H1098: 17.59 | I1098: 17.59 | J1098: 5.56
J1099: 5.56

Sheet AU - Q
C1: GDP: sa: 2022-23p | D1: GDP: sa: 2022-23p: Non Farm | E1: Import Price Deflator | F1: Consumer Price Index (CPI): All Groups | G1: CPI from 1970 Onwards | H1: CPI Trimmed Means Spliced | I1: CPI Core Index | J1: CPI Core Inflation Annualised | K1: CPI Core Moving Average | L1: Unemployment | M1: Covid Stringency Index | N1: Nominal Unit Labour Costs non-farm (s.a) | O1: Expectations Melb | P1: Expectations Union | Q1: Expectations Combined | R1: Interest | S1: SSR | T1: CPI Core Inflation Forecast | U1: Real GNI (s.a.)
B2: Date | F2: NSA | G2: WCA sa - don’t drag down! | I2: sa tax adj
A3: 1948 | B3: 17593 | M3: 0
B4: 17685 | M4: 0
B5: 17777 | M5: 0
B6: 17868 | M6: 0
A7: 1949 | B7: 17958 | M7: 0
B8: 18050 | M8: 0
B9: 18142 | M9: 0
B10: 18233 | M10: 0
A11: 1950 | B11: 18323 | M11: 0
B12: 18415 | M12: 0
B13: 18507 | M13: 0
B14: 18598 | M14: 0
A15: 1951 | B15: 18688 | M15: 0
B16: 18780 | M16: 0
B17: 18872 | M17: 0
B18: 18963 | M18: 0
A19: 1952 | B19: 19054 | M19: 0
B20: 19146 | M20: 0
B21: 19238 | M21: 0
B22: 19329 | M22: 0
A23: 1953 | B23: 19419 | M23: 0
B24: 19511 | M24: 0
B25: 19603 | M25: 0
B26: 19694 | M26: 0
A27: 1954 | B27: 19784 | M27: 0
B28: 19876 | M28: 0
B29: 19968 | M29: 0
B30: 20059 | M30: 0
A31: 1955 | B31: 20149 | M31: 0
B32: 20241 | M32: 0
B33: 20333 | M33: 0
B34: 20424 | M34: 0
A35: 1956 | B35: 20515 | M35: 0
B36: 20607 | M36: 0
B37: 20699 | M37: 0
B38: 20790 | M38: 0
A39: 1957 | B39: 20880 | M39: 0
B40: 20972 | M40: 0
B41: 21064 | M41: 0
B42: 21155 | M42: 0
A43: 1958 | B43: 21245 | M43: 0
B44: 21337 | M44: 0
B45: 21429 | M45: 0
B46: 21520 | M46: 0
A47: 1959 | B47: 21610 | M47: 0
B48: 21702 | M48: 0
B49: 21794 | C49: ='CDM - Q'!C50 -> 80842 | D49: ='CDM - Q'!D50 -> 70717 | E49: ='CDM - Q'!I50/'CDM - Q'!J50*100 -> 12.576832 | M49: 0 | U49: 69787
B50: 21885 | C50: ='CDM - Q'!C51 -> 81602 | D50: ='CDM - Q'!D51 -> 71383 | E50: ='CDM - Q'!I51/'CDM - Q'!J51*100 -> 12.879464 | M50: 0 | U50: 70741
A51: 1960 | B51: 21976 | C51: ='CDM - Q'!C52 -> 82016 | D51: ='CDM - Q'!D52 -> 71736 | E51: ='CDM - Q'!I52/'CDM - Q'!J52*100 -> 12.80052 | M51: 0 | U51: 71850
B52: 22068 | C52: ='CDM - Q'!C53 -> 84257 | D52: ='CDM - Q'!D53 -> 74042 | E52: ='CDM - Q'!I53/'CDM - Q'!J53*100 -> 12.723618 | M52: 0 | U52: 73865
B53: 22160 | C53: ='CDM - Q'!C54 -> 84438 | D53: ='CDM - Q'!D54 -> 75837 | E53: ='CDM - Q'!I54/'CDM - Q'!J54*100 -> 12.796028 | M53: 0 | U53: 73355
B54: 22251 | C54: ='CDM - Q'!C55 -> 84286 | D54: ='CDM - Q'!D55 -> 74904 | E54: ='CDM - Q'!I55/'CDM - Q'!J55*100 -> 12.643253 | M54: 0 | U54: 73712
A55: 1961 | B55: 22341 | C55: ='CDM - Q'!C56 -> 84539 | D55: ='CDM - Q'!D56 -> 75052 | E55: ='CDM - Q'!I56/'CDM - Q'!J56*100 -> 12.874647 | M55: 0 | U55: 73099
B56: 22433 | C56: ='CDM - Q'!C57 -> 83609 | D56: ='CDM - Q'!D57 -> 74293 | E56: ='CDM - Q'!I57/'CDM - Q'!J57*100 -> 12.882378 | M56: 0 | U56: 71806
B57: 22525 | C57: ='CDM - Q'!C58 -> 83006 | D57: ='CDM - Q'!D58 -> 73907 | E57: ='CDM - Q'!I58/'CDM - Q'!J58*100 -> 12.816189 | M57: 0 | U57: 72236
B58: 22616 | C58: ='CDM - Q'!C59 -> 83959 | D58: ='CDM - Q'!D59 -> 74655 | E58: ='CDM - Q'!I59/'CDM - Q'!J59*100 -> 12.744141 | M58: 0 | U58: 72706
A59: 1962 | B59: 22706 | C59: ='CDM - Q'!C60 -> 86308 | D59: ='CDM - Q'!D60 -> 77094 | E59: ='CDM - Q'!I60/'CDM - Q'!J60*100 -> 12.661839 | M59: 0 | U59: 75339
B60: 22798 | C60: ='CDM - Q'!C61 -> 87969 | D60: ='CDM - Q'!D61 -> 78361 | E60: ='CDM - Q'!I61/'CDM - Q'!J61*100 -> 12.651968 | M60: 0 | U60: 76725
B61: 22890 | C61: ='CDM - Q'!C62 -> 88673 | D61: ='CDM - Q'!D62 -> 78916 | E61: ='CDM - Q'!I62/'CDM - Q'!J62*100 -> 12.859694 | M61: 0 | U61: 77010
B62: 22981 | C62: ='CDM - Q'!C63 -> 90263 | D62: ='CDM - Q'!D63 -> 80543 | E62: ='CDM - Q'!I63/'CDM - Q'!J63*100 -> 12.849162 | M62: 0 | U62: 78238
A63: 1963 | B63: 23071 | C63: ='CDM - Q'!C64 -> 92352 | D63: ='CDM - Q'!D64 -> 82882 | E63: ='CDM - Q'!I64/'CDM - Q'!J64*100 -> 12.773793 | M63: 0 | U63: 80389
B64: 23163 | C64: ='CDM - Q'!C65 -> 91159 | D64: ='CDM - Q'!D65 -> 81477 | E64: ='CDM - Q'!I65/'CDM - Q'!J65*100 -> 12.856607 | M64: 0 | U64: 79890
B65: 23255 | C65: ='CDM - Q'!C66 -> 94901 | D65: ='CDM - Q'!D66 -> 85041 | E65: ='CDM - Q'!I66/'CDM - Q'!J66*100 -> 12.568908 | M65: 0 | U65: 83298
B66: 23346 | C66: ='CDM - Q'!C67 -> 96925 | D66: ='CDM - Q'!D67 -> 87267 | E66: ='CDM - Q'!I67/'CDM - Q'!J67*100 -> 12.657534 | M66: 0 | U66: 85812
A67: 1964 | B67: 23437 | C67: ='CDM - Q'!C68 -> 96758 | D67: ='CDM - Q'!D68 -> 86849 | E67: ='CDM - Q'!I68/'CDM - Q'!J68*100 -> 12.666212 | M67: 0 | U67: 86140
B68: 23529 | C68: ='CDM - Q'!C69 -> 99153 | D68: ='CDM - Q'!D69 -> 89107 | E68: ='CDM - Q'!I69/'CDM - Q'!J69*100 -> 12.823379 | M68: 0 | U68: 87410
B69: 23621 | C69: ='CDM - Q'!C70 -> 99760 | D69: ='CDM - Q'!D70 -> 90659 | E69: ='CDM - Q'!I70/'CDM - Q'!J70*100 -> 12.672599 | M69: 0 | U69: 88280
B70: 23712 | C70: ='CDM - Q'!C71 -> 102593 | D70: ='CDM - Q'!D71 -> 93155 | E70: ='CDM - Q'!I71/'CDM - Q'!J71*100 -> 12.747507 | M70: 0 | U70: 90511
A71: 1965 | B71: 23802 | C71: ='CDM - Q'!C72 -> 103470 | D71: ='CDM - Q'!D72 -> 93422 | E71: ='CDM - Q'!I72/'CDM - Q'!J72*100 -> 13.04791 | M71: 0 | U71: 90817
B72: 23894 | C72: ='CDM - Q'!C73 -> 105090 | D72: ='CDM - Q'!D73 -> 95981 | E72: ='CDM - Q'!I73/'CDM - Q'!J73*100 -> 13.112917 | M72: 0 | U72: 91834
B73: 23986 | C73: ='CDM - Q'!C74 -> 104774 | D73: ='CDM - Q'!D74 -> 96203 | E73: ='CDM - Q'!I74/'CDM - Q'!J74*100 -> 12.949546 | M73: 0 | U73: 91695
B74: 24077 | C74: ='CDM - Q'!C75 -> 105032 | D74: ='CDM - Q'!D75 -> 96513 | E74: ='CDM - Q'!I75/'CDM - Q'!J75*100 -> 12.938298 | M74: 0 | U74: 92223
A75: 1966 | B75: 24167 | C75: ='CDM - Q'!C76 -> 104732 | D75: ='CDM - Q'!D76 -> 96681 | E75: ='CDM - Q'!I76/'CDM - Q'!J76*100 -> 13.159472 | M75: 0 | U75: 92271
B76: 24259 | C76: ='CDM - Q'!C77 -> 106160 | D76: ='CDM - Q'!D77 -> 96969 | E76: ='CDM - Q'!I77/'CDM - Q'!J77*100 -> 13.229927 | M76: 0 | U76: 93620
B77: 24351 | C77: ='CDM - Q'!C78 -> 109160 | D77: ='CDM - Q'!D78 -> 99990 | E77: ='CDM - Q'!I78/'CDM - Q'!J78*100 -> 13.07228 | M77: 0 | U77: 95905
B78: 24442 | C78: ='CDM - Q'!C79 -> 109881 | D78: ='CDM - Q'!D79 -> 100363 | E78: ='CDM - Q'!I79/'CDM - Q'!J79*100 -> 12.920303 | M78: 0 | U78: 97078
A79: 1967 | B79: 24532 | C79: ='CDM - Q'!C80 -> 114174 | D79: ='CDM - Q'!D80 -> 103475 | E79: ='CDM - Q'!I80/'CDM - Q'!J80*100 -> 13.30911 | M79: 0 | U79: 100402
B80: 24624 | C80: ='CDM - Q'!C81 -> 114016 | D80: ='CDM - Q'!D81 -> 103674 | E80: ='CDM - Q'!I81/'CDM - Q'!J81*100 -> 13.324397 | M80: 0 | U80: 99575
B81: 24716 | C81: ='CDM - Q'!C82 -> 116153 | D81: ='CDM - Q'!D82 -> 106808 | E81: ='CDM - Q'!I82/'CDM - Q'!J82*100 -> 13.578032 | M81: 0 | U81: 101013
B82: 24807 | C82: ='CDM - Q'!C83 -> 117162 | D82: ='CDM - Q'!D83 -> 106826 | E82: ='CDM - Q'!I83/'CDM - Q'!J83*100 -> 13.361444 | M82: 0 | U82: 101595
A83: 1968 | B83: 24898 | C83: ='CDM - Q'!C84 -> 116120 | D83: ='CDM - Q'!D84 -> 109051 | E83: ='CDM - Q'!I84/'CDM - Q'!J84*100 -> 13.359711 | M83: 0 | U83: 101384
B84: 24990 | C84: ='CDM - Q'!C85 -> 120583 | D84: ='CDM - Q'!D85 -> 110601 | E84: ='CDM - Q'!I85/'CDM - Q'!J85*100 -> 13.419163 | M84: 0 | U84: 105373
B85: 25082 | C85: ='CDM - Q'!C86 -> 122177 | D85: ='CDM - Q'!D86 -> 112548 | E85: ='CDM - Q'!I86/'CDM - Q'!J86*100 -> 13.438346 | M85: 0 | U85: 106308
B86: 25173 | C86: ='CDM - Q'!C87 -> 126736 | D86: ='CDM - Q'!D87 -> 114921 | E86: ='CDM - Q'!I87/'CDM - Q'!J87*100 -> 13.121296 | M86: 0 | U86: 110033
A87: 1969 | B87: 25263 | C87: ='CDM - Q'!C88 -> 125871 | D87: ='CDM - Q'!D88 -> 117012 | E87: ='CDM - Q'!I88/'CDM - Q'!J88*100 -> 13.216186 | M87: 0 | U87: 110839
B88: 25355 | C88: ='CDM - Q'!C89 -> 128360 | D88: ='CDM - Q'!D89 -> 118107 | E88: ='CDM - Q'!I89/'CDM - Q'!J89*100 -> 13.722592 | M88: 0 | U88: 112474
B89: 25447 | C89: ='CDM - Q'!C90 -> 130479 | D89: ='CDM - Q'!D90 -> 120350 | E89: ='CDM - Q'!I90/'CDM - Q'!J90*100 -> 13.759531 | M89: 0 | U89: 114299
B90: 25538 | C90: ='CDM - Q'!C91 -> 133488 | D90: ='CDM - Q'!D91 -> 122466 | E90: ='CDM - Q'!I91/'CDM - Q'!J91*100 -> 13.60261 | M90: 0 | U90: 116643
A91: 1970 | B91: 25628 | C91: ='CDM - Q'!C92 -> 136256 | D91: ='CDM - Q'!D92 -> 123815 | E91: ='CDM - Q'!I92/'CDM - Q'!J92*100 -> 13.722397 | G91: 9.69759 | H91: =H92*G91/G92 -> 9.8264673 | M91: 0 | U91: 119668
B92: 25720 | C92: ='CDM - Q'!C93 -> 139020 | D92: ='CDM - Q'!D93 -> 126942 | E92: ='CDM - Q'!I93/'CDM - Q'!J93*100 -> 14.10839 | G92: 9.7835087 | H92: =H93*G92/G93 -> 9.9135279 | M92: 0 | U92: 121759
B93: 25812 | C93: ='CDM - Q'!C94 -> 138729 | D93: ='CDM - Q'!D94 -> 128270 | E93: ='CDM - Q'!I94/'CDM - Q'!J94*100 -> 14.076539 | G93: 9.8338211 | H93: =H94*G93/G94 -> 9.9645089 | M93: 0 | U93: 121135
B94: 25903 | C94: ='CDM - Q'!C95 -> 139334 | D94: ='CDM - Q'!D95 -> 129985 | E94: ='CDM - Q'!I95/'CDM - Q'!J95*100 -> 13.915223 | G94: 9.9668661 | H94: =H95*G94/G95 -> 10.099322 | M94: 0 | U94: 120911
A95: 1971 | B95: 25993 | C95: ='CDM - Q'!C96 -> 141069 | D95: ='CDM - Q'!D96 -> 130674 | E95: ='CDM - Q'!I96/'CDM - Q'!J96*100 -> 14.273137 | G95: 10.066956 | H95: =H96*G95/G96 -> 10.200742 | M95: 0 | U95: 122603
B96: 26085 | C96: ='CDM - Q'!C97 -> 141684 | D96: ='CDM - Q'!D97 -> 131101 | E96: ='CDM - Q'!I97/'CDM - Q'!J97*100 -> 15.085025 | G96: 10.17359 | H96: =H97*G96/G97 -> 10.308793 | M96: 0 | U96: 122809
B97: 26177 | C97: ='CDM - Q'!C98 -> 146103 | D97: ='CDM - Q'!D98 -> 134540 | E97: ='CDM - Q'!I98/'CDM - Q'!J98*100 -> 15.278239 | G97: 10.40098 | H97: =H98*G97/G98 -> 10.539205 | M97: 0 | U97: 127128
B98: 26268 | C98: ='CDM - Q'!C99 -> 145631 | D98: ='CDM - Q'!D99 -> 135134 | E98: ='CDM - Q'!I99/'CDM - Q'!J99*100 -> 16.124453 | G98: 10.600318 | H98: =H99*G98/G99 -> 10.741192 | M98: 0 | U98: 124230
A99: 1972 | B99: 26359 | C99: ='CDM - Q'!C100 -> 143895 | D99: ='CDM - Q'!D100 -> 133170 | E99: ='CDM - Q'!I100/'CDM - Q'!J100*100 -> 15.887739 | G99: 10.744126 | H99: =H100*G99/G100 -> 10.886911 | M99: 0 | U99: 124193
B100: 26451 | C100: ='CDM - Q'!C101 -> 147099 | D100: ='CDM - Q'!D101 -> 137037 | E100: ='CDM - Q'!I101/'CDM - Q'!J101*100 -> 16.387828 | G100: 10.904065 | H100: =H101*G100/G101 -> 11.048976 | M100: 0 | U100: 127632
...

Sheet AU - M
C1: Unemployment Rate: Monthly: sa: Australia | D1: RBA Cash Rate | E1: SSR Spliced
B2: Date
A3: 1948 | B3: 17533
B4: 17564
B5: 17593
B6: 17624
B7: 17654
B8: 17685
B9: 17715
B10: 17746
B11: 17777
B12: 17807
B13: 17838
B14: 17868
A15: 1949 | B15: 17899
B16: 17930
B17: 17958
B18: 17989
B19: 18019
B20: 18050
B21: 18080
B22: 18111
B23: 18142
B24: 18172
B25: 18203
B26: 18233
A27: 1950 | B27: 18264
B28: 18295
B29: 18323
B30: 18354
B31: 18384
B32: 18415
B33: 18445
B34: 18476
B35: 18507
B36: 18537
B37: 18568
B38: 18598
A39: 1951 | B39: 18629
B40: 18660
B41: 18688
B42: 18719
B43: 18749
B44: 18780
B45: 18810
B46: 18841
B47: 18872
B48: 18902
B49: 18933
B50: 18963
A51: 1952 | B51: 18994
B52: 19025
B53: 19054
B54: 19085
B55: 19115
B56: 19146
B57: 19176
B58: 19207
B59: 19238
B60: 19268
B61: 19299
B62: 19329
A63: 1953 | B63: 19360
B64: 19391
B65: 19419
B66: 19450
B67: 19480
B68: 19511
B69: 19541
B70: 19572
B71: 19603
B72: 19633
B73: 19664
B74: 19694
A75: 1954 | B75: 19725
B76: 19756
B77: 19784
B78: 19815
B79: 19845
B80: 19876
B81: 19906
B82: 19937
B83: 19968
B84: 19998
B85: 20029
B86: 20059
A87: 1955 | B87: 20090
B88: 20121
B89: 20149
B90: 20180
B91: 20210
B92: 20241
B93: 20271
B94: 20302
B95: 20333
B96: 20363
B97: 20394
B98: 20424
A99: 1956 | B99: 20455
B100: 20486
...

Sheet AU Edits
C1: CPI All Excl Food and Energy
B2: Date | C2: Index | D2: Tax | F2: Tax Adjusted | G2: Sa
A3: 1975 | B3: 27454
B4: 27546
B5: 27638
B6: 27729
A7: 1976 | B7: 27820
B8: 27912
B9: 28004
B10: 28095
A11: 1977 | B11: 28185
B12: 28277
B13: 28369
B14: 28460
A15: 1978 | B15: 28550
B16: 28642
B17: 28734
B18: 28825
A19: 1979 | B19: 28915
B20: 29007
B21: 29099
B22: 29190
A23: 1980 | B23: 29281
B24: 29373
B25: 29465
B26: 29556
A27: 1981 | B27: 29646
B28: 29738
B29: 29830
B30: 29921
A31: 1982 | B31: 30011
B32: 30103
B33: 30195
B34: 30286
A35: 1983 | B35: 30376
B36: 30468
B37: 30560
B38: 30651
A39: 1984 | B39: 30742
B40: 30834
B41: 30926
B42: 31017
A43: 1985 | B43: 31107
B44: 31199
B45: 31291
B46: 31382
A47: 1986 | B47: 31472
B48: 31564
B49: 31656
B50: 31747
A51: 1987 | B51: 31837
B52: 31929
B53: 32021
B54: 32112
A55: 1988 | B55: 32203
B56: 32295
B57: 32387
B58: 32478
A59: 1989 | B59: 32568
B60: 32660
B61: 32752 | C61: 57.2 | F61: =C61*$D$105 -> 59.106667 | G61: 59.257413
B62: 32843 | C62: 58.4 | F62: =C62*$D$105 -> 60.346667 | G62: 60.25786
A63: 1990 | B63: 32933 | C63: 59.4 | F63: =C63*$D$105 -> 61.38 | G63: 61.316158
B64: 33025 | C64: 60.3 | F64: =C64*$D$105 -> 62.31 | G64: 62.316643
B65: 33117 | C65: 60.9 | F65: =C65*$D$105 -> 62.93 | G65: 63.068499
B66: 33208 | C66: 61.9 | F66: =C66*$D$105 -> 63.963333 | G66: 63.889885
A67: 1991 | B67: 33298 | C67: 62.2 | F67: =C67*$D$105 -> 64.273333 | G67: 64.208889
B68: 33390 | C68: 62.6 | F68: =C68*$D$105 -> 64.686667 | G68: 64.686064
B69: 33482 | C69: 62.7 | F69: =C69*$D$105 -> 64.79 | G69: 64.905415
B70: 33573 | C70: 63.4 | F70: =C70*$D$105 -> 65.513333 | G70: 65.474314
A71: 1992 | B71: 33664 | C71: 63.4 | F71: =C71*$D$105 -> 65.513333 | G71: 65.451194
B72: 33756 | C72: 63.1 | F72: =C72*$D$105 -> 65.203333 | G72: 65.189544
B73: 33848 | C73: 63.1 | F73: =C73*$D$105 -> 65.203333 | G73: 65.290474
B74: 33939 | C74: 63.3 | F74: =C74*$D$105 -> 65.41 | G74: 65.40852
A75: 1993 | B75: 34029 | C75: 63.9 | F75: =C75*$D$105 -> 66.03 | G75: 65.973087
B76: 34121 | C76: 64.3 | F76: =C76*$D$105 -> 66.443333 | G76: 66.417179
B77: 34213 | C77: 64.6 | F77: =C77*$D$105 -> 66.753333 | G77: 66.809736
B78: 34304 | C78: 64.6 | F78: =C78*$D$105 -> 66.753333 | G78: 66.789618
A79: 1994 | B79: 34394 | C79: 65 | F79: =C79*$D$105 -> 67.166667 | G79: 67.116465
B80: 34486 | C80: 65.5 | F80: =C80*$D$105 -> 67.683333 | G80: 67.641284
B81: 34578 | C81: 65.9 | F81: =C81*$D$105 -> 68.096667 | G81: 68.133095
B82: 34669 | C82: 66.6 | F82: =C82*$D$105 -> 68.82 | G82: 68.879283
A83: 1995 | B83: 34759 | C83: 67.7 | F83: =C83*$D$105 -> 69.956667 | G83: 69.917415
B84: 34851 | C84: 68.7 | F84: =C84*$D$105 -> 70.99 | G84: 70.929494
B85: 34943 | C85: 69.4 | F85: =C85*$D$105 -> 71.713333 | G85: 71.745172
B86: 35034 | C86: 70.1 | F86: =C86*$D$105 -> 72.436667 | G86: 72.501771
A87: 1996 | B87: 35125 | C87: 70.5 | F87: =C87*$D$105 -> 72.85 | G87: 72.824156
B88: 35217 | C88: 70.8 | F88: =C88*$D$105 -> 73.16 | G88: 73.087346
B89: 35309 | C89: 71 | F89: =C89*$D$105 -> 73.366667 | G89: 73.403362
B90: 35400 | C90: 70.9 | F90: =C90*$D$105 -> 73.263333 | G90: 73.314717
A91: 1997 | B91: 35490 | C91: 70.8 | F91: =C91*$D$105 -> 73.16 | G91: 73.148065
B92: 35582 | C92: 70.6 | F92: =C92*$D$105 -> 72.953333 | G92: 72.883206
B93: 35674 | C93: 70.2 | F93: =C93*$D$105 -> 72.54 | G93: 72.569487
B94: 35765 | C94: 70.4 | F94: =C94*$D$105 -> 72.746667 | G94: 72.794359
A95: 1998 | B95: 35855 | C95: 70.7 | F95: =C95*$D$105 -> 73.056667 | G95: 73.049944
B96: 35947 | C96: 71 | F96: =C96*$D$105 -> 73.366667 | G96: 73.300342
B97: 36039 | C97: 70.7 | F97: =C97*$D$105 -> 73.056667 | G97: 73.078143
B98: 36130 | C98: 71 | F98: =C98*$D$105 -> 73.366667 | G98: 73.418366
A99: 1999 | B99: 36220 | C99: 70.8 | F99: =C99*$D$105 -> 73.16 | G99: 73.153831
B100: 36312 | C100: 71 | F100: =C100*$D$105 -> 73.366667 | G100: 73.302983
...

Sheet JN - Q
C1: Real GDP: 2020p | D1: Gross Domestic Product: Seasonally Adjusted (sa) (Japan) | E1: Unit Labour Cost: Nominal | F1: Unit Labour Cost: Nominal | G1: JN Core CPI | H1: JN Core Core CPI | I1: Core Core CPI Forecast | J1: Unemployment | K1: Expectations | L1: Covid Stringency Index | M1: Import Price Deflator | N1: Interest | O1: SSR | S1: Japan Inflation YoY
B2: Date | D2: Nominal | E2: nsa | F2: sa | S2: Core+2
A3: 1980 | B3: 29281 | C3: ='CDM - Q'!M132 -> 277749.49 | G3: =AVERAGEIFS('JN - M'!D:D,'JN - M'!$B:$B,">="&EDATE('JN - Q'!$B3,-2),'JN - M'!$B:$B,"<="&EOMONTH('JN - Q'!$B3,0)) -> 77.581051 | H3: =AVERAGEIFS('JN - M'!E:E,'JN - M'!$B:$B,">="&EDATE('JN - Q'!$B3,-2),'JN - M'!$B:$B,"<="&EOMONTH('JN - Q'!$B3,0)) -> 77.620409 | I3: =AVERAGEIFS('JN - M'!F:F,'JN - M'!$B:$B,">="&EDATE('JN - Q'!$B3,-2),'JN - M'!$B:$B,"<="&EOMONTH('JN - Q'!$B3,0)) -> 77.620409 | J3: =AVERAGEIFS('JN - M'!K:K,'JN - M'!$B:$B,">="&EDATE('JN - Q'!$B3,-2),'JN - M'!$B:$B,"<="&EOMONTH('JN - Q'!$B3,0)) -> 1.8829931 | L3: 0 | N3: =AVERAGEIFS('JN - M'!I:I,'JN - M'!$B:$B,">="&EDATE('JN - Q'!$B3,-2),'JN - M'!$B:$B,"<="&EOMONTH('JN - Q'!$B3,0)) -> 9.1755667 | O3: =AVERAGEIFS('JN - M'!J:J,'JN - M'!$B:$B,">="&EDATE('JN - Q'!$B3,-2),'JN - M'!$B:$B,"<="&EOMONTH('JN - Q'!$B3,0)) -> 11.365418
B4: 29373 | C4: ='CDM - Q'!M133 -> 276285.32 | G4: =AVERAGEIFS('JN - M'!D:D,'JN - M'!$B:$B,">="&EDATE('JN - Q'!$B4,-2),'JN - M'!$B:$B,"<="&EOMONTH('JN - Q'!$B4,0)) -> 80.011111 | H4: =AVERAGEIFS('JN - M'!E:E,'JN - M'!$B:$B,">="&EDATE('JN - Q'!$B4,-2),'JN - M'!$B:$B,"<="&EOMONTH('JN - Q'!$B4,0)) -> 79.950131 | I4: =AVERAGEIFS('JN - M'!F:F,'JN - M'!$B:$B,">="&EDATE('JN - Q'!$B4,-2),'JN - M'!$B:$B,"<="&EOMONTH('JN - Q'!$B4,0)) -> 79.950131 | J4: =AVERAGEIFS('JN - M'!K:K,'JN - M'!$B:$B,">="&EDATE('JN - Q'!$B4,-2),'JN - M'!$B:$B,"<="&EOMONTH('JN - Q'!$B4,0)) -> 1.9402977 | L4: 0 | N4: =AVERAGEIFS('JN - M'!I:I,'JN - M'!$B:$B,">="&EDATE('JN - Q'!$B4,-2),'JN - M'!$B:$B,"<="&EOMONTH('JN - Q'!$B4,0)) -> 12.471667 | O4: =AVERAGEIFS('JN - M'!J:J,'JN - M'!$B:$B,">="&EDATE('JN - Q'!$B4,-2),'JN - M'!$B:$B,"<="&EOMONTH('JN - Q'!$B4,0)) -> 13.210224
B5: 29465 | C5: ='CDM - Q'!M134 -> 282473.93 | G5: =AVERAGEIFS('JN - M'!D:D,'JN - M'!$B:$B,">="&EDATE('JN - Q'!$B5,-2),'JN - M'!$B:$B,"<="&EOMONTH('JN - Q'!$B5,0)) -> 81.159659 | H5: =AVERAGEIFS('JN - M'!E:E,'JN - M'!$B:$B,">="&EDATE('JN - Q'!$B5,-2),'JN - M'!$B:$B,"<="&EOMONTH('JN - Q'!$B5,0)) -> 80.874623 | I5: =AVERAGEIFS('JN - M'!F:F,'JN - M'!$B:$B,">="&EDATE('JN - Q'!$B5,-2),'JN - M'!$B:$B,"<="&EOMONTH('JN - Q'!$B5,0)) -> 80.874623 | J5: =AVERAGEIFS('JN - M'!K:K,'JN - M'!$B:$B,">="&EDATE('JN - Q'!$B5,-2),'JN - M'!$B:$B,"<="&EOMONTH('JN - Q'!$B5,0)) -> 2.060493 | L5: 0 | N5: =AVERAGEIFS('JN - M'!I:I,'JN - M'!$B:$B,">="&EDATE('JN - Q'!$B5,-2),'JN - M'!$B:$B,"<="&EOMONTH('JN - Q'!$B5,0)) -> 12.063833 | O5: =AVERAGEIFS('JN - M'!J:J,'JN - M'!$B:$B,">="&EDATE('JN - Q'!$B5,-2),'JN - M'!$B:$B,"<="&EOMONTH('JN - Q'!$B5,0)) -> 12.778239
B6: 29556 | C6: ='CDM - Q'!M135 -> 288477.88 | G6: =AVERAGEIFS('JN - M'!D:D,'JN - M'!$B:$B,">="&EDATE('JN - Q'!$B6,-2),'JN - M'!$B:$B,"<="&EOMONTH('JN - Q'!$B6,0)) -> 82.102485 | H6: =AVERAGEIFS('JN - M'!E:E,'JN - M'!$B:$B,">="&EDATE('JN - Q'!$B6,-2),'JN - M'!$B:$B,"<="&EOMONTH('JN - Q'!$B6,0)) -> 82.094954 | I6: =AVERAGEIFS('JN - M'!F:F,'JN - M'!$B:$B,">="&EDATE('JN - Q'!$B6,-2),'JN - M'!$B:$B,"<="&EOMONTH('JN - Q'!$B6,0)) -> 82.094954 | J6: =AVERAGEIFS('JN - M'!K:K,'JN - M'!$B:$B,">="&EDATE('JN - Q'!$B6,-2),'JN - M'!$B:$B,"<="&EOMONTH('JN - Q'!$B6,0)) -> 2.1733967 | L6: 0 | N6: =AVERAGEIFS('JN - M'!I:I,'JN - M'!$B:$B,">="&EDATE('JN - Q'!$B6,-2),'JN - M'!$B:$B,"<="&EOMONTH('JN - Q'!$B6,0)) -> 10.008167 | O6: =AVERAGEIFS('JN - M'!J:J,'JN - M'!$B:$B,">="&EDATE('JN - Q'!$B6,-2),'JN - M'!$B:$B,"<="&EOMONTH('JN - Q'!$B6,0)) -> 10.600838
A7: 1981 | B7: 29646 | C7: ='CDM - Q'!M136 -> 290246.47 | G7: =AVERAGEIFS('JN - M'!D:D,'JN - M'!$B:$B,">="&EDATE('JN - Q'!$B7,-2),'JN - M'!$B:$B,"<="&EOMONTH('JN - Q'!$B7,0)) -> 82.88134 | H7: =AVERAGEIFS('JN - M'!E:E,'JN - M'!$B:$B,">="&EDATE('JN - Q'!$B7,-2),'JN - M'!$B:$B,"<="&EOMONTH('JN - Q'!$B7,0)) -> 82.279852 | I7: =AVERAGEIFS('JN - M'!F:F,'JN - M'!$B:$B,">="&EDATE('JN - Q'!$B7,-2),'JN - M'!$B:$B,"<="&EOMONTH('JN - Q'!$B7,0)) -> 82.279852 | J7: =AVERAGEIFS('JN - M'!K:K,'JN - M'!$B:$B,">="&EDATE('JN - Q'!$B7,-2),'JN - M'!$B:$B,"<="&EOMONTH('JN - Q'!$B7,0)) -> 2.1839602 | K7: =K8*S7/S8 -> 4.2171197 | L7: 0 | N7: =AVERAGEIFS('JN - M'!I:I,'JN - M'!$B:$B,">="&EDATE('JN - Q'!$B7,-2),'JN - M'!$B:$B,"<="&EOMONTH('JN - Q'!$B7,0)) -> 8.5153 | O7: =AVERAGEIFS('JN - M'!J:J,'JN - M'!$B:$B,">="&EDATE('JN - Q'!$B7,-2),'JN - M'!$B:$B,"<="&EOMONTH('JN - Q'!$B7,0)) -> 9.0195659 | S7: =(H7/H3-1)*100+2 -> 8.0028585
B8: 29738 | C8: ='CDM - Q'!M137 -> 293798.4 | G8: =AVERAGEIFS('JN - M'!D:D,'JN - M'!$B:$B,">="&EDATE('JN - Q'!$B8,-2),'JN - M'!$B:$B,"<="&EOMONTH('JN - Q'!$B8,0)) -> 83.564763 | H8: =AVERAGEIFS('JN - M'!E:E,'JN - M'!$B:$B,">="&EDATE('JN - Q'!$B8,-2),'JN - M'!$B:$B,"<="&EOMONTH('JN - Q'!$B8,0)) -> 83.759041 | I8: =AVERAGEIFS('JN - M'!F:F,'JN - M'!$B:$B,">="&EDATE('JN - Q'!$B8,-2),'JN - M'!$B:$B,"<="&EOMONTH('JN - Q'!$B8,0)) -> 83.759041 | J8: =AVERAGEIFS('JN - M'!K:K,'JN - M'!$B:$B,">="&EDATE('JN - Q'!$B8,-2),'JN - M'!$B:$B,"<="&EOMONTH('JN - Q'!$B8,0)) -> 2.2746378 | K8: =K9*S8/S9 -> 3.5643577 | L8: 0 | N8: =AVERAGEIFS('JN - M'!I:I,'JN - M'!$B:$B,">="&EDATE('JN - Q'!$B8,-2),'JN - M'!$B:$B,"<="&EOMONTH('JN - Q'!$B8,0)) -> 7.1200333 | O8: =AVERAGEIFS('JN - M'!J:J,'JN - M'!$B:$B,">="&EDATE('JN - Q'!$B8,-2),'JN - M'!$B:$B,"<="&EOMONTH('JN - Q'!$B8,0)) -> 7.5416732 | S8: =(H8/H4-1)*100+2 -> 6.7641073
B9: 29830 | C9: ='CDM - Q'!M138 -> 293144.94 | G9: =AVERAGEIFS('JN - M'!D:D,'JN - M'!$B:$B,">="&EDATE('JN - Q'!$B9,-2),'JN - M'!$B:$B,"<="&EOMONTH('JN - Q'!$B9,0)) -> 84.460922 | H9: =AVERAGEIFS('JN - M'!E:E,'JN - M'!$B:$B,">="&EDATE('JN - Q'!$B9,-2),'JN - M'!$B:$B,"<="&EOMONTH('JN - Q'!$B9,0)) -> 84.239777 | I9: =AVERAGEIFS('JN - M'!F:F,'JN - M'!$B:$B,">="&EDATE('JN - Q'!$B9,-2),'JN - M'!$B:$B,"<="&EOMONTH('JN - Q'!$B9,0)) -> 84.239777 | J9: =AVERAGEIFS('JN - M'!K:K,'JN - M'!$B:$B,">="&EDATE('JN - Q'!$B9,-2),'JN - M'!$B:$B,"<="&EOMONTH('JN - Q'!$B9,0)) -> 2.1598291 | K9: =K10*S9/S10 -> 3.2465235 | L9: 0 | N9: =AVERAGEIFS('JN - M'!I:I,'JN - M'!$B:$B,">="&EDATE('JN - Q'!$B9,-2),'JN - M'!$B:$B,"<="&EOMONTH('JN - Q'!$B9,0)) -> 7.2509 | O9: =AVERAGEIFS('JN - M'!J:J,'JN - M'!$B:$B,">="&EDATE('JN - Q'!$B9,-2),'JN - M'!$B:$B,"<="&EOMONTH('JN - Q'!$B9,0)) -> 7.6802896 | S9: =(H9/H5-1)*100+2 -> 6.1609511
B10: 29921 | C10: ='CDM - Q'!M139 -> 295284.72 | G10: =AVERAGEIFS('JN - M'!D:D,'JN - M'!$B:$B,">="&EDATE('JN - Q'!$B10,-2),'JN - M'!$B:$B,"<="&EOMONTH('JN - Q'!$B10,0)) -> 85.32145 | H10: =AVERAGEIFS('JN - M'!E:E,'JN - M'!$B:$B,">="&EDATE('JN - Q'!$B10,-2),'JN - M'!$B:$B,"<="&EOMONTH('JN - Q'!$B10,0)) -> 85.349168 | I10: =AVERAGEIFS('JN - M'!F:F,'JN - M'!$B:$B,">="&EDATE('JN - Q'!$B10,-2),'JN - M'!$B:$B,"<="&EOMONTH('JN - Q'!$B10,0)) -> 85.349168 | J10: =AVERAGEIFS('JN - M'!K:K,'JN - M'!$B:$B,">="&EDATE('JN - Q'!$B10,-2),'JN - M'!$B:$B,"<="&EOMONTH('JN - Q'!$B10,0)) -> 2.2174355 | K10: =K11*S10/S11 -> 3.1427208 | L10: 0 | N10: =AVERAGEIFS('JN - M'!I:I,'JN - M'!$B:$B,">="&EDATE('JN - Q'!$B10,-2),'JN - M'!$B:$B,"<="&EOMONTH('JN - Q'!$B10,0)) -> 6.8502667 | O10: =AVERAGEIFS('JN - M'!J:J,'JN - M'!$B:$B,">="&EDATE('JN - Q'!$B10,-2),'JN - M'!$B:$B,"<="&EOMONTH('JN - Q'!$B10,0)) -> 7.2559313 | S10: =(H10/H6-1)*100+2 -> 5.963964
A11: 1982 | B11: 30011 | C11: ='CDM - Q'!M140 -> 299809.96 | G11: =AVERAGEIFS('JN - M'!D:D,'JN - M'!$B:$B,">="&EDATE('JN - Q'!$B11,-2),'JN - M'!$B:$B,"<="&EOMONTH('JN - Q'!$B11,0)) -> 85.813063 | H11: =AVERAGEIFS('JN - M'!E:E,'JN - M'!$B:$B,">="&EDATE('JN - Q'!$B11,-2),'JN - M'!$B:$B,"<="&EOMONTH('JN - Q'!$B11,0)) -> 85.12729 | I11: =AVERAGEIFS('JN - M'!F:F,'JN - M'!$B:$B,">="&EDATE('JN - Q'!$B11,-2),'JN - M'!$B:$B,"<="&EOMONTH('JN - Q'!$B11,0)) -> 85.12729 | J11: =AVERAGEIFS('JN - M'!K:K,'JN - M'!$B:$B,">="&EDATE('JN - Q'!$B11,-2),'JN - M'!$B:$B,"<="&EOMONTH('JN - Q'!$B11,0)) -> 2.2333783 | K11: =K12*S11/S12 -> 2.8775114 | L11: 0 | N11: =AVERAGEIFS('JN - M'!I:I,'JN - M'!$B:$B,">="&EDATE('JN - Q'!$B11,-2),'JN - M'!$B:$B,"<="&EOMONTH('JN - Q'!$B11,0)) -> 6.6092333 | O11: =AVERAGEIFS('JN - M'!J:J,'JN - M'!$B:$B,">="&EDATE('JN - Q'!$B11,-2),'JN - M'!$B:$B,"<="&EOMONTH('JN - Q'!$B11,0)) -> 7.0006242 | S11: =(H11/H7-1)*100+2 -> 5.4606742
B12: 30103 | C12: ='CDM - Q'!M141 -> 301868.35 | G12: =AVERAGEIFS('JN - M'!D:D,'JN - M'!$B:$B,">="&EDATE('JN - Q'!$B12,-2),'JN - M'!$B:$B,"<="&EOMONTH('JN - Q'!$B12,0)) -> 86.22609 | H12: =AVERAGEIFS('JN - M'!E:E,'JN - M'!$B:$B,">="&EDATE('JN - Q'!$B12,-2),'JN - M'!$B:$B,"<="&EOMONTH('JN - Q'!$B12,0)) -> 86.310641 | I12: =AVERAGEIFS('JN - M'!F:F,'JN - M'!$B:$B,">="&EDATE('JN - Q'!$B12,-2),'JN - M'!$B:$B,"<="&EOMONTH('JN - Q'!$B12,0)) -> 86.310641 | J12: =AVERAGEIFS('JN - M'!K:K,'JN - M'!$B:$B,">="&EDATE('JN - Q'!$B12,-2),'JN - M'!$B:$B,"<="&EOMONTH('JN - Q'!$B12,0)) -> 2.3421579 | K12: =K13*S12/S13 -> 2.6591866 | L12: 0 | N12: =AVERAGEIFS('JN - M'!I:I,'JN - M'!$B:$B,">="&EDATE('JN - Q'!$B12,-2),'JN - M'!$B:$B,"<="&EOMONTH('JN - Q'!$B12,0)) -> 7.1722333 | O12: =AVERAGEIFS('JN - M'!J:J,'JN - M'!$B:$B,">="&EDATE('JN - Q'!$B12,-2),'JN - M'!$B:$B,"<="&EOMONTH('JN - Q'!$B12,0)) -> 7.5969644 | S12: =(H12/H8-1)*100+2 -> 5.0463576
B13: 30195 | C13: ='CDM - Q'!M142 -> 303187.53 | G13: =AVERAGEIFS('JN - M'!D:D,'JN - M'!$B:$B,">="&EDATE('JN - Q'!$B13,-2),'JN - M'!$B:$B,"<="&EOMONTH('JN - Q'!$B13,0)) -> 86.96563 | H13: =AVERAGEIFS('JN - M'!E:E,'JN - M'!$B:$B,">="&EDATE('JN - Q'!$B13,-2),'JN - M'!$B:$B,"<="&EOMONTH('JN - Q'!$B13,0)) -> 86.606478 | I13: =AVERAGEIFS('JN - M'!F:F,'JN - M'!$B:$B,">="&EDATE('JN - Q'!$B13,-2),'JN - M'!$B:$B,"<="&EOMONTH('JN - Q'!$B13,0)) -> 86.606478 | J13: =AVERAGEIFS('JN - M'!K:K,'JN - M'!$B:$B,">="&EDATE('JN - Q'!$B13,-2),'JN - M'!$B:$B,"<="&EOMONTH('JN - Q'!$B13,0)) -> 2.3711765 | K13: =K14*S13/S14 -> 2.5343646 | L13: 0 | N13: =AVERAGEIFS('JN - M'!I:I,'JN - M'!$B:$B,">="&EDATE('JN - Q'!$B13,-2),'JN - M'!$B:$B,"<="&EOMONTH('JN - Q'!$B13,0)) -> 7.1183 | O13: =AVERAGEIFS('JN - M'!J:J,'JN - M'!$B:$B,">="&EDATE('JN - Q'!$B13,-2),'JN - M'!$B:$B,"<="&EOMONTH('JN - Q'!$B13,0)) -> 7.5398372 | S13: =(H13/H9-1)*100+2 -> 4.809482
B14: 30286 | C14: ='CDM - Q'!M143 -> 307400.63 | G14: =AVERAGEIFS('JN - M'!D:D,'JN - M'!$B:$B,">="&EDATE('JN - Q'!$B14,-2),'JN - M'!$B:$B,"<="&EOMONTH('JN - Q'!$B14,0)) -> 87.572005 | H14: =AVERAGEIFS('JN - M'!E:E,'JN - M'!$B:$B,">="&EDATE('JN - Q'!$B14,-2),'JN - M'!$B:$B,"<="&EOMONTH('JN - Q'!$B14,0)) -> 87.567951 | I14: =AVERAGEIFS('JN - M'!F:F,'JN - M'!$B:$B,">="&EDATE('JN - Q'!$B14,-2),'JN - M'!$B:$B,"<="&EOMONTH('JN - Q'!$B14,0)) -> 87.567951 | J14: =AVERAGEIFS('JN - M'!K:K,'JN - M'!$B:$B,">="&EDATE('JN - Q'!$B14,-2),'JN - M'!$B:$B,"<="&EOMONTH('JN - Q'!$B14,0)) -> 2.4610027 | K14: =K15*S14/S15 -> 2.423795 | L14: 0 | N14: =AVERAGEIFS('JN - M'!I:I,'JN - M'!$B:$B,">="&EDATE('JN - Q'!$B14,-2),'JN - M'!$B:$B,"<="&EOMONTH('JN - Q'!$B14,0)) -> 6.8412333 | O14: =AVERAGEIFS('JN - M'!J:J,'JN - M'!$B:$B,">="&EDATE('JN - Q'!$B14,-2),'JN - M'!$B:$B,"<="&EOMONTH('JN - Q'!$B14,0)) -> 7.246363 | S14: =(H14/H10-1)*100+2 -> 4.5996534
A15: 1983 | B15: 30376 | C15: ='CDM - Q'!M144 -> 307594.48 | G15: =AVERAGEIFS('JN - M'!D:D,'JN - M'!$B:$B,">="&EDATE('JN - Q'!$B15,-2),'JN - M'!$B:$B,"<="&EOMONTH('JN - Q'!$B15,0)) -> 87.740424 | H15: =AVERAGEIFS('JN - M'!E:E,'JN - M'!$B:$B,">="&EDATE('JN - Q'!$B15,-2),'JN - M'!$B:$B,"<="&EOMONTH('JN - Q'!$B15,0)) -> 87.124194 | I15: =AVERAGEIFS('JN - M'!F:F,'JN - M'!$B:$B,">="&EDATE('JN - Q'!$B15,-2),'JN - M'!$B:$B,"<="&EOMONTH('JN - Q'!$B15,0)) -> 87.124194 | J15: =AVERAGEIFS('JN - M'!K:K,'JN - M'!$B:$B,">="&EDATE('JN - Q'!$B15,-2),'JN - M'!$B:$B,"<="&EOMONTH('JN - Q'!$B15,0)) -> 2.6717197 | K15: =K16*S15/S16 -> 2.2900193 | L15: 0 | N15: =AVERAGEIFS('JN - M'!I:I,'JN - M'!$B:$B,">="&EDATE('JN - Q'!$B15,-2),'JN - M'!$B:$B,"<="&EOMONTH('JN - Q'!$B15,0)) -> 6.6356667 | O15: =AVERAGEIFS('JN - M'!J:J,'JN - M'!$B:$B,">="&EDATE('JN - Q'!$B15,-2),'JN - M'!$B:$B,"<="&EOMONTH('JN - Q'!$B15,0)) -> 7.0286229 | S15: =(H15/H11-1)*100+2 -> 4.3457863
B16: 30468 | C16: ='CDM - Q'!M145 -> 309907.44 | G16: =AVERAGEIFS('JN - M'!D:D,'JN - M'!$B:$B,">="&EDATE('JN - Q'!$B16,-2),'JN - M'!$B:$B,"<="&EOMONTH('JN - Q'!$B16,0)) -> 87.943773 | H16: =AVERAGEIFS('JN - M'!E:E,'JN - M'!$B:$B,">="&EDATE('JN - Q'!$B16,-2),'JN - M'!$B:$B,"<="&EOMONTH('JN - Q'!$B16,0)) -> 88.344525 | I16: =AVERAGEIFS('JN - M'!F:F,'JN - M'!$B:$B,">="&EDATE('JN - Q'!$B16,-2),'JN - M'!$B:$B,"<="&EOMONTH('JN - Q'!$B16,0)) -> 88.344525 | J16: =AVERAGEIFS('JN - M'!K:K,'JN - M'!$B:$B,">="&EDATE('JN - Q'!$B16,-2),'JN - M'!$B:$B,"<="&EOMONTH('JN - Q'!$B16,0)) -> 2.6450835 | K16: =K17*S16/S17 -> 2.2956489 | L16: 0 | N16: =AVERAGEIFS('JN - M'!I:I,'JN - M'!$B:$B,">="&EDATE('JN - Q'!$B16,-2),'JN - M'!$B:$B,"<="&EOMONTH('JN - Q'!$B16,0)) -> 6.1909333 | O16: =AVERAGEIFS('JN - M'!J:J,'JN - M'!$B:$B,">="&EDATE('JN - Q'!$B16,-2),'JN - M'!$B:$B,"<="&EOMONTH('JN - Q'!$B16,0)) -> 6.557553 | S16: =(H16/H12-1)*100+2 -> 4.3564696
B17: 30560 | C17: ='CDM - Q'!M146 -> 314544.44 | G17: =AVERAGEIFS('JN - M'!D:D,'JN - M'!$B:$B,">="&EDATE('JN - Q'!$B17,-2),'JN - M'!$B:$B,"<="&EOMONTH('JN - Q'!$B17,0)) -> 88.30048 | H17: =AVERAGEIFS('JN - M'!E:E,'JN - M'!$B:$B,">="&EDATE('JN - Q'!$B17,-2),'JN - M'!$B:$B,"<="&EOMONTH('JN - Q'!$B17,0)) -> 88.455464 | I17: =AVERAGEIFS('JN - M'!F:F,'JN - M'!$B:$B,">="&EDATE('JN - Q'!$B17,-2),'JN - M'!$B:$B,"<="&EOMONTH('JN - Q'!$B17,0)) -> 88.455464 | J17: =AVERAGEIFS('JN - M'!K:K,'JN - M'!$B:$B,">="&EDATE('JN - Q'!$B17,-2),'JN - M'!$B:$B,"<="&EOMONTH('JN - Q'!$B17,0)) -> 2.6748134 | K17: =K18*S17/S18 -> 2.1789069 | L17: 0 | N17: =AVERAGEIFS('JN - M'!I:I,'JN - M'!$B:$B,">="&EDATE('JN - Q'!$B17,-2),'JN - M'!$B:$B,"<="&EOMONTH('JN - Q'!$B17,0)) -> 6.4587667 | O17: =AVERAGEIFS('JN - M'!J:J,'JN - M'!$B:$B,">="&EDATE('JN - Q'!$B17,-2),'JN - M'!$B:$B,"<="&EOMONTH('JN - Q'!$B17,0)) -> 6.8412471 | S17: =(H17/H13-1)*100+2 -> 4.1349274
B18: 30651 | C18: ='CDM - Q'!M147 -> 317164.99 | G18: =AVERAGEIFS('JN - M'!D:D,'JN - M'!$B:$B,">="&EDATE('JN - Q'!$B18,-2),'JN - M'!$B:$B,"<="&EOMONTH('JN - Q'!$B18,0)) -> 89.007704 | H18: =AVERAGEIFS('JN - M'!E:E,'JN - M'!$B:$B,">="&EDATE('JN - Q'!$B18,-2),'JN - M'!$B:$B,"<="&EOMONTH('JN - Q'!$B18,0)) -> 89.527875 | I18: =AVERAGEIFS('JN - M'!F:F,'JN - M'!$B:$B,">="&EDATE('JN - Q'!$B18,-2),'JN - M'!$B:$B,"<="&EOMONTH('JN - Q'!$B18,0)) -> 89.527875 | J18: =AVERAGEIFS('JN - M'!K:K,'JN - M'!$B:$B,">="&EDATE('JN - Q'!$B18,-2),'JN - M'!$B:$B,"<="&EOMONTH('JN - Q'!$B18,0)) -> 2.621624 | K18: =K19*S18/S19 -> 2.2333138 | L18: 0 | N18: =AVERAGEIFS('JN - M'!I:I,'JN - M'!$B:$B,">="&EDATE('JN - Q'!$B18,-2),'JN - M'!$B:$B,"<="&EOMONTH('JN - Q'!$B18,0)) -> 6.2836667 | O18: =AVERAGEIFS('JN - M'!J:J,'JN - M'!$B:$B,">="&EDATE('JN - Q'!$B18,-2),'JN - M'!$B:$B,"<="&EOMONTH('JN - Q'!$B18,0)) -> 6.6557779 | S18: =(H18/H14-1)*100+2 -> 4.2381757
A19: 1984 | B19: 30742 | C19: ='CDM - Q'!M148 -> 320817.71 | G19: =AVERAGEIFS('JN - M'!D:D,'JN - M'!$B:$B,">="&EDATE('JN - Q'!$B19,-2),'JN - M'!$B:$B,"<="&EOMONTH('JN - Q'!$B19,0)) -> 89.334208 | H19: =AVERAGEIFS('JN - M'!E:E,'JN - M'!$B:$B,">="&EDATE('JN - Q'!$B19,-2),'JN - M'!$B:$B,"<="&EOMONTH('JN - Q'!$B19,0)) -> 89.305997 | I19: =AVERAGEIFS('JN - M'!F:F,'JN - M'!$B:$B,">="&EDATE('JN - Q'!$B19,-2),'JN - M'!$B:$B,"<="&EOMONTH('JN - Q'!$B19,0)) -> 89.305997 | J19: =AVERAGEIFS('JN - M'!K:K,'JN - M'!$B:$B,">="&EDATE('JN - Q'!$B19,-2),'JN - M'!$B:$B,"<="&EOMONTH('JN - Q'!$B19,0)) -> 2.7405279 | K19: =K20*S19/S20 -> 2.3735192 | L19: 0 | N19: =AVERAGEIFS('JN - M'!I:I,'JN - M'!$B:$B,">="&EDATE('JN - Q'!$B19,-2),'JN - M'!$B:$B,"<="&EOMONTH('JN - Q'!$B19,0)) -> 6.1817667 | O19: =AVERAGEIFS('JN - M'!J:J,'JN - M'!$B:$B,">="&EDATE('JN - Q'!$B19,-2),'JN - M'!$B:$B,"<="&EOMONTH('JN - Q'!$B19,0)) -> 6.5478435 | S19: =(H19/H15-1)*100+2 -> 4.5042445
B20: 30834 | C20: ='CDM - Q'!M149 -> 325676.25 | G20: =AVERAGEIFS('JN - M'!D:D,'JN - M'!$B:$B,">="&EDATE('JN - Q'!$B20,-2),'JN - M'!$B:$B,"<="&EOMONTH('JN - Q'!$B20,0)) -> 89.833273 | H20: =AVERAGEIFS('JN - M'!E:E,'JN - M'!$B:$B,">="&EDATE('JN - Q'!$B20,-2),'JN - M'!$B:$B,"<="&EOMONTH('JN - Q'!$B20,0)) -> 90.526327 | I20: =AVERAGEIFS('JN - M'!F:F,'JN - M'!$B:$B,">="&EDATE('JN - Q'!$B20,-2),'JN - M'!$B:$B,"<="&EOMONTH('JN - Q'!$B20,0)) -> 90.526327 | J20: =AVERAGEIFS('JN - M'!K:K,'JN - M'!$B:$B,">="&EDATE('JN - Q'!$B20,-2),'JN - M'!$B:$B,"<="&EOMONTH('JN - Q'!$B20,0)) -> 2.7143292 | K20: =K21*S20/S21 -> 2.3552909 | L20: 0 | N20: =AVERAGEIFS('JN - M'!I:I,'JN - M'!$B:$B,">="&EDATE('JN - Q'!$B20,-2),'JN - M'!$B:$B,"<="&EOMONTH('JN - Q'!$B20,0)) -> 5.8443 | O20: =AVERAGEIFS('JN - M'!J:J,'JN - M'!$B:$B,">="&EDATE('JN - Q'!$B20,-2),'JN - M'!$B:$B,"<="&EOMONTH('JN - Q'!$B20,0)) -> 6.1903925 | S20: =(H20/H16-1)*100+2 -> 4.4696526
B21: 30926 | C21: ='CDM - Q'!M150 -> 329656.23 | G21: =AVERAGEIFS('JN - M'!D:D,'JN - M'!$B:$B,">="&EDATE('JN - Q'!$B21,-2),'JN - M'!$B:$B,"<="&EOMONTH('JN - Q'!$B21,0)) -> 90.242485 | H21: =AVERAGEIFS('JN - M'!E:E,'JN - M'!$B:$B,">="&EDATE('JN - Q'!$B21,-2),'JN - M'!$B:$B,"<="&EOMONTH('JN - Q'!$B21,0)) -> 90.637267 | I21: =AVERAGEIFS('JN - M'!F:F,'JN - M'!$B:$B,">="&EDATE('JN - Q'!$B21,-2),'JN - M'!$B:$B,"<="&EOMONTH('JN - Q'!$B21,0)) -> 90.637267 | J21: =AVERAGEIFS('JN - M'!K:K,'JN - M'!$B:$B,">="&EDATE('JN - Q'!$B21,-2),'JN - M'!$B:$B,"<="&EOMONTH('JN - Q'!$B21,0)) -> 2.7312395 | K21: =K22*S21/S22 -> 2.3536587 | L21: 0 | N21: =AVERAGEIFS('JN - M'!I:I,'JN - M'!$B:$B,">="&EDATE('JN - Q'!$B21,-2),'JN - M'!$B:$B,"<="&EOMONTH('JN - Q'!$B21,0)) -> 6.1527667 | O21: =AVERAGEIFS('JN - M'!J:J,'JN - M'!$B:$B,">="&EDATE('JN - Q'!$B21,-2),'JN - M'!$B:$B,"<="&EOMONTH('JN - Q'!$B21,0)) -> 6.5171262 | S21: =(H21/H17-1)*100+2 -> 4.4665552
B22: 31017 | C22: ='CDM - Q'!M151 -> 330225.23 | G22: =AVERAGEIFS('JN - M'!D:D,'JN - M'!$B:$B,">="&EDATE('JN - Q'!$B22,-2),'JN - M'!$B:$B,"<="&EOMONTH('JN - Q'!$B22,0)) -> 91.046593 | H22: =AVERAGEIFS('JN - M'!E:E,'JN - M'!$B:$B,">="&EDATE('JN - Q'!$B22,-2),'JN - M'!$B:$B,"<="&EOMONTH('JN - Q'!$B22,0)) -> 91.820617 | I22: =AVERAGEIFS('JN - M'!F:F,'JN - M'!$B:$B,">="&EDATE('JN - Q'!$B22,-2),'JN - M'!$B:$B,"<="&EOMONTH('JN - Q'!$B22,0)) -> 91.820617 | J22: =AVERAGEIFS('JN - M'!K:K,'JN - M'!$B:$B,">="&EDATE('JN - Q'!$B22,-2),'JN - M'!$B:$B,"<="&EOMONTH('JN - Q'!$B22,0)) -> 2.6796846 | K22: =K23*S22/S23 -> 2.4033872 | L22: 0 | N22: =AVERAGEIFS('JN - M'!I:I,'JN - M'!$B:$B,">="&EDATE('JN - Q'!$B22,-2),'JN - M'!$B:$B,"<="&EOMONTH('JN - Q'!$B22,0)) -> 6.2211 | O22: =AVERAGEIFS('JN - M'!J:J,'JN - M'!$B:$B,">="&EDATE('JN - Q'!$B22,-2),'JN - M'!$B:$B,"<="&EOMONTH('JN - Q'!$B22,0)) -> 6.5895061 | S22: =(H22/H18-1)*100+2 -> 4.5609252
A23: 1985 | B23: 31107 | C23: ='CDM - Q'!M152 -> 338317.63 | G23: =AVERAGEIFS('JN - M'!D:D,'JN - M'!$B:$B,">="&EDATE('JN - Q'!$B23,-2),'JN - M'!$B:$B,"<="&EOMONTH('JN - Q'!$B23,0)) -> 91.480649 | H23: =AVERAGEIFS('JN - M'!E:E,'JN - M'!$B:$B,">="&EDATE('JN - Q'!$B23,-2),'JN - M'!$B:$B,"<="&EOMONTH('JN - Q'!$B23,0)) -> 91.746658 | I23: =AVERAGEIFS('JN - M'!F:F,'JN - M'!$B:$B,">="&EDATE('JN - Q'!$B23,-2),'JN - M'!$B:$B,"<="&EOMONTH('JN - Q'!$B23,0)) -> 91.746658 | J23: =AVERAGEIFS('JN - M'!K:K,'JN - M'!$B:$B,">="&EDATE('JN - Q'!$B23,-2),'JN - M'!$B:$B,"<="&EOMONTH('JN - Q'!$B23,0)) -> 2.5623958 | K23: =K24*S23/S24 -> 2.4940197 | L23: 0 | N23: =AVERAGEIFS('JN - M'!I:I,'JN - M'!$B:$B,">="&EDATE('JN - Q'!$B23,-2),'JN - M'!$B:$B,"<="&EOMONTH('JN - Q'!$B23,0)) -> 6.2487333 | O23: =AVERAGEIFS('JN - M'!J:J,'JN - M'!$B:$B,">="&EDATE('JN - Q'!$B23,-2),'JN - M'!$B:$B,"<="&EOMONTH('JN - Q'!$B23,0)) -> 6.6187759 | S23: =(H23/H19-1)*100+2 -> 4.7329193
B24: 31199 | C24: ='CDM - Q'!M153 -> 345168.39 | G24: =AVERAGEIFS('JN - M'!D:D,'JN - M'!$B:$B,">="&EDATE('JN - Q'!$B24,-2),'JN - M'!$B:$B,"<="&EOMONTH('JN - Q'!$B24,0)) -> 91.813508 | H24: =AVERAGEIFS('JN - M'!E:E,'JN - M'!$B:$B,">="&EDATE('JN - Q'!$B24,-2),'JN - M'!$B:$B,"<="&EOMONTH('JN - Q'!$B24,0)) -> 92.671151 | I24: =AVERAGEIFS('JN - M'!F:F,'JN - M'!$B:$B,">="&EDATE('JN - Q'!$B24,-2),'JN - M'!$B:$B,"<="&EOMONTH('JN - Q'!$B24,0)) -> 92.671151 | J24: =AVERAGEIFS('JN - M'!K:K,'JN - M'!$B:$B,">="&EDATE('JN - Q'!$B24,-2),'JN - M'!$B:$B,"<="&EOMONTH('JN - Q'!$B24,0)) -> 2.5467524 | K24: =K25*S24/S25 -> 2.3024 | L24: 0 | N24: =AVERAGEIFS('JN - M'!I:I,'JN - M'!$B:$B,">="&EDATE('JN - Q'!$B24,-2),'JN - M'!$B:$B,"<="&EOMONTH('JN - Q'!$B24,0)) -> 6.0685667 | O24: =AVERAGEIFS('JN - M'!J:J,'JN - M'!$B:$B,">="&EDATE('JN - Q'!$B24,-2),'JN - M'!$B:$B,"<="&EOMONTH('JN - Q'!$B24,0)) -> 6.4279399 | S24: =(H24/H20-1)*100+2 -> 4.369281
B25: 31291 | C25: ='CDM - Q'!M154 -> 349685.13 | G25: =AVERAGEIFS('JN - M'!D:D,'JN - M'!$B:$B,">="&EDATE('JN - Q'!$B25,-2),'JN - M'!$B:$B,"<="&EOMONTH('JN - Q'!$B25,0)) -> 92.110872 | H25: =AVERAGEIFS('JN - M'!E:E,'JN - M'!$B:$B,">="&EDATE('JN - Q'!$B25,-2),'JN - M'!$B:$B,"<="&EOMONTH('JN - Q'!$B25,0)) -> 92.819069 | I25: =AVERAGEIFS('JN - M'!F:F,'JN - M'!$B:$B,">="&EDATE('JN - Q'!$B25,-2),'JN - M'!$B:$B,"<="&EOMONTH('JN - Q'!$B25,0)) -> 92.819069 | J25: =AVERAGEIFS('JN - M'!K:K,'JN - M'!$B:$B,">="&EDATE('JN - Q'!$B25,-2),'JN - M'!$B:$B,"<="&EOMONTH('JN - Q'!$B25,0)) -> 2.5862001 | K25: =K26*S25/S26 -> 2.3223713 | L25: 0 | N25: =AVERAGEIFS('JN - M'!I:I,'JN - M'!$B:$B,">="&EDATE('JN - Q'!$B25,-2),'JN - M'!$B:$B,"<="&EOMONTH('JN - Q'!$B25,0)) -> 6.2540333 | O25: =AVERAGEIFS('JN - M'!J:J,'JN - M'!$B:$B,">="&EDATE('JN - Q'!$B25,-2),'JN - M'!$B:$B,"<="&EOMONTH('JN - Q'!$B25,0)) -> 6.6243897 | S25: =(H25/H21-1)*100+2 -> 4.4071807
B26: 31382 | C26: ='CDM - Q'!M155 -> 354330.43 | G26: =AVERAGEIFS('JN - M'!D:D,'JN - M'!$B:$B,">="&EDATE('JN - Q'!$B26,-2),'JN - M'!$B:$B,"<="&EOMONTH('JN - Q'!$B26,0)) -> 92.297282 | H26: =AVERAGEIFS('JN - M'!E:E,'JN - M'!$B:$B,">="&EDATE('JN - Q'!$B26,-2),'JN - M'!$B:$B,"<="&EOMONTH('JN - Q'!$B26,0)) -> 93.410745 | I26: =AVERAGEIFS('JN - M'!F:F,'JN - M'!$B:$B,">="&EDATE('JN - Q'!$B26,-2),'JN - M'!$B:$B,"<="&EOMONTH('JN - Q'!$B26,0)) -> 93.410745 | J26: =AVERAGEIFS('JN - M'!K:K,'JN - M'!$B:$B,">="&EDATE('JN - Q'!$B26,-2),'JN - M'!$B:$B,"<="&EOMONTH('JN - Q'!$B26,0)) -> 2.7792051 | K26: =K27*S26/S27 -> 1.9664656 | L26: 0 | N26: =AVERAGEIFS('JN - M'!I:I,'JN - M'!$B:$B,">="&EDATE('JN - Q'!$B26,-2),'JN - M'!$B:$B,"<="&EOMONTH('JN - Q'!$B26,0)) -> 7.2818333 | O26: =AVERAGEIFS('JN - M'!J:J,'JN - M'!$B:$B,">="&EDATE('JN - Q'!$B26,-2),'JN - M'!$B:$B,"<="&EOMONTH('JN - Q'!$B26,0)) -> 7.7130548 | S26: =(H26/H22-1)*100+2 -> 3.7317761
A27: 1986 | B27: 31472 | C27: ='CDM - Q'!M156 -> 355739.42 | G27: =AVERAGEIFS('JN - M'!D:D,'JN - M'!$B:$B,">="&EDATE('JN - Q'!$B27,-2),'JN - M'!$B:$B,"<="&EOMONTH('JN - Q'!$B27,0)) -> 92.755167 | H27: =AVERAGEIFS('JN - M'!E:E,'JN - M'!$B:$B,">="&EDATE('JN - Q'!$B27,-2),'JN - M'!$B:$B,"<="&EOMONTH('JN - Q'!$B27,0)) -> 93.336785 | I27: =AVERAGEIFS('JN - M'!F:F,'JN - M'!$B:$B,">="&EDATE('JN - Q'!$B27,-2),'JN - M'!$B:$B,"<="&EOMONTH('JN - Q'!$B27,0)) -> 93.336785 | J27: =AVERAGEIFS('JN - M'!K:K,'JN - M'!$B:$B,">="&EDATE('JN - Q'!$B27,-2),'JN - M'!$B:$B,"<="&EOMONTH('JN - Q'!$B27,0)) -> 2.6757036 | K27: =K28*S27/S28 -> 1.9672013 | L27: 0 | N27: =AVERAGEIFS('JN - M'!I:I,'JN - M'!$B:$B,">="&EDATE('JN - Q'!$B27,-2),'JN - M'!$B:$B,"<="&EOMONTH('JN - Q'!$B27,0)) -> 6.053 | O27: =AVERAGEIFS('JN - M'!J:J,'JN - M'!$B:$B,">="&EDATE('JN - Q'!$B27,-2),'JN - M'!$B:$B,"<="&EOMONTH('JN - Q'!$B27,0)) -> 6.4114514 | S27: =(H27/H23-1)*100+2 -> 3.7331721
B28: 31564 | C28: ='CDM - Q'!M157 -> 354865.4 | G28: =AVERAGEIFS('JN - M'!D:D,'JN - M'!$B:$B,">="&EDATE('JN - Q'!$B28,-2),'JN - M'!$B:$B,"<="&EOMONTH('JN - Q'!$B28,0)) -> 92.843616 | H28: =AVERAGEIFS('JN - M'!E:E,'JN - M'!$B:$B,">="&EDATE('JN - Q'!$B28,-2),'JN - M'!$B:$B,"<="&EOMONTH('JN - Q'!$B28,0)) -> 94.224298 | I28: =AVERAGEIFS('JN - M'!F:F,'JN - M'!$B:$B,">="&EDATE('JN - Q'!$B28,-2),'JN - M'!$B:$B,"<="&EOMONTH('JN - Q'!$B28,0)) -> 94.224298 | J28: =AVERAGEIFS('JN - M'!K:K,'JN - M'!$B:$B,">="&EDATE('JN - Q'!$B28,-2),'JN - M'!$B:$B,"<="&EOMONTH('JN - Q'!$B28,0)) -> 2.7539109 | K28: =K29*S28/S29 -> 1.9370626 | L28: 0 | N28: =AVERAGEIFS('JN - M'!I:I,'JN - M'!$B:$B,">="&EDATE('JN - Q'!$B28,-2),'JN - M'!$B:$B,"<="&EOMONTH('JN - Q'!$B28,0)) -> 4.4357333 | O28: =AVERAGEIFS('JN - M'!J:J,'JN - M'!$B:$B,">="&EDATE('JN - Q'!$B28,-2),'JN - M'!$B:$B,"<="&EOMONTH('JN - Q'!$B28,0)) -> 4.6984122 | S28: =(H28/H24-1)*100+2 -> 3.6759777
B29: 31656 | C29: ='CDM - Q'!M158 -> 356944.16 | G29: =AVERAGEIFS('JN - M'!D:D,'JN - M'!$B:$B,">="&EDATE('JN - Q'!$B29,-2),'JN - M'!$B:$B,"<="&EOMONTH('JN - Q'!$B29,0)) -> 92.623869 | H29: =AVERAGEIFS('JN - M'!E:E,'JN - M'!$B:$B,">="&EDATE('JN - Q'!$B29,-2),'JN - M'!$B:$B,"<="&EOMONTH('JN - Q'!$B29,0)) -> 94.224298 | I29: =AVERAGEIFS('JN - M'!F:F,'JN - M'!$B:$B,">="&EDATE('JN - Q'!$B29,-2),'JN - M'!$B:$B,"<="&EOMONTH('JN - Q'!$B29,0)) -> 94.224298 | J29: =AVERAGEIFS('JN - M'!K:K,'JN - M'!$B:$B,">="&EDATE('JN - Q'!$B29,-2),'JN - M'!$B:$B,"<="&EOMONTH('JN - Q'!$B29,0)) -> 2.8438701 | K29: =K30*S29/S30 -> 1.8516788 | L29: 0 | N29: =AVERAGEIFS('JN - M'!I:I,'JN - M'!$B:$B,">="&EDATE('JN - Q'!$B29,-2),'JN - M'!$B:$B,"<="&EOMONTH('JN - Q'!$B29,0)) -> 4.5625333 | O29: =AVERAGEIFS('JN - M'!J:J,'JN - M'!$B:$B,">="&EDATE('JN - Q'!$B29,-2),'JN - M'!$B:$B,"<="&EOMONTH('JN - Q'!$B29,0)) -> 4.8327211 | S29: =(H29/H25-1)*100+2 -> 3.5139442
B30: 31747 | C30: ='CDM - Q'!M159 -> 359759.46 | G30: =AVERAGEIFS('JN - M'!D:D,'JN - M'!$B:$B,">="&EDATE('JN - Q'!$B30,-2),'JN - M'!$B:$B,"<="&EOMONTH('JN - Q'!$B30,0)) -> 92.569319 | H30: =AVERAGEIFS('JN - M'!E:E,'JN - M'!$B:$B,">="&EDATE('JN - Q'!$B30,-2),'JN - M'!$B:$B,"<="&EOMONTH('JN - Q'!$B30,0)) -> 94.778994 | I30: =AVERAGEIFS('JN - M'!F:F,'JN - M'!$B:$B,">="&EDATE('JN - Q'!$B30,-2),'JN - M'!$B:$B,"<="&EOMONTH('JN - Q'!$B30,0)) -> 94.778994 | J30: =AVERAGEIFS('JN - M'!K:K,'JN - M'!$B:$B,">="&EDATE('JN - Q'!$B30,-2),'JN - M'!$B:$B,"<="&EOMONTH('JN - Q'!$B30,0)) -> 2.7941754 | K30: =K31*S30/S31 -> 1.8257645 | L30: 0 | N30: =AVERAGEIFS('JN - M'!I:I,'JN - M'!$B:$B,">="&EDATE('JN - Q'!$B30,-2),'JN - M'!$B:$B,"<="&EOMONTH('JN - Q'!$B30,0)) -> 4.1207333 | O30: =AVERAGEIFS('JN - M'!J:J,'JN - M'!$B:$B,">="&EDATE('JN - Q'!$B30,-2),'JN - M'!$B:$B,"<="&EOMONTH('JN - Q'!$B30,0)) -> 4.3647582 | S30: =(H30/H26-1)*100+2 -> 3.4647664
A31: 1987 | B31: 31837 | C31: ='CDM - Q'!M160 -> 359501.42 | G31: =AVERAGEIFS('JN - M'!D:D,'JN - M'!$B:$B,">="&EDATE('JN - Q'!$B31,-2),'JN - M'!$B:$B,"<="&EOMONTH('JN - Q'!$B31,0)) -> 92.616929 | H31: =AVERAGEIFS('JN - M'!E:E,'JN - M'!$B:$B,">="&EDATE('JN - Q'!$B31,-2),'JN - M'!$B:$B,"<="&EOMONTH('JN - Q'!$B31,0)) -> 94.446177 | I31: =AVERAGEIFS('JN - M'!F:F,'JN - M'!$B:$B,">="&EDATE('JN - Q'!$B31,-2),'JN - M'!$B:$B,"<="&EOMONTH('JN - Q'!$B31,0)) -> 94.446177 | J31: =AVERAGEIFS('JN - M'!K:K,'JN - M'!$B:$B,">="&EDATE('JN - Q'!$B31,-2),'JN - M'!$B:$B,"<="&EOMONTH('JN - Q'!$B31,0)) -> 2.9426737 | K31: =K32*S31/S32 -> 1.6802326 | L31: 0 | N31: =AVERAGEIFS('JN - M'!I:I,'JN - M'!$B:$B,">="&EDATE('JN - Q'!$B31,-2),'JN - M'!$B:$B,"<="&EOMONTH('JN - Q'!$B31,0)) -> 3.9980333 | O31: =AVERAGEIFS('JN - M'!J:J,'JN - M'!$B:$B,">="&EDATE('JN - Q'!$B31,-2),'JN - M'!$B:$B,"<="&EOMONTH('JN - Q'!$B31,0)) -> 4.2347921 | S31: =(H31/H27-1)*100+2 -> 3.1885895
B32: 31929 | C32: ='CDM - Q'!M161 -> 367035.11 | G32: =AVERAGEIFS('JN - M'!D:D,'JN - M'!$B:$B,">="&EDATE('JN - Q'!$B32,-2),'JN - M'!$B:$B,"<="&EOMONTH('JN - Q'!$B32,0)) -> 92.88688 | H32: =AVERAGEIFS('JN - M'!E:E,'JN - M'!$B:$B,">="&EDATE('JN - Q'!$B32,-2),'JN - M'!$B:$B,"<="&EOMONTH('JN - Q'!$B32,0)) -> 95.037852 | I32: =AVERAGEIFS('JN - M'!F:F,'JN - M'!$B:$B,">="&EDATE('JN - Q'!$B32,-2),'JN - M'!$B:$B,"<="&EOMONTH('JN - Q'!$B32,0)) -> 95.037852 | J32: =AVERAGEIFS('JN - M'!K:K,'JN - M'!$B:$B,">="&EDATE('JN - Q'!$B32,-2),'JN - M'!$B:$B,"<="&EOMONTH('JN - Q'!$B32,0)) -> 3.0070389 | K32: =K33*S32/S33 -> 1.5088852 | L32: 0 | N32: =AVERAGEIFS('JN - M'!I:I,'JN - M'!$B:$B,">="&EDATE('JN - Q'!$B32,-2),'JN - M'!$B:$B,"<="&EOMONTH('JN - Q'!$B32,0)) -> 3.2817667 | O32: =AVERAGEIFS('JN - M'!J:J,'JN - M'!$B:$B,">="&EDATE('JN - Q'!$B32,-2),'JN - M'!$B:$B,"<="&EOMONTH('JN - Q'!$B32,0)) -> 3.476109 | S32: =(H32/H28-1)*100+2 -> 2.8634223
B33: 32021 | C33: ='CDM - Q'!M162 -> 374376.83 | G33: =AVERAGEIFS('JN - M'!D:D,'JN - M'!$B:$B,">="&EDATE('JN - Q'!$B33,-2),'JN - M'!$B:$B,"<="&EOMONTH('JN - Q'!$B33,0)) -> 93.103929 | H33: =AVERAGEIFS('JN - M'!E:E,'JN - M'!$B:$B,">="&EDATE('JN - Q'!$B33,-2),'JN - M'!$B:$B,"<="&EOMONTH('JN - Q'!$B33,0)) -> 95.074832 | I33: =AVERAGEIFS('JN - M'!F:F,'JN - M'!$B:$B,">="&EDATE('JN - Q'!$B33,-2),'JN - M'!$B:$B,"<="&EOMONTH('JN - Q'!$B33,0)) -> 95.074832 | J33: =AVERAGEIFS('JN - M'!K:K,'JN - M'!$B:$B,">="&EDATE('JN - Q'!$B33,-2),'JN - M'!$B:$B,"<="&EOMONTH('JN - Q'!$B33,0)) -> 2.7532668 | K33: =K34*S33/S34 -> 1.5295662 | L33: 0 | N33: =AVERAGEIFS('JN - M'!I:I,'JN - M'!$B:$B,">="&EDATE('JN - Q'!$B33,-2),'JN - M'!$B:$B,"<="&EOMONTH('JN - Q'!$B33,0)) -> 3.2489333 | O33: =AVERAGEIFS('JN - M'!J:J,'JN - M'!$B:$B,">="&EDATE('JN - Q'!$B33,-2),'JN - M'!$B:$B,"<="&EOMONTH('JN - Q'!$B33,0)) -> 3.4413313 | S33: =(H33/H29-1)*100+2 -> 2.9026688
B34: 32112 | C34: ='CDM - Q'!M163 -> 384016.28 | G34: =AVERAGEIFS('JN - M'!D:D,'JN - M'!$B:$B,">="&EDATE('JN - Q'!$B34,-2),'JN - M'!$B:$B,"<="&EOMONTH('JN - Q'!$B34,0)) -> 93.081721 | H34: =AVERAGEIFS('JN - M'!E:E,'JN - M'!$B:$B,">="&EDATE('JN - Q'!$B34,-2),'JN - M'!$B:$B,"<="&EOMONTH('JN - Q'!$B34,0)) -> 95.444629 | I34: =AVERAGEIFS('JN - M'!F:F,'JN - M'!$B:$B,">="&EDATE('JN - Q'!$B34,-2),'JN - M'!$B:$B,"<="&EOMONTH('JN - Q'!$B34,0)) -> 95.444629 | J34: =AVERAGEIFS('JN - M'!K:K,'JN - M'!$B:$B,">="&EDATE('JN - Q'!$B34,-2),'JN - M'!$B:$B,"<="&EOMONTH('JN - Q'!$B34,0)) -> 2.6737895 | K34: =K35*S34/S35 -> 1.4239826 | L34: 0 | N34: =AVERAGEIFS('JN - M'!I:I,'JN - M'!$B:$B,">="&EDATE('JN - Q'!$B34,-2),'JN - M'!$B:$B,"<="&EOMONTH('JN - Q'!$B34,0)) -> 3.5249667 | O34: =AVERAGEIFS('JN - M'!J:J,'JN - M'!$B:$B,">="&EDATE('JN - Q'!$B34,-2),'JN - M'!$B:$B,"<="&EOMONTH('JN - Q'!$B34,0)) -> 3.733711 | S34: =(H34/H30-1)*100+2 -> 2.702302
A35: 1988 | B35: 32203 | C35: ='CDM - Q'!M164 -> 393183.57 | G35: =AVERAGEIFS('JN - M'!D:D,'JN - M'!$B:$B,">="&EDATE('JN - Q'!$B35,-2),'JN - M'!$B:$B,"<="&EOMONTH('JN - Q'!$B35,0)) -> 93.11523 | H35: =AVERAGEIFS('JN - M'!E:E,'JN - M'!$B:$B,">="&EDATE('JN - Q'!$B35,-2),'JN - M'!$B:$B,"<="&EOMONTH('JN - Q'!$B35,0)) -> 95.037852 | I35: =AVERAGEIFS('JN - M'!F:F,'JN - M'!$B:$B,">="&EDATE('JN - Q'!$B35,-2),'JN - M'!$B:$B,"<="&EOMONTH('JN - Q'!$B35,0)) -> 95.037852 | J35: =AVERAGEIFS('JN - M'!K:K,'JN - M'!$B:$B,">="&EDATE('JN - Q'!$B35,-2),'JN - M'!$B:$B,"<="&EOMONTH('JN - Q'!$B35,0)) -> 2.6941991 | K35: =K36*S35/S36 -> 1.3840219 | L35: 0 | N35: =AVERAGEIFS('JN - M'!I:I,'JN - M'!$B:$B,">="&EDATE('JN - Q'!$B35,-2),'JN - M'!$B:$B,"<="&EOMONTH('JN - Q'!$B35,0)) -> 3.4885667 | O35: =AVERAGEIFS('JN - M'!J:J,'JN - M'!$B:$B,">="&EDATE('JN - Q'!$B35,-2),'JN - M'!$B:$B,"<="&EOMONTH('JN - Q'!$B35,0)) -> 3.6951554 | S35: =(H35/H31-1)*100+2 -> 2.6264683
B36: 32295 | C36: ='CDM - Q'!M165 -> 392609.53 | G36: =AVERAGEIFS('JN - M'!D:D,'JN - M'!$B:$B,">="&EDATE('JN - Q'!$B36,-2),'JN - M'!$B:$B,"<="&EOMONTH('JN - Q'!$B36,0)) -> 93.219632 | H36: =AVERAGEIFS('JN - M'!E:E,'JN - M'!$B:$B,">="&EDATE('JN - Q'!$B36,-2),'JN - M'!$B:$B,"<="&EOMONTH('JN - Q'!$B36,0)) -> 95.740466 | I36: =AVERAGEIFS('JN - M'!F:F,'JN - M'!$B:$B,">="&EDATE('JN - Q'!$B36,-2),'JN - M'!$B:$B,"<="&EOMONTH('JN - Q'!$B36,0)) -> 95.740466 | J36: =AVERAGEIFS('JN - M'!K:K,'JN - M'!$B:$B,">="&EDATE('JN - Q'!$B36,-2),'JN - M'!$B:$B,"<="&EOMONTH('JN - Q'!$B36,0)) -> 2.4840468 | K36: =K37*S36/S37 -> 1.4434785 | L36: 0 | N36: =AVERAGEIFS('JN - M'!I:I,'JN - M'!$B:$B,">="&EDATE('JN - Q'!$B36,-2),'JN - M'!$B:$B,"<="&EOMONTH('JN - Q'!$B36,0)) -> 3.3323667 | O36: =AVERAGEIFS('JN - M'!J:J,'JN - M'!$B:$B,">="&EDATE('JN - Q'!$B36,-2),'JN - M'!$B:$B,"<="&EOMONTH('JN - Q'!$B36,0)) -> 3.5297054 | S36: =(H36/H32-1)*100+2 -> 2.7392996
B37: 32387 | C37: ='CDM - Q'!M166 -> 401368.44 | G37: =AVERAGEIFS('JN - M'!D:D,'JN - M'!$B:$B,">="&EDATE('JN - Q'!$B37,-2),'JN - M'!$B:$B,"<="&EOMONTH('JN - Q'!$B37,0)) -> 93.395413 | H37: =AVERAGEIFS('JN - M'!E:E,'JN - M'!$B:$B,">="&EDATE('JN - Q'!$B37,-2),'JN - M'!$B:$B,"<="&EOMONTH('JN - Q'!$B37,0)) -> 95.666507 | I37: =AVERAGEIFS('JN - M'!F:F,'JN - M'!$B:$B,">="&EDATE('JN - Q'!$B37,-2),'JN - M'!$B:$B,"<="&EOMONTH('JN - Q'!$B37,0)) -> 95.666507 | J37: =AVERAGEIFS('JN - M'!K:K,'JN - M'!$B:$B,">="&EDATE('JN - Q'!$B37,-2),'JN - M'!$B:$B,"<="&EOMONTH('JN - Q'!$B37,0)) -> 2.5203507 | K37: =K38*S37/S38 -> 1.381839 | L37: 0 | N37: =AVERAGEIFS('JN - M'!I:I,'JN - M'!$B:$B,">="&EDATE('JN - Q'!$B37,-2),'JN - M'!$B:$B,"<="&EOMONTH('JN - Q'!$B37,0)) -> 3.7781333 | O37: =AVERAGEIFS('JN - M'!J:J,'JN - M'!$B:$B,">="&EDATE('JN - Q'!$B37,-2),'JN - M'!$B:$B,"<="&EOMONTH('JN - Q'!$B37,0)) -> 4.0018699 | S37: =(H37/H33-1)*100+2 -> 2.6223259
B38: 32478 | C38: ='CDM - Q'!M167 -> 405598.16 | G38: =AVERAGEIFS('JN - M'!D:D,'JN - M'!$B:$B,">="&EDATE('JN - Q'!$B38,-2),'JN - M'!$B:$B,"<="&EOMONTH('JN - Q'!$B38,0)) -> 93.625668 | H38: =AVERAGEIFS('JN - M'!E:E,'JN - M'!$B:$B,">="&EDATE('JN - Q'!$B38,-2),'JN - M'!$B:$B,"<="&EOMONTH('JN - Q'!$B38,0)) -> 96.295162 | I38: =AVERAGEIFS('JN - M'!F:F,'JN - M'!$B:$B,">="&EDATE('JN - Q'!$B38,-2),'JN - M'!$B:$B,"<="&EOMONTH('JN - Q'!$B38,0)) -> 96.295162 | J38: =AVERAGEIFS('JN - M'!K:K,'JN - M'!$B:$B,">="&EDATE('JN - Q'!$B38,-2),'JN - M'!$B:$B,"<="&EOMONTH('JN - Q'!$B38,0)) -> 2.4009921 | K38: =K39*S38/S39 -> 1.5234845 | L38: 0 | N38: =AVERAGEIFS('JN - M'!I:I,'JN - M'!$B:$B,">="&EDATE('JN - Q'!$B38,-2),'JN - M'!$B:$B,"<="&EOMONTH('JN - Q'!$B38,0)) -> 3.8885667 | O38: =AVERAGEIFS('JN - M'!J:J,'JN - M'!$B:$B,">="&EDATE('JN - Q'!$B38,-2),'JN - M'!$B:$B,"<="&EOMONTH('JN - Q'!$B38,0)) -> 4.1188429 | S38: =(H38/H34-1)*100+2 -> 2.8911275
A39: 1989 | B39: 32568 | C39: ='CDM - Q'!M168 -> 416541.36 | G39: =AVERAGEIFS('JN - M'!D:D,'JN - M'!$B:$B,">="&EDATE('JN - Q'!$B39,-2),'JN - M'!$B:$B,"<="&EOMONTH('JN - Q'!$B39,0)) -> 93.925037 | H39: =AVERAGEIFS('JN - M'!E:E,'JN - M'!$B:$B,">="&EDATE('JN - Q'!$B39,-2),'JN - M'!$B:$B,"<="&EOMONTH('JN - Q'!$B39,0)) -> 96.147243 | I39: =AVERAGEIFS('JN - M'!F:F,'JN - M'!$B:$B,">="&EDATE('JN - Q'!$B39,-2),'JN - M'!$B:$B,"<="&EOMONTH('JN - Q'!$B39,0)) -> 96.147243 | J39: =AVERAGEIFS('JN - M'!K:K,'JN - M'!$B:$B,">="&EDATE('JN - Q'!$B39,-2),'JN - M'!$B:$B,"<="&EOMONTH('JN - Q'!$B39,0)) -> 2.3276462 | K39: =K40*S39/S40 -> 1.669022 | L39: 0 | N39: =AVERAGEIFS('JN - M'!I:I,'JN - M'!$B:$B,">="&EDATE('JN - Q'!$B39,-2),'JN - M'!$B:$B,"<="&EOMONTH('JN - Q'!$B39,0)) -> 3.9091633 | O39: =AVERAGEIFS('JN - M'!J:J,'JN - M'!$B:$B,">="&EDATE('JN - Q'!$B39,-2),'JN - M'!$B:$B,"<="&EOMONTH('JN - Q'!$B39,0)) -> 4.1406593 | S39: =(H39/H35-1)*100+2 -> 3.1673152
B40: 32660 | C40: ='CDM - Q'!M169 -> 411102.45 | G40: =AVERAGEIFS('JN - M'!D:D,'JN - M'!$B:$B,">="&EDATE('JN - Q'!$B40,-2),'JN - M'!$B:$B,"<="&EOMONTH('JN - Q'!$B40,0)) -> 92.891018 | H40: =AVERAGEIFS('JN - M'!E:E,'JN - M'!$B:$B,">="&EDATE('JN - Q'!$B40,-2),'JN - M'!$B:$B,"<="&EOMONTH('JN - Q'!$B40,0)) -> 95.644606 | I40: =AVERAGEIFS('JN - M'!F:F,'JN - M'!$B:$B,">="&EDATE('JN - Q'!$B40,-2),'JN - M'!$B:$B,"<="&EOMONTH('JN - Q'!$B40,0)) -> 95.644606 | J40: =AVERAGEIFS('JN - M'!K:K,'JN - M'!$B:$B,">="&EDATE('JN - Q'!$B40,-2),'JN - M'!$B:$B,"<="&EOMONTH('JN - Q'!$B40,0)) -> 2.30018 | K40: =K41*S40/S41 -> 1.0011424 | L40: 0 | N40: =AVERAGEIFS('JN - M'!I:I,'JN - M'!$B:$B,">="&EDATE('JN - Q'!$B40,-2),'JN - M'!$B:$B,"<="&EOMONTH('JN - Q'!$B40,0)) -> 4.3608433 | O40: =AVERAGEIFS('JN - M'!J:J,'JN - M'!$B:$B,">="&EDATE('JN - Q'!$B40,-2),'JN - M'!$B:$B,"<="&EOMONTH('JN - Q'!$B40,0)) -> 4.6190873 | S40: =(H40/H36-1)*100+2 -> 1.8998751
B41: 32752 | C41: ='CDM - Q'!M170 -> 418295.42 | G41: =AVERAGEIFS('JN - M'!D:D,'JN - M'!$B:$B,">="&EDATE('JN - Q'!$B41,-2),'JN - M'!$B:$B,"<="&EOMONTH('JN - Q'!$B41,0)) -> 93.329828 | H41: =AVERAGEIFS('JN - M'!E:E,'JN - M'!$B:$B,">="&EDATE('JN - Q'!$B41,-2),'JN - M'!$B:$B,"<="&EOMONTH('JN - Q'!$B41,0)) -> 95.752314 | I41: =AVERAGEIFS('JN - M'!F:F,'JN - M'!$B:$B,">="&EDATE('JN - Q'!$B41,-2),'JN - M'!$B:$B,"<="&EOMONTH('JN - Q'!$B41,0)) -> 95.752314 | J41: =AVERAGEIFS('JN - M'!K:K,'JN - M'!$B:$B,">="&EDATE('JN - Q'!$B41,-2),'JN - M'!$B:$B,"<="&EOMONTH('JN - Q'!$B41,0)) -> 2.220434 | K41: =K42*S41/S42 -> 1.1011678 | L41: 0 | N41: =AVERAGEIFS('JN - M'!I:I,'JN - M'!$B:$B,">="&EDATE('JN - Q'!$B41,-2),'JN - M'!$B:$B,"<="&EOMONTH('JN - Q'!$B41,0)) -> 5.18326 | O41: =AVERAGEIFS('JN - M'!J:J,'JN - M'!$B:$B,">="&EDATE('JN - Q'!$B41,-2),'JN - M'!$B:$B,"<="&EOMONTH('JN - Q'!$B41,0)) -> 5.4902065 | S41: =(H41/H37-1)*100+2 -> 2.0896942
B42: 32843 | C42: ='CDM - Q'!M171 -> 431255.26 | G42: =AVERAGEIFS('JN - M'!D:D,'JN - M'!$B:$B,">="&EDATE('JN - Q'!$B42,-2),'JN - M'!$B:$B,"<="&EOMONTH('JN - Q'!$B42,0)) -> 93.541555 | H42: =AVERAGEIFS('JN - M'!E:E,'JN - M'!$B:$B,">="&EDATE('JN - Q'!$B42,-2),'JN - M'!$B:$B,"<="&EOMONTH('JN - Q'!$B42,0)) -> 96.398562 | I42: =AVERAGEIFS('JN - M'!F:F,'JN - M'!$B:$B,">="&EDATE('JN - Q'!$B42,-2),'JN - M'!$B:$B,"<="&EOMONTH('JN - Q'!$B42,0)) -> 96.398562 | J42: =AVERAGEIFS('JN - M'!K:K,'JN - M'!$B:$B,">="&EDATE('JN - Q'!$B42,-2),'JN - M'!$B:$B,"<="&EOMONTH('JN - Q'!$B42,0)) -> 2.1863614 | K42: =K43*S42/S43 -> 1.1104862 | L42: 0 | N42: =AVERAGEIFS('JN - M'!I:I,'JN - M'!$B:$B,">="&EDATE('JN - Q'!$B42,-2),'JN - M'!$B:$B,"<="&EOMONTH('JN - Q'!$B42,0)) -> 6.0353667 | O42: =AVERAGEIFS('JN - M'!J:J,'JN - M'!$B:$B,">="&EDATE('JN - Q'!$B42,-2),'JN - M'!$B:$B,"<="&EOMONTH('JN - Q'!$B42,0)) -> 6.3927739 | S42: =(H42/H38-1)*100+2 -> 2.1073777
A43: 1990 | B43: 32933 | C43: ='CDM - Q'!M172 -> 429203.51 | E43: =AVERAGEIFS('JN - M'!G:G,'JN - M'!$B:$B,">="&EDATE('JN - Q'!$B43,-2),'JN - M'!$B:$B,"<="&EOMONTH('JN - Q'!$B43,0)) -> 74.9 | F43: =AVERAGEIFS('JN - M'!H:H,'JN - M'!$B:$B,">="&EDATE('JN - Q'!$B43,-2),'JN - M'!$B:$B,"<="&EOMONTH('JN - Q'!$B43,0)) -> 72.360197 | G43: =AVERAGEIFS('JN - M'!D:D,'JN - M'!$B:$B,">="&EDATE('JN - Q'!$B43,-2),'JN - M'!$B:$B,"<="&EOMONTH('JN - Q'!$B43,0)) -> 94.149231 | H43: =AVERAGEIFS('JN - M'!E:E,'JN - M'!$B:$B,">="&EDATE('JN - Q'!$B43,-2),'JN - M'!$B:$B,"<="&EOMONTH('JN - Q'!$B43,0)) -> 96.398562 | I43: =AVERAGEIFS('JN - M'!F:F,'JN - M'!$B:$B,">="&EDATE('JN - Q'!$B43,-2),'JN - M'!$B:$B,"<="&EOMONTH('JN - Q'!$B43,0)) -> 96.398562 | J43: =AVERAGEIFS('JN - M'!K:K,'JN - M'!$B:$B,">="&EDATE('JN - Q'!$B43,-2),'JN - M'!$B:$B,"<="&EOMONTH('JN - Q'!$B43,0)) -> 2.1027708 | K43: =K44*S43/S44 -> 1.1916428 | L43: 0 | N43: =AVERAGEIFS('JN - M'!I:I,'JN - M'!$B:$B,">="&EDATE('JN - Q'!$B43,-2),'JN - M'!$B:$B,"<="&EOMONTH('JN - Q'!$B43,0)) -> 6.5162633 | O43: =AVERAGEIFS('JN - M'!J:J,'JN - M'!$B:$B,">="&EDATE('JN - Q'!$B43,-2),'JN - M'!$B:$B,"<="&EOMONTH('JN - Q'!$B43,0)) -> 6.9021487 | S43: =(H43/H39-1)*100+2 -> 2.2613891
B44: 33025 | C44: ='CDM - Q'!M173 -> 442740.46 | E44: =AVERAGEIFS('JN - M'!G:G,'JN - M'!$B:$B,">="&EDATE('JN - Q'!$B44,-2),'JN - M'!$B:$B,"<="&EOMONTH('JN - Q'!$B44,0)) -> 72.1 | F44: =AVERAGEIFS('JN - M'!H:H,'JN - M'!$B:$B,">="&EDATE('JN - Q'!$B44,-2),'JN - M'!$B:$B,"<="&EOMONTH('JN - Q'!$B44,0)) -> 74.114893 | G44: =AVERAGEIFS('JN - M'!D:D,'JN - M'!$B:$B,">="&EDATE('JN - Q'!$B44,-2),'JN - M'!$B:$B,"<="&EOMONTH('JN - Q'!$B44,0)) -> 94.843397 | H44: =AVERAGEIFS('JN - M'!E:E,'JN - M'!$B:$B,">="&EDATE('JN - Q'!$B44,-2),'JN - M'!$B:$B,"<="&EOMONTH('JN - Q'!$B44,0)) -> 97.583348 | I44: =AVERAGEIFS('JN - M'!F:F,'JN - M'!$B:$B,">="&EDATE('JN - Q'!$B44,-2),'JN - M'!$B:$B,"<="&EOMONTH('JN - Q'!$B44,0)) -> 97.583348 | J44: =AVERAGEIFS('JN - M'!K:K,'JN - M'!$B:$B,">="&EDATE('JN - Q'!$B44,-2),'JN - M'!$B:$B,"<="&EOMONTH('JN - Q'!$B44,0)) -> 2.1141884 | K44: =K45*S44/S45 -> 2.1220486 | L44: 0 | N44: =AVERAGEIFS('JN - M'!I:I,'JN - M'!$B:$B,">="&EDATE('JN - Q'!$B44,-2),'JN - M'!$B:$B,"<="&EOMONTH('JN - Q'!$B44,0)) -> 7.1001733 | O44: =AVERAGEIFS('JN - M'!J:J,'JN - M'!$B:$B,">="&EDATE('JN - Q'!$B44,-2),'JN - M'!$B:$B,"<="&EOMONTH('JN - Q'!$B44,0)) -> 7.5206371 | S44: =(H44/H40-1)*100+2 -> 4.027027
B45: 33117 | C45: ='CDM - Q'!M174 -> 450164.07 | E45: =AVERAGEIFS('JN - M'!G:G,'JN - M'!$B:$B,">="&EDATE('JN - Q'!$B45,-2),'JN - M'!$B:$B,"<="&EOMONTH('JN - Q'!$B45,0)) -> 74.9 | F45: =AVERAGEIFS('JN - M'!H:H,'JN - M'!$B:$B,">="&EDATE('JN - Q'!$B45,-2),'JN - M'!$B:$B,"<="&EOMONTH('JN - Q'!$B45,0)) -> 75.163466 | G45: =AVERAGEIFS('JN - M'!D:D,'JN - M'!$B:$B,">="&EDATE('JN - Q'!$B45,-2),'JN - M'!$B:$B,"<="&EOMONTH('JN - Q'!$B45,0)) -> 95.479903 | H45: =AVERAGEIFS('JN - M'!E:E,'JN - M'!$B:$B,">="&EDATE('JN - Q'!$B45,-2),'JN - M'!$B:$B,"<="&EOMONTH('JN - Q'!$B45,0)) -> 97.942375 | I45: =AVERAGEIFS('JN - M'!F:F,'JN - M'!$B:$B,">="&EDATE('JN - Q'!$B45,-2),'JN - M'!$B:$B,"<="&EOMONTH('JN - Q'!$B45,0)) -> 97.942375 | J45: =AVERAGEIFS('JN - M'!K:K,'JN - M'!$B:$B,">="&EDATE('JN - Q'!$B45,-2),'JN - M'!$B:$B,"<="&EOMONTH('JN - Q'!$B45,0)) -> 2.0841978 | K45: =K46*S45/S46 -> 2.2591546 | L45: 0 | N45: =AVERAGEIFS('JN - M'!I:I,'JN - M'!$B:$B,">="&EDATE('JN - Q'!$B45,-2),'JN - M'!$B:$B,"<="&EOMONTH('JN - Q'!$B45,0)) -> 7.4412133 | O45: =AVERAGEIFS('JN - M'!J:J,'JN - M'!$B:$B,">="&EDATE('JN - Q'!$B45,-2),'JN - M'!$B:$B,"<="&EOMONTH('JN - Q'!$B45,0)) -> 7.8818731 | S45: =(H45/H41-1)*100+2 -> 4.2872141
B46: 33208 | C46: ='CDM - Q'!M175 -> 449308.85 | E46: =AVERAGEIFS('JN - M'!G:G,'JN - M'!$B:$B,">="&EDATE('JN - Q'!$B46,-2),'JN - M'!$B:$B,"<="&EOMONTH('JN - Q'!$B46,0)) -> 76.666667 | F46: =AVERAGEIFS('JN - M'!H:H,'JN - M'!$B:$B,">="&EDATE('JN - Q'!$B46,-2),'JN - M'!$B:$B,"<="&EOMONTH('JN - Q'!$B46,0)) -> 76.997172 | G46: =AVERAGEIFS('JN - M'!D:D,'JN - M'!$B:$B,">="&EDATE('JN - Q'!$B46,-2),'JN - M'!$B:$B,"<="&EOMONTH('JN - Q'!$B46,0)) -> 96.478006 | H46: =AVERAGEIFS('JN - M'!E:E,'JN - M'!$B:$B,">="&EDATE('JN - Q'!$B46,-2),'JN - M'!$B:$B,"<="&EOMONTH('JN - Q'!$B46,0)) -> 98.983551 | I46: =AVERAGEIFS('JN - M'!F:F,'JN - M'!$B:$B,">="&EDATE('JN - Q'!$B46,-2),'JN - M'!$B:$B,"<="&EOMONTH('JN - Q'!$B46,0)) -> 98.983551 | J46: =AVERAGEIFS('JN - M'!K:K,'JN - M'!$B:$B,">="&EDATE('JN - Q'!$B46,-2),'JN - M'!$B:$B,"<="&EOMONTH('JN - Q'!$B46,0)) -> 2.0802511 | K46: =K47*S46/S47 -> 2.4669581 | L46: 0 | N46: =AVERAGEIFS('JN - M'!I:I,'JN - M'!$B:$B,">="&EDATE('JN - Q'!$B46,-2),'JN - M'!$B:$B,"<="&EOMONTH('JN - Q'!$B46,0)) -> 7.90952 | O46: =AVERAGEIFS('JN - M'!J:J,'JN - M'!$B:$B,">="&EDATE('JN - Q'!$B46,-2),'JN - M'!$B:$B,"<="&EOMONTH('JN - Q'!$B46,0)) -> 8.3779123 | S46: =(H46/H42-1)*100+2 -> 4.6815642
A47: 1991 | B47: 33298 | C47: ='CDM - Q'!M176 -> 453223.75 | E47: =AVERAGEIFS('JN - M'!G:G,'JN - M'!$B:$B,">="&EDATE('JN - Q'!$B47,-2),'JN - M'!$B:$B,"<="&EOMONTH('JN - Q'!$B47,0)) -> 79.866667 | F47: =AVERAGEIFS('JN - M'!H:H,'JN - M'!$B:$B,">="&EDATE('JN - Q'!$B47,-2),'JN - M'!$B:$B,"<="&EOMONTH('JN - Q'!$B47,0)) -> 77.128026 | G47: =AVERAGEIFS('JN - M'!D:D,'JN - M'!$B:$B,">="&EDATE('JN - Q'!$B47,-2),'JN - M'!$B:$B,"<="&EOMONTH('JN - Q'!$B47,0)) -> 97.189274 | H47: =AVERAGEIFS('JN - M'!E:E,'JN - M'!$B:$B,">="&EDATE('JN - Q'!$B47,-2),'JN - M'!$B:$B,"<="&EOMONTH('JN - Q'!$B47,0)) -> 99.234869 | I47: =AVERAGEIFS('JN - M'!F:F,'JN - M'!$B:$B,">="&EDATE('JN - Q'!$B47,-2),'JN - M'!$B:$B,"<="&EOMONTH('JN - Q'!$B47,0)) -> 99.234869 | J47: =AVERAGEIFS('JN - M'!K:K,'JN - M'!$B:$B,">="&EDATE('JN - Q'!$B47,-2),'JN - M'!$B:$B,"<="&EOMONTH('JN - Q'!$B47,0)) -> 2.0781701 | K47: =K48*S47/S48 -> 2.6043384 | L47: 0 | N47: =AVERAGEIFS('JN - M'!I:I,'JN - M'!$B:$B,">="&EDATE('JN - Q'!$B47,-2),'JN - M'!$B:$B,"<="&EOMONTH('JN - Q'!$B47,0)) -> 8.0805367 | O47: =AVERAGEIFS('JN - M'!J:J,'JN - M'!$B:$B,">="&EDATE('JN - Q'!$B47,-2),'JN - M'!$B:$B,"<="&EOMONTH('JN - Q'!$B47,0)) -> 8.5590564 | S47: =(H47/H43-1)*100+2 -> 4.9422719
B48: 33390 | C48: ='CDM - Q'!M177 -> 458600.85 | E48: =AVERAGEIFS('JN - M'!G:G,'JN - M'!$B:$B,">="&EDATE('JN - Q'!$B48,-2),'JN - M'!$B:$B,"<="&EOMONTH('JN - Q'!$B48,0)) -> 75 | F48: =AVERAGEIFS('JN - M'!H:H,'JN - M'!$B:$B,">="&EDATE('JN - Q'!$B48,-2),'JN - M'!$B:$B,"<="&EOMONTH('JN - Q'!$B48,0)) -> 77.088396 | G48: =AVERAGEIFS('JN - M'!D:D,'JN - M'!$B:$B,">="&EDATE('JN - Q'!$B48,-2),'JN - M'!$B:$B,"<="&EOMONTH('JN - Q'!$B48,0)) -> 97.696774 | H48: =AVERAGEIFS('JN - M'!E:E,'JN - M'!$B:$B,">="&EDATE('JN - Q'!$B48,-2),'JN - M'!$B:$B,"<="&EOMONTH('JN - Q'!$B48,0)) -> 100.56327 | I48: =AVERAGEIFS('JN - M'!F:F,'JN - M'!$B:$B,">="&EDATE('JN - Q'!$B48,-2),'JN - M'!$B:$B,"<="&EOMONTH('JN - Q'!$B48,0)) -> 100.56327 | J48: =AVERAGEIFS('JN - M'!K:K,'JN - M'!$B:$B,">="&EDATE('JN - Q'!$B48,-2),'JN - M'!$B:$B,"<="&EOMONTH('JN - Q'!$B48,0)) -> 2.1041678 | K48: =K49*S48/S49 -> 2.6630641 | L48: 0 | N48: =AVERAGEIFS('JN - M'!I:I,'JN - M'!$B:$B,">="&EDATE('JN - Q'!$B48,-2),'JN - M'!$B:$B,"<="&EOMONTH('JN - Q'!$B48,0)) -> 8.03167 | O48: =AVERAGEIFS('JN - M'!J:J,'JN - M'!$B:$B,">="&EDATE('JN - Q'!$B48,-2),'JN - M'!$B:$B,"<="&EOMONTH('JN - Q'!$B48,0)) -> 8.5072959 | S48: =(H48/H44-1)*100+2 -> 5.053716
B49: 33482 | C49: ='CDM - Q'!M178 -> 457585.61 | E49: =AVERAGEIFS('JN - M'!G:G,'JN - M'!$B:$B,">="&EDATE('JN - Q'!$B49,-2),'JN - M'!$B:$B,"<="&EOMONTH('JN - Q'!$B49,0)) -> 76.633333 | F49: =AVERAGEIFS('JN - M'!H:H,'JN - M'!$B:$B,">="&EDATE('JN - Q'!$B49,-2),'JN - M'!$B:$B,"<="&EOMONTH('JN - Q'!$B49,0)) -> 76.914516 | G49: =AVERAGEIFS('JN - M'!D:D,'JN - M'!$B:$B,">="&EDATE('JN - Q'!$B49,-2),'JN - M'!$B:$B,"<="&EOMONTH('JN - Q'!$B49,0)) -> 98.303688 | H49: =AVERAGEIFS('JN - M'!E:E,'JN - M'!$B:$B,">="&EDATE('JN - Q'!$B49,-2),'JN - M'!$B:$B,"<="&EOMONTH('JN - Q'!$B49,0)) -> 100.88639 | I49: =AVERAGEIFS('JN - M'!F:F,'JN - M'!$B:$B,">="&EDATE('JN - Q'!$B49,-2),'JN - M'!$B:$B,"<="&EOMONTH('JN - Q'!$B49,0)) -> 100.88639 | J49: =AVERAGEIFS('JN - M'!K:K,'JN - M'!$B:$B,">="&EDATE('JN - Q'!$B49,-2),'JN - M'!$B:$B,"<="&EOMONTH('JN - Q'!$B49,0)) -> 2.1355036 | K49: =K50*S49/S50 -> 2.637849 | L49: 0 | N49: =AVERAGEIFS('JN - M'!I:I,'JN - M'!$B:$B,">="&EDATE('JN - Q'!$B49,-2),'JN - M'!$B:$B,"<="&EOMONTH('JN - Q'!$B49,0)) -> 7.26074 | O49: =AVERAGEIFS('JN - M'!J:J,'JN - M'!$B:$B,">="&EDATE('JN - Q'!$B49,-2),'JN - M'!$B:$B,"<="&EOMONTH('JN - Q'!$B49,0)) -> 7.6907124 | S49: =(H49/H45-1)*100+2 -> 5.0058651
B50: 33573 | C50: ='CDM - Q'!M179 -> 460799.38 | E50: =AVERAGEIFS('JN - M'!G:G,'JN - M'!$B:$B,">="&EDATE('JN - Q'!$B50,-2),'JN - M'!$B:$B,"<="&EOMONTH('JN - Q'!$B50,0)) -> 76.4 | F50: =AVERAGEIFS('JN - M'!H:H,'JN - M'!$B:$B,">="&EDATE('JN - Q'!$B50,-2),'JN - M'!$B:$B,"<="&EOMONTH('JN - Q'!$B50,0)) -> 76.81781 | G50: =AVERAGEIFS('JN - M'!D:D,'JN - M'!$B:$B,">="&EDATE('JN - Q'!$B50,-2),'JN - M'!$B:$B,"<="&EOMONTH('JN - Q'!$B50,0)) -> 98.750074 | H50: =AVERAGEIFS('JN - M'!E:E,'JN - M'!$B:$B,">="&EDATE('JN - Q'!$B50,-2),'JN - M'!$B:$B,"<="&EOMONTH('JN - Q'!$B50,0)) -> 101.67625 | I50: =AVERAGEIFS('JN - M'!F:F,'JN - M'!$B:$B,">="&EDATE('JN - Q'!$B50,-2),'JN - M'!$B:$B,"<="&EOMONTH('JN - Q'!$B50,0)) -> 101.67625 | J50: =AVERAGEIFS('JN - M'!K:K,'JN - M'!$B:$B,">="&EDATE('JN - Q'!$B50,-2),'JN - M'!$B:$B,"<="&EOMONTH('JN - Q'!$B50,0)) -> 2.0652137 | K50: =K51*S50/S51 -> 2.4873954 | L50: 0 | N50: =AVERAGEIFS('JN - M'!I:I,'JN - M'!$B:$B,">="&EDATE('JN - Q'!$B50,-2),'JN - M'!$B:$B,"<="&EOMONTH('JN - Q'!$B50,0)) -> 6.4548767 | O50: =AVERAGEIFS('JN - M'!J:J,'JN - M'!$B:$B,">="&EDATE('JN - Q'!$B50,-2),'JN - M'!$B:$B,"<="&EOMONTH('JN - Q'!$B50,0)) -> 6.8371268 | S50: =(H50/H46-1)*100+2 -> 4.7203482
A51: 1992 | B51: 33664 | C51: ='CDM - Q'!M180 -> 460942.69 | E51: =AVERAGEIFS('JN - M'!G:G,'JN - M'!$B:$B,">="&EDATE('JN - Q'!$B51,-2),'JN - M'!$B:$B,"<="&EOMONTH('JN - Q'!$B51,0)) -> 77.466667 | F51: =AVERAGEIFS('JN - M'!H:H,'JN - M'!$B:$B,">="&EDATE('JN - Q'!$B51,-2),'JN - M'!$B:$B,"<="&EOMONTH('JN - Q'!$B51,0)) -> 74.756963 | G51: =AVERAGEIFS('JN - M'!D:D,'JN - M'!$B:$B,">="&EDATE('JN - Q'!$B51,-2),'JN - M'!$B:$B,"<="&EOMONTH('JN - Q'!$B51,0)) -> 99.337749 | H51: =AVERAGEIFS('JN - M'!E:E,'JN - M'!$B:$B,">="&EDATE('JN - Q'!$B51,-2),'JN - M'!$B:$B,"<="&EOMONTH('JN - Q'!$B51,0)) -> 101.74805 | I51: =AVERAGEIFS('JN - M'!F:F,'JN - M'!$B:$B,">="&EDATE('JN - Q'!$B51,-2),'JN - M'!$B:$B,"<="&EOMONTH('JN - Q'!$B51,0)) -> 101.74805 | J51: =AVERAGEIFS('JN - M'!K:K,'JN - M'!$B:$B,">="&EDATE('JN - Q'!$B51,-2),'JN - M'!$B:$B,"<="&EOMONTH('JN - Q'!$B51,0)) -> 2.0901003 | K51: =K52*S51/S52 -> 2.3884409 | L51: 0 | N51: =AVERAGEIFS('JN - M'!I:I,'JN - M'!$B:$B,">="&EDATE('JN - Q'!$B51,-2),'JN - M'!$B:$B,"<="&EOMONTH('JN - Q'!$B51,0)) -> 5.5433367 | O51: =AVERAGEIFS('JN - M'!J:J,'JN - M'!$B:$B,">="&EDATE('JN - Q'!$B51,-2),'JN - M'!$B:$B,"<="&EOMONTH('JN - Q'!$B51,0)) -> 5.8716064 | S51: =(H51/H47-1)*100+2 -> 4.5325615
B52: 33756 | C52: ='CDM - Q'!M181 -> 462556.7 | E52: =AVERAGEIFS('JN - M'!G:G,'JN - M'!$B:$B,">="&EDATE('JN - Q'!$B52,-2),'JN - M'!$B:$B,"<="&EOMONTH('JN - Q'!$B52,0)) -> 72.1 | F52: =AVERAGEIFS('JN - M'!H:H,'JN - M'!$B:$B,">="&EDATE('JN - Q'!$B52,-2),'JN - M'!$B:$B,"<="&EOMONTH('JN - Q'!$B52,0)) -> 74.114548 | G52: =AVERAGEIFS('JN - M'!D:D,'JN - M'!$B:$B,">="&EDATE('JN - Q'!$B52,-2),'JN - M'!$B:$B,"<="&EOMONTH('JN - Q'!$B52,0)) -> 100.13655 | H52: =AVERAGEIFS('JN - M'!E:E,'JN - M'!$B:$B,">="&EDATE('JN - Q'!$B52,-2),'JN - M'!$B:$B,"<="&EOMONTH('JN - Q'!$B52,0)) -> 103.29187 | I52: =AVERAGEIFS('JN - M'!F:F,'JN - M'!$B:$B,">="&EDATE('JN - Q'!$B52,-2),'JN - M'!$B:$B,"<="&EOMONTH('JN - Q'!$B52,0)) -> 103.29187 | J52: =AVERAGEIFS('JN - M'!K:K,'JN - M'!$B:$B,">="&EDATE('JN - Q'!$B52,-2),'JN - M'!$B:$B,"<="&EOMONTH('JN - Q'!$B52,0)) -> 2.0996323 | K52: =K53*S52/S53 -> 2.4836901 | L52: 0 | N52: =AVERAGEIFS('JN - M'!I:I,'JN - M'!$B:$B,">="&EDATE('JN - Q'!$B52,-2),'JN - M'!$B:$B,"<="&EOMONTH('JN - Q'!$B52,0)) -> 4.6802967 | O52: =AVERAGEIFS('JN - M'!J:J,'JN - M'!$B:$B,">="&EDATE('JN - Q'!$B52,-2),'JN - M'!$B:$B,"<="&EOMONTH('JN - Q'!$B52,0)) -> 4.9574582 | S52: =(H52/H48-1)*100+2 -> 4.7133167
B53: 33848 | C53: ='CDM - Q'!M182 -> 463100.97 | E53: =AVERAGEIFS('JN - M'!G:G,'JN - M'!$B:$B,">="&EDATE('JN - Q'!$B53,-2),'JN - M'!$B:$B,"<="&EOMONTH('JN - Q'!$B53,0)) -> 74.433333 | F53: =AVERAGEIFS('JN - M'!H:H,'JN - M'!$B:$B,">="&EDATE('JN - Q'!$B53,-2),'JN - M'!$B:$B,"<="&EOMONTH('JN - Q'!$B53,0)) -> 74.703617 | G53: =AVERAGEIFS('JN - M'!D:D,'JN - M'!$B:$B,">="&EDATE('JN - Q'!$B53,-2),'JN - M'!$B:$B,"<="&EOMONTH('JN - Q'!$B53,0)) -> 100.44853 | H53: =AVERAGEIFS('JN - M'!E:E,'JN - M'!$B:$B,">="&EDATE('JN - Q'!$B53,-2),'JN - M'!$B:$B,"<="&EOMONTH('JN - Q'!$B53,0)) -> 103.29187 | I53: =AVERAGEIFS('JN - M'!F:F,'JN - M'!$B:$B,">="&EDATE('JN - Q'!$B53,-2),'JN - M'!$B:$B,"<="&EOMONTH('JN - Q'!$B53,0)) -> 103.29187 | J53: =AVERAGEIFS('JN - M'!K:K,'JN - M'!$B:$B,">="&EDATE('JN - Q'!$B53,-2),'JN - M'!$B:$B,"<="&EOMONTH('JN - Q'!$B53,0)) -> 2.1761715 | K53: =K54*S53/S54 -> 2.3103362 | L53: 0 | N53: =AVERAGEIFS('JN - M'!I:I,'JN - M'!$B:$B,">="&EDATE('JN - Q'!$B53,-2),'JN - M'!$B:$B,"<="&EOMONTH('JN - Q'!$B53,0)) -> 4.20153 | O53: =AVERAGEIFS('JN - M'!J:J,'JN - M'!$B:$B,">="&EDATE('JN - Q'!$B53,-2),'JN - M'!$B:$B,"<="&EOMONTH('JN - Q'!$B53,0)) -> 4.4503396 | S53: =(H53/H49-1)*100+2 -> 4.3843416
B54: 33939 | C54: ='CDM - Q'!M183 -> 460148.69 | E54: =AVERAGEIFS('JN - M'!G:G,'JN - M'!$B:$B,">="&EDATE('JN - Q'!$B54,-2),'JN - M'!$B:$B,"<="&EOMONTH('JN - Q'!$B54,0)) -> 72.9 | F54: =AVERAGEIFS('JN - M'!H:H,'JN - M'!$B:$B,">="&EDATE('JN - Q'!$B54,-2),'JN - M'!$B:$B,"<="&EOMONTH('JN - Q'!$B54,0)) -> 73.458253 | G54: =AVERAGEIFS('JN - M'!D:D,'JN - M'!$B:$B,">="&EDATE('JN - Q'!$B54,-2),'JN - M'!$B:$B,"<="&EOMONTH('JN - Q'!$B54,0)) -> 100.81234 | H54: =AVERAGEIFS('JN - M'!E:E,'JN - M'!$B:$B,">="&EDATE('JN - Q'!$B54,-2),'JN - M'!$B:$B,"<="&EOMONTH('JN - Q'!$B54,0)) -> 103.97402 | I54: =AVERAGEIFS('JN - M'!F:F,'JN - M'!$B:$B,">="&EDATE('JN - Q'!$B54,-2),'JN - M'!$B:$B,"<="&EOMONTH('JN - Q'!$B54,0)) -> 103.97402 | J54: =AVERAGEIFS('JN - M'!K:K,'JN - M'!$B:$B,">="&EDATE('JN - Q'!$B54,-2),'JN - M'!$B:$B,"<="&EOMONTH('JN - Q'!$B54,0)) -> 2.2724563 | K54: =K55*S54/S55 -> 2.2447546 | L54: 0 | N54: =AVERAGEIFS('JN - M'!I:I,'JN - M'!$B:$B,">="&EDATE('JN - Q'!$B54,-2),'JN - M'!$B:$B,"<="&EOMONTH('JN - Q'!$B54,0)) -> 3.90545 | O54: =AVERAGEIFS('JN - M'!J:J,'JN - M'!$B:$B,">="&EDATE('JN - Q'!$B54,-2),'JN - M'!$B:$B,"<="&EOMONTH('JN - Q'!$B54,0)) -> 4.1367261 | S54: =(H54/H50-1)*100+2 -> 4.259887
A55: 1993 | B55: 34029 | C55: ='CDM - Q'!M184 -> 465333.92 | E55: =AVERAGEIFS('JN - M'!G:G,'JN - M'!$B:$B,">="&EDATE('JN - Q'!$B55,-2),'JN - M'!$B:$B,"<="&EOMONTH('JN - Q'!$B55,0)) -> 76.9 | F55: =AVERAGEIFS('JN - M'!H:H,'JN - M'!$B:$B,">="&EDATE('JN - Q'!$B55,-2),'JN - M'!$B:$B,"<="&EOMONTH('JN - Q'!$B55,0)) -> 73.997122 | G55: =AVERAGEIFS('JN - M'!D:D,'JN - M'!$B:$B,">="&EDATE('JN - Q'!$B55,-2),'JN - M'!$B:$B,"<="&EOMONTH('JN - Q'!$B55,0)) -> 101.05089 | H55: =AVERAGEIFS('JN - M'!E:E,'JN - M'!$B:$B,">="&EDATE('JN - Q'!$B55,-2),'JN - M'!$B:$B,"<="&EOMONTH('JN - Q'!$B55,0)) -> 103.61499 | I55: =AVERAGEIFS('JN - M'!F:F,'JN - M'!$B:$B,">="&EDATE('JN - Q'!$B55,-2),'JN - M'!$B:$B,"<="&EOMONTH('JN - Q'!$B55,0)) -> 103.61499 | J55: =AVERAGEIFS('JN - M'!K:K,'JN - M'!$B:$B,">="&EDATE('JN - Q'!$B55,-2),'JN - M'!$B:$B,"<="&EOMONTH('JN - Q'!$B55,0)) -> 2.3271195 | K55: =K56*S55/S56 -> 2.0207871 | L55: 0 | N55: =AVERAGEIFS('JN - M'!I:I,'JN - M'!$B:$B,">="&EDATE('JN - Q'!$B55,-2),'JN - M'!$B:$B,"<="&EOMONTH('JN - Q'!$B55,0)) -> 3.3899667 | O55: =AVERAGEIFS('JN - M'!J:J,'JN - M'!$B:$B,">="&EDATE('JN - Q'!$B55,-2),'JN - M'!$B:$B,"<="&EOMONTH('JN - Q'!$B55,0)) -> 3.5907164 | S55: =(H55/H51-1)*100+2 -> 3.8348624
B56: 34121 | C56: ='CDM - Q'!M185 -> 462387.68 | E56: =AVERAGEIFS('JN - M'!G:G,'JN - M'!$B:$B,">="&EDATE('JN - Q'!$B56,-2),'JN - M'!$B:$B,"<="&EOMONTH('JN - Q'!$B56,0)) -> 71.833333 | F56: =AVERAGEIFS('JN - M'!H:H,'JN - M'!$B:$B,">="&EDATE('JN - Q'!$B56,-2),'JN - M'!$B:$B,"<="&EOMONTH('JN - Q'!$B56,0)) -> 73.823797 | G56: =AVERAGEIFS('JN - M'!D:D,'JN - M'!$B:$B,">="&EDATE('JN - Q'!$B56,-2),'JN - M'!$B:$B,"<="&EOMONTH('JN - Q'!$B56,0)) -> 101.42738 | H56: =AVERAGEIFS('JN - M'!E:E,'JN - M'!$B:$B,">="&EDATE('JN - Q'!$B56,-2),'JN - M'!$B:$B,"<="&EOMONTH('JN - Q'!$B56,0)) -> 104.72797 | I56: =AVERAGEIFS('JN - M'!F:F,'JN - M'!$B:$B,">="&EDATE('JN - Q'!$B56,-2),'JN - M'!$B:$B,"<="&EOMONTH('JN - Q'!$B56,0)) -> 104.72797 | J56: =AVERAGEIFS('JN - M'!K:K,'JN - M'!$B:$B,">="&EDATE('JN - Q'!$B56,-2),'JN - M'!$B:$B,"<="&EOMONTH('JN - Q'!$B56,0)) -> 2.4431685 | K56: =K57*S56/S57 -> 1.7865438 | L56: 0 | N56: =AVERAGEIFS('JN - M'!I:I,'JN - M'!$B:$B,">="&EDATE('JN - Q'!$B56,-2),'JN - M'!$B:$B,"<="&EOMONTH('JN - Q'!$B56,0)) -> 3.1341767 | O56: =AVERAGEIFS('JN - M'!J:J,'JN - M'!$B:$B,">="&EDATE('JN - Q'!$B56,-2),'JN - M'!$B:$B,"<="&EOMONTH('JN - Q'!$B56,0)) -> 3.3197789 | S56: =(H56/H52-1)*100+2 -> 3.3903372
B57: 34213 | C57: ='CDM - Q'!M186 -> 459068.37 | E57: =AVERAGEIFS('JN - M'!G:G,'JN - M'!$B:$B,">="&EDATE('JN - Q'!$B57,-2),'JN - M'!$B:$B,"<="&EOMONTH('JN - Q'!$B57,0)) -> 72.666667 | F57: =AVERAGEIFS('JN - M'!H:H,'JN - M'!$B:$B,">="&EDATE('JN - Q'!$B57,-2),'JN - M'!$B:$B,"<="&EOMONTH('JN - Q'!$B57,0)) -> 72.986659 | G57: =AVERAGEIFS('JN - M'!D:D,'JN - M'!$B:$B,">="&EDATE('JN - Q'!$B57,-2),'JN - M'!$B:$B,"<="&EOMONTH('JN - Q'!$B57,0)) -> 101.67793 | H57: =AVERAGEIFS('JN - M'!E:E,'JN - M'!$B:$B,">="&EDATE('JN - Q'!$B57,-2),'JN - M'!$B:$B,"<="&EOMONTH('JN - Q'!$B57,0)) -> 104.65617 | I57: =AVERAGEIFS('JN - M'!F:F,'JN - M'!$B:$B,">="&EDATE('JN - Q'!$B57,-2),'JN - M'!$B:$B,"<="&EOMONTH('JN - Q'!$B57,0)) -> 104.65617 | J57: =AVERAGEIFS('JN - M'!K:K,'JN - M'!$B:$B,">="&EDATE('JN - Q'!$B57,-2),'JN - M'!$B:$B,"<="&EOMONTH('JN - Q'!$B57,0)) -> 2.5230423 | K57: =K58*S57/S58 -> 1.7499118 | L57: 0 | N57: =AVERAGEIFS('JN - M'!I:I,'JN - M'!$B:$B,">="&EDATE('JN - Q'!$B57,-2),'JN - M'!$B:$B,"<="&EOMONTH('JN - Q'!$B57,0)) -> 3.0202633 | O57: =AVERAGEIFS('JN - M'!J:J,'JN - M'!$B:$B,">="&EDATE('JN - Q'!$B57,-2),'JN - M'!$B:$B,"<="&EOMONTH('JN - Q'!$B57,0)) -> 3.1991197 | S57: =(H57/H53-1)*100+2 -> 3.3208203
B58: 34304 | C58: ='CDM - Q'!M187 -> 461960.51 | E58: =AVERAGEIFS('JN - M'!G:G,'JN - M'!$B:$B,">="&EDATE('JN - Q'!$B58,-2),'JN - M'!$B:$B,"<="&EOMONTH('JN - Q'!$B58,0)) -> 71.6 | F58: =AVERAGEIFS('JN - M'!H:H,'JN - M'!$B:$B,">="&EDATE('JN - Q'!$B58,-2),'JN - M'!$B:$B,"<="&EOMONTH('JN - Q'!$B58,0)) -> 72.297486 | G58: =AVERAGEIFS('JN - M'!D:D,'JN - M'!$B:$B,">="&EDATE('JN - Q'!$B58,-2),'JN - M'!$B:$B,"<="&EOMONTH('JN - Q'!$B58,0)) -> 101.80871 | H58: =AVERAGEIFS('JN - M'!E:E,'JN - M'!$B:$B,">="&EDATE('JN - Q'!$B58,-2),'JN - M'!$B:$B,"<="&EOMONTH('JN - Q'!$B58,0)) -> 105.1229 | I58: =AVERAGEIFS('JN - M'!F:F,'JN - M'!$B:$B,">="&EDATE('JN - Q'!$B58,-2),'JN - M'!$B:$B,"<="&EOMONTH('JN - Q'!$B58,0)) -> 105.1229 | J58: =AVERAGEIFS('JN - M'!K:K,'JN - M'!$B:$B,">="&EDATE('JN - Q'!$B58,-2),'JN - M'!$B:$B,"<="&EOMONTH('JN - Q'!$B58,0)) -> 2.7313429 | K58: =K59*S58/S59 -> 1.6361704 | L58: 0 | N58: =AVERAGEIFS('JN - M'!I:I,'JN - M'!$B:$B,">="&EDATE('JN - Q'!$B58,-2),'JN - M'!$B:$B,"<="&EOMONTH('JN - Q'!$B58,0)) -> 2.4181533 | O58: =AVERAGEIFS('JN - M'!J:J,'JN - M'!$B:$B,">="&EDATE('JN - Q'!$B58,-2),'JN - M'!$B:$B,"<="&EOMONTH('JN - Q'!$B58,0)) -> 2.5613535 | S58: =(H58/H54-1)*100+2 -> 3.1049724
A59: 1994 | B59: 34394 | C59: ='CDM - Q'!M188 -> 465065 | D59: 521929.2 | E59: =AVERAGEIFS('JN - M'!G:G,'JN - M'!$B:$B,">="&EDATE('JN - Q'!$B59,-2),'JN - M'!$B:$B,"<="&EOMONTH('JN - Q'!$B59,0)) -> 76.266667 | F59: =AVERAGEIFS('JN - M'!H:H,'JN - M'!$B:$B,">="&EDATE('JN - Q'!$B59,-2),'JN - M'!$B:$B,"<="&EOMONTH('JN - Q'!$B59,0)) -> 73.129317 | G59: =AVERAGEIFS('JN - M'!D:D,'JN - M'!$B:$B,">="&EDATE('JN - Q'!$B59,-2),'JN - M'!$B:$B,"<="&EOMONTH('JN - Q'!$B59,0)) -> 101.96389 | H59: =AVERAGEIFS('JN - M'!E:E,'JN - M'!$B:$B,">="&EDATE('JN - Q'!$B59,-2),'JN - M'!$B:$B,"<="&EOMONTH('JN - Q'!$B59,0)) -> 104.76387 | I59: =AVERAGEIFS('JN - M'!F:F,'JN - M'!$B:$B,">="&EDATE('JN - Q'!$B59,-2),'JN - M'!$B:$B,"<="&EOMONTH('JN - Q'!$B59,0)) -> 104.76387 | J59: =AVERAGEIFS('JN - M'!K:K,'JN - M'!$B:$B,">="&EDATE('JN - Q'!$B59,-2),'JN - M'!$B:$B,"<="&EOMONTH('JN - Q'!$B59,0)) -> 2.8551699 | K59: =K60*S59/S60 -> 1.6381879 | L59: 0 | M59: ='CDM - Q'!P188/'CDM - Q'!O188*100 -> 84.857684 | N59: =AVERAGEIFS('JN - M'!I:I,'JN - M'!$B:$B,">="&EDATE('JN - Q'!$B59,-2),'JN - M'!$B:$B,"<="&EOMONTH('JN - Q'!$B59,0)) -> 2.1955967 | O59: =AVERAGEIFS('JN - M'!J:J,'JN - M'!$B:$B,">="&EDATE('JN - Q'!$B59,-2),'JN - M'!$B:$B,"<="&EOMONTH('JN - Q'!$B59,0)) -> 2.3256173 | S59: =(H59/H55-1)*100+2 -> 3.1088011
B60: 34486 | C60: ='CDM - Q'!M189 -> 461497.8 | D60: 519853.1 | E60: =AVERAGEIFS('JN - M'!G:G,'JN - M'!$B:$B,">="&EDATE('JN - Q'!$B60,-2),'JN - M'!$B:$B,"<="&EOMONTH('JN - Q'!$B60,0)) -> 72.866667 | F60: =AVERAGEIFS('JN - M'!H:H,'JN - M'!$B:$B,">="&EDATE('JN - Q'!$B60,-2),'JN - M'!$B:$B,"<="&EOMONTH('JN - Q'!$B60,0)) -> 74.928115 | G60: =AVERAGEIFS('JN - M'!D:D,'JN - M'!$B:$B,">="&EDATE('JN - Q'!$B60,-2),'JN - M'!$B:$B,"<="&EOMONTH('JN - Q'!$B60,0)) -> 102.39729 | H60: =AVERAGEIFS('JN - M'!E:E,'JN - M'!$B:$B,">="&EDATE('JN - Q'!$B60,-2),'JN - M'!$B:$B,"<="&EOMONTH('JN - Q'!$B60,0)) -> 105.91276 | I60: =AVERAGEIFS('JN - M'!F:F,'JN - M'!$B:$B,">="&EDATE('JN - Q'!$B60,-2),'JN - M'!$B:$B,"<="&EOMONTH('JN - Q'!$B60,0)) -> 105.91276 | J60: =AVERAGEIFS('JN - M'!K:K,'JN - M'!$B:$B,">="&EDATE('JN - Q'!$B60,-2),'JN - M'!$B:$B,"<="&EOMONTH('JN - Q'!$B60,0)) -> 2.8202328 | K60: =K61*S60/S61 -> 1.6500434 | L60: 0 | M60: ='CDM - Q'!P189/'CDM - Q'!O189*100 -> 87.154563 | N60: =AVERAGEIFS('JN - M'!I:I,'JN - M'!$B:$B,">="&EDATE('JN - Q'!$B60,-2),'JN - M'!$B:$B,"<="&EOMONTH('JN - Q'!$B60,0)) -> 2.0462733 | O60: =AVERAGEIFS('JN - M'!J:J,'JN - M'!$B:$B,">="&EDATE('JN - Q'!$B60,-2),'JN - M'!$B:$B,"<="&EOMONTH('JN - Q'!$B60,0)) -> 2.1674512 | S60: =(H60/H56-1)*100+2 -> 3.1312993
B61: 34578 | C61: ='CDM - Q'!M190 -> 466136.4 | D61: 522921.4 | E61: =AVERAGEIFS('JN - M'!G:G,'JN - M'!$B:$B,">="&EDATE('JN - Q'!$B61,-2),'JN - M'!$B:$B,"<="&EOMONTH('JN - Q'!$B61,0)) -> 75.466667 | F61: =AVERAGEIFS('JN - M'!H:H,'JN - M'!$B:$B,">="&EDATE('JN - Q'!$B61,-2),'JN - M'!$B:$B,"<="&EOMONTH('JN - Q'!$B61,0)) -> 75.837176 | G61: =AVERAGEIFS('JN - M'!D:D,'JN - M'!$B:$B,">="&EDATE('JN - Q'!$B61,-2),'JN - M'!$B:$B,"<="&EOMONTH('JN - Q'!$B61,0)) -> 102.34097 | H61: =AVERAGEIFS('JN - M'!E:E,'JN - M'!$B:$B,">="&EDATE('JN - Q'!$B61,-2),'JN - M'!$B:$B,"<="&EOMONTH('JN - Q'!$B61,0)) -> 105.55373 | I61: =AVERAGEIFS('JN - M'!F:F,'JN - M'!$B:$B,">="&EDATE('JN - Q'!$B61,-2),'JN - M'!$B:$B,"<="&EOMONTH('JN - Q'!$B61,0)) -> 105.55373 | J61: =AVERAGEIFS('JN - M'!K:K,'JN - M'!$B:$B,">="&EDATE('JN - Q'!$B61,-2),'JN - M'!$B:$B,"<="&EOMONTH('JN - Q'!$B61,0)) -> 2.9664144 | K61: =K62*S61/S62 -> 1.5058345 | L61: 0 | M61: ='CDM - Q'!P190/'CDM - Q'!O190*100 -> 86.898286 | N61: =AVERAGEIFS('JN - M'!I:I,'JN - M'!$B:$B,">="&EDATE('JN - Q'!$B61,-2),'JN - M'!$B:$B,"<="&EOMONTH('JN - Q'!$B61,0)) -> 2.0698567 | O61: =AVERAGEIFS('JN - M'!J:J,'JN - M'!$B:$B,">="&EDATE('JN - Q'!$B61,-2),'JN - M'!$B:$B,"<="&EOMONTH('JN - Q'!$B61,0)) -> 2.1924311 | S61: =(H61/H57-1)*100+2 -> 2.8576329
B62: 34669 | C62: ='CDM - Q'!M191 -> 464395.6 | D62: 521954.8 | E62: =AVERAGEIFS('JN - M'!G:G,'JN - M'!$B:$B,">="&EDATE('JN - Q'!$B62,-2),'JN - M'!$B:$B,"<="&EOMONTH('JN - Q'!$B62,0)) -> 76.033333 | F62: =AVERAGEIFS('JN - M'!H:H,'JN - M'!$B:$B,">="&EDATE('JN - Q'!$B62,-2),'JN - M'!$B:$B,"<="&EOMONTH('JN - Q'!$B62,0)) -> 76.887898 | G62: =AVERAGEIFS('JN - M'!D:D,'JN - M'!$B:$B,">="&EDATE('JN - Q'!$B62,-2),'JN - M'!$B:$B,"<="&EOMONTH('JN - Q'!$B62,0)) -> 102.22743 | H62: =AVERAGEIFS('JN - M'!E:E,'JN - M'!$B:$B,">="&EDATE('JN - Q'!$B62,-2),'JN - M'!$B:$B,"<="&EOMONTH('JN - Q'!$B62,0)) -> 105.73325 | I62: =AVERAGEIFS('JN - M'!F:F,'JN - M'!$B:$B,">="&EDATE('JN - Q'!$B62,-2),'JN - M'!$B:$B,"<="&EOMONTH('JN - Q'!$B62,0)) -> 105.73325 | J62: =AVERAGEIFS('JN - M'!K:K,'JN - M'!$B:$B,">="&EDATE('JN - Q'!$B62,-2),'JN - M'!$B:$B,"<="&EOMONTH('JN - Q'!$B62,0)) -> 2.9100501 | K62: =K63*S62/S63 -> 1.3598521 | L62: 0 | M62: ='CDM - Q'!P191/'CDM - Q'!O191*100 -> 86.114687 | N62: =AVERAGEIFS('JN - M'!I:I,'JN - M'!$B:$B,">="&EDATE('JN - Q'!$B62,-2),'JN - M'!$B:$B,"<="&EOMONTH('JN - Q'!$B62,0)) -> 2.2029767 | O62: =AVERAGEIFS('JN - M'!J:J,'JN - M'!$B:$B,">="&EDATE('JN - Q'!$B62,-2),'JN - M'!$B:$B,"<="&EOMONTH('JN - Q'!$B62,0)) -> 2.3334343 | S62: =(H62/H58-1)*100+2 -> 2.5806011
A63: 1995 | B63: 34759 | C63: ='CDM - Q'!M192 -> 468895.6 | D63: 524167.5 | E63: =AVERAGEIFS('JN - M'!G:G,'JN - M'!$B:$B,">="&EDATE('JN - Q'!$B63,-2),'JN - M'!$B:$B,"<="&EOMONTH('JN - Q'!$B63,0)) -> 81.233333 | F63: =AVERAGEIFS('JN - M'!H:H,'JN - M'!$B:$B,">="&EDATE('JN - Q'!$B63,-2),'JN - M'!$B:$B,"<="&EOMONTH('JN - Q'!$B63,0)) -> 77.699432 | G63: =AVERAGEIFS('JN - M'!D:D,'JN - M'!$B:$B,">="&EDATE('JN - Q'!$B63,-2),'JN - M'!$B:$B,"<="&EOMONTH('JN - Q'!$B63,0)) -> 102.33707 | H63: =AVERAGEIFS('JN - M'!E:E,'JN - M'!$B:$B,">="&EDATE('JN - Q'!$B63,-2),'JN - M'!$B:$B,"<="&EOMONTH('JN - Q'!$B63,0)) -> 105.26651 | I63: =AVERAGEIFS('JN - M'!F:F,'JN - M'!$B:$B,">="&EDATE('JN - Q'!$B63,-2),'JN - M'!$B:$B,"<="&EOMONTH('JN - Q'!$B63,0)) -> 105.26651 | J63: =AVERAGEIFS('JN - M'!K:K,'JN - M'!$B:$B,">="&EDATE('JN - Q'!$B63,-2),'JN - M'!$B:$B,"<="&EOMONTH('JN - Q'!$B63,0)) -> 3.0037127 | K63: =K64*S63/S64 -> 1.3067246 | L63: 0 | M63: ='CDM - Q'!P192/'CDM - Q'!O192*100 -> 85.032555 | N63: =AVERAGEIFS('JN - M'!I:I,'JN - M'!$B:$B,">="&EDATE('JN - Q'!$B63,-2),'JN - M'!$B:$B,"<="&EOMONTH('JN - Q'!$B63,0)) -> 2.15471 | O63: =AVERAGEIFS('JN - M'!J:J,'JN - M'!$B:$B,">="&EDATE('JN - Q'!$B63,-2),'JN - M'!$B:$B,"<="&EOMONTH('JN - Q'!$B63,0)) -> 2.1356816 | S63: =(H63/H59-1)*100+2 -> 2.4797807
B64: 34851 | C64: ='CDM - Q'!M193 -> 473156 | D64: 527594.6 | E64: =AVERAGEIFS('JN - M'!G:G,'JN - M'!$B:$B,">="&EDATE('JN - Q'!$B64,-2),'JN - M'!$B:$B,"<="&EOMONTH('JN - Q'!$B64,0)) -> 76.733333 | F64: =AVERAGEIFS('JN - M'!H:H,'JN - M'!$B:$B,">="&EDATE('JN - Q'!$B64,-2),'JN - M'!$B:$B,"<="&EOMONTH('JN - Q'!$B64,0)) -> 79.060005 | G64: =AVERAGEIFS('JN - M'!D:D,'JN - M'!$B:$B,">="&EDATE('JN - Q'!$B64,-2),'JN - M'!$B:$B,"<="&EOMONTH('JN - Q'!$B64,0)) -> 102.18501 | H64: =AVERAGEIFS('JN - M'!E:E,'JN - M'!$B:$B,">="&EDATE('JN - Q'!$B64,-2),'JN - M'!$B:$B,"<="&EOMONTH('JN - Q'!$B64,0)) -> 105.80505 | I64: =AVERAGEIFS('JN - M'!F:F,'JN - M'!$B:$B,">="&EDATE('JN - Q'!$B64,-2),'JN - M'!$B:$B,"<="&EOMONTH('JN - Q'!$B64,0)) -> 105.80505 | J64: =AVERAGEIFS('JN - M'!K:K,'JN - M'!$B:$B,">="&EDATE('JN - Q'!$B64,-2),'JN - M'!$B:$B,"<="&EOMONTH('JN - Q'!$B64,0)) -> 3.0739634 | K64: =K65*S64/S65 -> 1.000315 | L64: 0 | M64: ='CDM - Q'!P193/'CDM - Q'!O193*100 -> 81.248754 | N64: =AVERAGEIFS('JN - M'!I:I,'JN - M'!B:B,">="&EDATE('JN - Q'!B64,-2),'JN - M'!B:B,"<="&EOMONTH('JN - Q'!B64,0)) -> 1.3201033 | O64: =AVERAGEIFS('JN - M'!J:J,'JN - M'!$B:$B,">="&EDATE('JN - Q'!$B64,-2),'JN - M'!$B:$B,"<="&EOMONTH('JN - Q'!$B64,0)) -> 1.0496934 | S64: =(H64/H60-1)*100+2 -> 1.8983051
B65: 34943 | C65: ='CDM - Q'!M194 -> 478593 | D65: 534041.2 | E65: =AVERAGEIFS('JN - M'!G:G,'JN - M'!$B:$B,">="&EDATE('JN - Q'!$B65,-2),'JN - M'!$B:$B,"<="&EOMONTH('JN - Q'!$B65,0)) -> 77.133333 | F65: =AVERAGEIFS('JN - M'!H:H,'JN - M'!$B:$B,">="&EDATE('JN - Q'!$B65,-2),'JN - M'!$B:$B,"<="&EOMONTH('JN - Q'!$B65,0)) -> 77.514163 | G65: =AVERAGEIFS('JN - M'!D:D,'JN - M'!$B:$B,">="&EDATE('JN - Q'!$B65,-2),'JN - M'!$B:$B,"<="&EOMONTH('JN - Q'!$B65,0)) -> 102.23138 | H65: =AVERAGEIFS('JN - M'!E:E,'JN - M'!$B:$B,">="&EDATE('JN - Q'!$B65,-2),'JN - M'!$B:$B,"<="&EOMONTH('JN - Q'!$B65,0)) -> 105.55373 | I65: =AVERAGEIFS('JN - M'!F:F,'JN - M'!$B:$B,">="&EDATE('JN - Q'!$B65,-2),'JN - M'!$B:$B,"<="&EOMONTH('JN - Q'!$B65,0)) -> 105.55373 | J65: =AVERAGEIFS('JN - M'!K:K,'JN - M'!$B:$B,">="&EDATE('JN - Q'!$B65,-2),'JN - M'!$B:$B,"<="&EOMONTH('JN - Q'!$B65,0)) -> 3.1882607 | K65: =K66*S65/S66 -> 1.0539033 | L65: 0 | M65: ='CDM - Q'!P194/'CDM - Q'!O194*100 -> 85.100158 | N65: =AVERAGEIFS('JN - M'!I:I,'JN - M'!B:B,">="&EDATE('JN - Q'!B65,-2),'JN - M'!B:B,"<="&EOMONTH('JN - Q'!B65,0)) -> 0.74666667 | O65: =AVERAGEIFS('JN - M'!J:J,'JN - M'!$B:$B,">="&EDATE('JN - Q'!$B65,-2),'JN - M'!$B:$B,"<="&EOMONTH('JN - Q'!$B65,0)) -> 0.50784848 | S65: =(H65/H61-1)*100+2 -> 2
B66: 35034 | C66: ='CDM - Q'!M195 -> 479789.2 | D66: 535702.9 | E66: =AVERAGEIFS('JN - M'!G:G,'JN - M'!$B:$B,">="&EDATE('JN - Q'!$B66,-2),'JN - M'!$B:$B,"<="&EOMONTH('JN - Q'!$B66,0)) -> 78.433333 | F66: =AVERAGEIFS('JN - M'!H:H,'JN - M'!$B:$B,">="&EDATE('JN - Q'!$B66,-2),'JN - M'!$B:$B,"<="&EOMONTH('JN - Q'!$B66,0)) -> 79.344304 | G66: =AVERAGEIFS('JN - M'!D:D,'JN - M'!$B:$B,">="&EDATE('JN - Q'!$B66,-2),'JN - M'!$B:$B,"<="&EOMONTH('JN - Q'!$B66,0)) -> 102.28336 | H66: =AVERAGEIFS('JN - M'!E:E,'JN - M'!$B:$B,">="&EDATE('JN - Q'!$B66,-2),'JN - M'!$B:$B,"<="&EOMONTH('JN - Q'!$B66,0)) -> 106.02047 | I66: =AVERAGEIFS('JN - M'!F:F,'JN - M'!$B:$B,">="&EDATE('JN - Q'!$B66,-2),'JN - M'!$B:$B,"<="&EOMONTH('JN - Q'!$B66,0)) -> 106.02047 | J66: =AVERAGEIFS('JN - M'!K:K,'JN - M'!$B:$B,">="&EDATE('JN - Q'!$B66,-2),'JN - M'!$B:$B,"<="&EOMONTH('JN - Q'!$B66,0)) -> 3.3371671 | K66: =K67*S66/S67 -> 1.1970481 | L66: 0 | M66: ='CDM - Q'!P195/'CDM - Q'!O195*100 -> 86.934096 | N66: =AVERAGEIFS('JN - M'!I:I,'JN - M'!B:B,">="&EDATE('JN - Q'!B66,-2),'JN - M'!B:B,"<="&EOMONTH('JN - Q'!B66,0)) -> 0.40333333 | O66: =AVERAGEIFS('JN - M'!J:J,'JN - M'!$B:$B,">="&EDATE('JN - Q'!$B66,-2),'JN - M'!$B:$B,"<="&EOMONTH('JN - Q'!$B66,0)) -> -0.16655901 | S66: =(H66/H62-1)*100+2 -> 2.2716469
A67: 1996 | B67: 35125 | C67: ='CDM - Q'!M196 -> 484268.9 | D67: 540542.8 | E67: =AVERAGEIFS('JN - M'!G:G,'JN - M'!$B:$B,">="&EDATE('JN - Q'!$B67,-2),'JN - M'!$B:$B,"<="&EOMONTH('JN - Q'!$B67,0)) -> 82.833333 | F67: =AVERAGEIFS('JN - M'!H:H,'JN - M'!$B:$B,">="&EDATE('JN - Q'!$B67,-2),'JN - M'!$B:$B,"<="&EOMONTH('JN - Q'!$B67,0)) -> 79.229177 | G67: =AVERAGEIFS('JN - M'!D:D,'JN - M'!$B:$B,">="&EDATE('JN - Q'!$B67,-2),'JN - M'!$B:$B,"<="&EOMONTH('JN - Q'!$B67,0)) -> 102.24208 | H67: =AVERAGEIFS('JN - M'!E:E,'JN - M'!$B:$B,">="&EDATE('JN - Q'!$B67,-2),'JN - M'!$B:$B,"<="&EOMONTH('JN - Q'!$B67,0)) -> 105.51783 | I67: =AVERAGEIFS('JN - M'!F:F,'JN - M'!$B:$B,">="&EDATE('JN - Q'!$B67,-2),'JN - M'!$B:$B,"<="&EOMONTH('JN - Q'!$B67,0)) -> 105.51783 | J67: =AVERAGEIFS('JN - M'!K:K,'JN - M'!$B:$B,">="&EDATE('JN - Q'!$B67,-2),'JN - M'!$B:$B,"<="&EOMONTH('JN - Q'!$B67,0)) -> 3.3503795 | K67: =K68*S67/S68 -> 1.1797104 | L67: 0 | M67: ='CDM - Q'!P196/'CDM - Q'!O196*100 -> 88.82367 | N67: =AVERAGEIFS('JN - M'!I:I,'JN - M'!B:B,">="&EDATE('JN - Q'!B67,-2),'JN - M'!B:B,"<="&EOMONTH('JN - Q'!B67,0)) -> 0.40333333 | O67: =AVERAGEIFS('JN - M'!J:J,'JN - M'!$B:$B,">="&EDATE('JN - Q'!$B67,-2),'JN - M'!$B:$B,"<="&EOMONTH('JN - Q'!$B67,0)) -> 0.31793911 | S67: =(H67/H63-1)*100+2 -> 2.2387449
B68: 35217 | C68: ='CDM - Q'!M197 -> 489500.4 | D68: 546527.4 | E68: =AVERAGEIFS('JN - M'!G:G,'JN - M'!$B:$B,">="&EDATE('JN - Q'!$B68,-2),'JN - M'!$B:$B,"<="&EOMONTH('JN - Q'!$B68,0)) -> 77.566667 | F68: =AVERAGEIFS('JN - M'!H:H,'JN - M'!$B:$B,">="&EDATE('JN - Q'!$B68,-2),'JN - M'!$B:$B,"<="&EOMONTH('JN - Q'!$B68,0)) -> 80.084901 | G68: =AVERAGEIFS('JN - M'!D:D,'JN - M'!$B:$B,">="&EDATE('JN - Q'!$B68,-2),'JN - M'!$B:$B,"<="&EOMONTH('JN - Q'!$B68,0)) -> 102.37154 | H68: =AVERAGEIFS('JN - M'!E:E,'JN - M'!$B:$B,">="&EDATE('JN - Q'!$B68,-2),'JN - M'!$B:$B,"<="&EOMONTH('JN - Q'!$B68,0)) -> 106.16408 | I68: =AVERAGEIFS('JN - M'!F:F,'JN - M'!$B:$B,">="&EDATE('JN - Q'!$B68,-2),'JN - M'!$B:$B,"<="&EOMONTH('JN - Q'!$B68,0)) -> 106.16408 | J68: =AVERAGEIFS('JN - M'!K:K,'JN - M'!$B:$B,">="&EDATE('JN - Q'!$B68,-2),'JN - M'!$B:$B,"<="&EOMONTH('JN - Q'!$B68,0)) -> 3.3970178 | K68: =K69*S68/S69 -> 1.2327129 | L68: 0 | M68: ='CDM - Q'!P197/'CDM - Q'!O197*100 -> 91.05731 | N68: =AVERAGEIFS('JN - M'!I:I,'JN - M'!B:B,">="&EDATE('JN - Q'!B68,-2),'JN - M'!B:B,"<="&EOMONTH('JN - Q'!B68,0)) -> 0.41333333 | O68: =AVERAGEIFS('JN - M'!J:J,'JN - M'!$B:$B,">="&EDATE('JN - Q'!$B68,-2),'JN - M'!$B:$B,"<="&EOMONTH('JN - Q'!$B68,0)) -> 0.45843419 | S68: =(H68/H64-1)*100+2 -> 2.3393281
B69: 35309 | C69: ='CDM - Q'!M198 -> 490385.9 | D69: 546679.7 | E69: =AVERAGEIFS('JN - M'!G:G,'JN - M'!$B:$B,">="&EDATE('JN - Q'!$B69,-2),'JN - M'!$B:$B,"<="&EOMONTH('JN - Q'!$B69,0)) -> 80.9 | F69: =AVERAGEIFS('JN - M'!H:H,'JN - M'!$B:$B,">="&EDATE('JN - Q'!$B69,-2),'JN - M'!$B:$B,"<="&EOMONTH('JN - Q'!$B69,0)) -> 81.244656 | G69: =AVERAGEIFS('JN - M'!D:D,'JN - M'!$B:$B,">="&EDATE('JN - Q'!$B69,-2),'JN - M'!$B:$B,"<="&EOMONTH('JN - Q'!$B69,0)) -> 102.47183 | H69: =AVERAGEIFS('JN - M'!E:E,'JN - M'!$B:$B,">="&EDATE('JN - Q'!$B69,-2),'JN - M'!$B:$B,"<="&EOMONTH('JN - Q'!$B69,0)) -> 106.02047 | I69: =AVERAGEIFS('JN - M'!F:F,'JN - M'!$B:$B,">="&EDATE('JN - Q'!$B69,-2),'JN - M'!$B:$B,"<="&EOMONTH('JN - Q'!$B69,0)) -> 106.02047 | J69: =AVERAGEIFS('JN - M'!K:K,'JN - M'!$B:$B,">="&EDATE('JN - Q'!$B69,-2),'JN - M'!$B:$B,"<="&EOMONTH('JN - Q'!$B69,0)) -> 3.3255691 | K69: =K70*S69/S70 -> 1.2869092 | L69: 0 | M69: ='CDM - Q'!P198/'CDM - Q'!O198*100 -> 92.059827 | N69: =AVERAGEIFS('JN - M'!I:I,'JN - M'!B:B,">="&EDATE('JN - Q'!B69,-2),'JN - M'!B:B,"<="&EOMONTH('JN - Q'!B69,0)) -> 0.40666667 | O69: =AVERAGEIFS('JN - M'!J:J,'JN - M'!$B:$B,">="&EDATE('JN - Q'!$B69,-2),'JN - M'!$B:$B,"<="&EOMONTH('JN - Q'!$B69,0)) -> 0.40487746 | S69: =(H69/H65-1)*100+2 -> 2.4421769
B70: 35400 | C70: ='CDM - Q'!M199 -> 495641.6 | D70: 551567.2 | E70: =AVERAGEIFS('JN - M'!G:G,'JN - M'!$B:$B,">="&EDATE('JN - Q'!$B70,-2),'JN - M'!$B:$B,"<="&EOMONTH('JN - Q'!$B70,0)) -> 82 | F70: =AVERAGEIFS('JN - M'!H:H,'JN - M'!$B:$B,">="&EDATE('JN - Q'!$B70,-2),'JN - M'!$B:$B,"<="&EOMONTH('JN - Q'!$B70,0)) -> 82.915529 | G70: =AVERAGEIFS('JN - M'!D:D,'JN - M'!$B:$B,">="&EDATE('JN - Q'!$B70,-2),'JN - M'!$B:$B,"<="&EOMONTH('JN - Q'!$B70,0)) -> 102.58506 | H70: =AVERAGEIFS('JN - M'!E:E,'JN - M'!$B:$B,">="&EDATE('JN - Q'!$B70,-2),'JN - M'!$B:$B,"<="&EOMONTH('JN - Q'!$B70,0)) -> 106.4513 | I70: =AVERAGEIFS('JN - M'!F:F,'JN - M'!$B:$B,">="&EDATE('JN - Q'!$B70,-2),'JN - M'!$B:$B,"<="&EOMONTH('JN - Q'!$B70,0)) -> 106.4513 | J70: =AVERAGEIFS('JN - M'!K:K,'JN - M'!$B:$B,">="&EDATE('JN - Q'!$B70,-2),'JN - M'!$B:$B,"<="&EOMONTH('JN - Q'!$B70,0)) -> 3.3471772 | K70: =K71*S70/S71 -> 1.2680388 | L70: 0 | M70: ='CDM - Q'!P199/'CDM - Q'!O199*100 -> 94.265135 | N70: =AVERAGEIFS('JN - M'!I:I,'JN - M'!B:B,">="&EDATE('JN - Q'!B70,-2),'JN - M'!B:B,"<="&EOMONTH('JN - Q'!B70,0)) -> 0.42333333 | O70: =AVERAGEIFS('JN - M'!J:J,'JN - M'!$B:$B,">="&EDATE('JN - Q'!$B70,-2),'JN - M'!$B:$B,"<="&EOMONTH('JN - Q'!$B70,0)) -> 0.0092115712 | S70: =(H70/H66-1)*100+2 -> 2.4063664
A71: 1997 | B71: 35490 | C71: ='CDM - Q'!M200 -> 498907.8 | D71: 553273.7 | E71: =AVERAGEIFS('JN - M'!G:G,'JN - M'!$B:$B,">="&EDATE('JN - Q'!$B71,-2),'JN - M'!$B:$B,"<="&EOMONTH('JN - Q'!$B71,0)) -> 89.2 | F71: =AVERAGEIFS('JN - M'!H:H,'JN - M'!$B:$B,">="&EDATE('JN - Q'!$B71,-2),'JN - M'!$B:$B,"<="&EOMONTH('JN - Q'!$B71,0)) -> 85.103222 | G71: =AVERAGEIFS('JN - M'!D:D,'JN - M'!$B:$B,">="&EDATE('JN - Q'!$B71,-2),'JN - M'!$B:$B,"<="&EOMONTH('JN - Q'!$B71,0)) -> 102.72208 | H71: =AVERAGEIFS('JN - M'!E:E,'JN - M'!$B:$B,">="&EDATE('JN - Q'!$B71,-2),'JN - M'!$B:$B,"<="&EOMONTH('JN - Q'!$B71,0)) -> 105.91276 | I71: =AVERAGEIFS('JN - M'!F:F,'JN - M'!$B:$B,">="&EDATE('JN - Q'!$B71,-2),'JN - M'!$B:$B,"<="&EOMONTH('JN - Q'!$B71,0)) -> 105.91276 | J71: =AVERAGEIFS('JN - M'!K:K,'JN - M'!$B:$B,">="&EDATE('JN - Q'!$B71,-2),'JN - M'!$B:$B,"<="&EOMONTH('JN - Q'!$B71,0)) -> 3.3303777 | K71: =K72*S71/S72 -> 1.2511292 | L71: 0 | M71: ='CDM - Q'!P200/'CDM - Q'!O200*100 -> 98.640705 | N71: =AVERAGEIFS('JN - M'!I:I,'JN - M'!B:B,">="&EDATE('JN - Q'!B71,-2),'JN - M'!B:B,"<="&EOMONTH('JN - Q'!B71,0)) -> 0.43666667 | O71: =AVERAGEIFS('JN - M'!J:J,'JN - M'!$B:$B,">="&EDATE('JN - Q'!$B71,-2),'JN - M'!$B:$B,"<="&EOMONTH('JN - Q'!$B71,0)) -> -0.092426743 | S71: =(H71/H67-1)*100+2 -> 2.374277
B72: 35582 | C72: ='CDM - Q'!M201 -> 495402.7 | D72: 554794.7 | E72: =AVERAGEIFS('JN - M'!G:G,'JN - M'!$B:$B,">="&EDATE('JN - Q'!$B72,-2),'JN - M'!$B:$B,"<="&EOMONTH('JN - Q'!$B72,0)) -> 82.4 | F72: =AVERAGEIFS('JN - M'!H:H,'JN - M'!$B:$B,">="&EDATE('JN - Q'!$B72,-2),'JN - M'!$B:$B,"<="&EOMONTH('JN - Q'!$B72,0)) -> 85.242595 | G72: =AVERAGEIFS('JN - M'!D:D,'JN - M'!$B:$B,">="&EDATE('JN - Q'!$B72,-2),'JN - M'!$B:$B,"<="&EOMONTH('JN - Q'!$B72,0)) -> 102.65953 | H72: =AVERAGEIFS('JN - M'!E:E,'JN - M'!$B:$B,">="&EDATE('JN - Q'!$B72,-2),'JN - M'!$B:$B,"<="&EOMONTH('JN - Q'!$B72,0)) -> 106.38724 | I72: =AVERAGEIFS('JN - M'!F:F,'JN - M'!$B:$B,">="&EDATE('JN - Q'!$B72,-2),'JN - M'!$B:$B,"<="&EOMONTH('JN - Q'!$B72,0)) -> 106.38724 | J72: =AVERAGEIFS('JN - M'!K:K,'JN - M'!$B:$B,">="&EDATE('JN - Q'!$B72,-2),'JN - M'!$B:$B,"<="&EOMONTH('JN - Q'!$B72,0)) -> 3.3317596 | K72: =K73*S72/S73 -> 1.1646692 | L72: 0 | M72: ='CDM - Q'!P201/'CDM - Q'!O201*100 -> 97.277604 | N72: =AVERAGEIFS('JN - M'!I:I,'JN - M'!B:B,">="&EDATE('JN - Q'!B72,-2),'JN - M'!B:B,"<="&EOMONTH('JN - Q'!B72,0)) -> 0.43666667 | O72: =AVERAGEIFS('JN - M'!J:J,'JN - M'!$B:$B,">="&EDATE('JN - Q'!$B72,-2),'JN - M'!$B:$B,"<="&EOMONTH('JN - Q'!$B72,0)) -> 0.28741685 | S72: =(H72/H68-1)*100+2 -> 2.2102012
B73: 35674 | C73: ='CDM - Q'!M202 -> 496173.3 | D73: 554518.9 | E73: =AVERAGEIFS('JN - M'!G:G,'JN - M'!$B:$B,">="&EDATE('JN - Q'!$B73,-2),'JN - M'!$B:$B,"<="&EOMONTH('JN - Q'!$B73,0)) -> 85.966667 | F73: =AVERAGEIFS('JN - M'!H:H,'JN - M'!$B:$B,">="&EDATE('JN - Q'!$B73,-2),'JN - M'!$B:$B,"<="&EOMONTH('JN - Q'!$B73,0)) -> 86.252736 | G73: =AVERAGEIFS('JN - M'!D:D,'JN - M'!$B:$B,">="&EDATE('JN - Q'!$B73,-2),'JN - M'!$B:$B,"<="&EOMONTH('JN - Q'!$B73,0)) -> 102.92305 | H73: =AVERAGEIFS('JN - M'!E:E,'JN - M'!$B:$B,">="&EDATE('JN - Q'!$B73,-2),'JN - M'!$B:$B,"<="&EOMONTH('JN - Q'!$B73,0)) -> 106.35195 | I73: =AVERAGEIFS('JN - M'!F:F,'JN - M'!$B:$B,">="&EDATE('JN - Q'!$B73,-2),'JN - M'!$B:$B,"<="&EOMONTH('JN - Q'!$B73,0)) -> 106.35195 | J73: =AVERAGEIFS('JN - M'!K:K,'JN - M'!$B:$B,">="&EDATE('JN - Q'!$B73,-2),'JN - M'!$B:$B,"<="&EOMONTH('JN - Q'!$B73,0)) -> 3.4014146 | K73: =K74*S73/S74 -> 1.2186596 | L73: 0 | M73: ='CDM - Q'!P202/'CDM - Q'!O202*100 -> 95.426855 | N73: =AVERAGEIFS('JN - M'!I:I,'JN - M'!B:B,">="&EDATE('JN - Q'!B73,-2),'JN - M'!B:B,"<="&EOMONTH('JN - Q'!B73,0)) -> 0.43666667 | O73: =AVERAGEIFS('JN - M'!J:J,'JN - M'!$B:$B,">="&EDATE('JN - Q'!$B73,-2),'JN - M'!$B:$B,"<="&EOMONTH('JN - Q'!$B73,0)) -> 0.15914391 | S73: =(H73/H69-1)*100+2 -> 2.3126591
B74: 35765 | C74: ='CDM - Q'!M203 -> 496112 | D74: 555038.5 | E74: =AVERAGEIFS('JN - M'!G:G,'JN - M'!$B:$B,">="&EDATE('JN - Q'!$B74,-2),'JN - M'!$B:$B,"<="&EOMONTH('JN - Q'!$B74,0)) -> 83.733333 | F74: =AVERAGEIFS('JN - M'!H:H,'JN - M'!$B:$B,">="&EDATE('JN - Q'!$B74,-2),'JN - M'!$B:$B,"<="&EOMONTH('JN - Q'!$B74,0)) -> 84.619059 | G74: =AVERAGEIFS('JN - M'!D:D,'JN - M'!$B:$B,">="&EDATE('JN - Q'!$B74,-2),'JN - M'!$B:$B,"<="&EOMONTH('JN - Q'!$B74,0)) -> 103.06781 | H74: =AVERAGEIFS('JN - M'!E:E,'JN - M'!$B:$B,">="&EDATE('JN - Q'!$B74,-2),'JN - M'!$B:$B,"<="&EOMONTH('JN - Q'!$B74,0)) -> 106.91652 | I74: =AVERAGEIFS('JN - M'!F:F,'JN - M'!$B:$B,">="&EDATE('JN - Q'!$B74,-2),'JN - M'!$B:$B,"<="&EOMONTH('JN - Q'!$B74,0)) -> 106.91652 | J74: =AVERAGEIFS('JN - M'!K:K,'JN - M'!$B:$B,">="&EDATE('JN - Q'!$B74,-2),'JN - M'!$B:$B,"<="&EOMONTH('JN - Q'!$B74,0)) -> 3.5153333 | K74: =K75*S74/S75 -> 1.2841984 | L74: 0 | M74: ='CDM - Q'!P203/'CDM - Q'!O203*100 -> 97.458629 | N74: =AVERAGEIFS('JN - M'!I:I,'JN - M'!B:B,">="&EDATE('JN - Q'!B74,-2),'JN - M'!B:B,"<="&EOMONTH('JN - Q'!B74,0)) -> 0.42333333 | O74: =AVERAGEIFS('JN - M'!J:J,'JN - M'!$B:$B,">="&EDATE('JN - Q'!$B74,-2),'JN - M'!$B:$B,"<="&EOMONTH('JN - Q'!$B74,0)) -> -0.02110735 | S74: =(H74/H70-1)*100+2 -> 2.4370326
A75: 1998 | B75: 35855 | C75: ='CDM - Q'!M204 -> 488264.2 | D75: 545621 | E75: =AVERAGEIFS('JN - M'!G:G,'JN - M'!$B:$B,">="&EDATE('JN - Q'!$B75,-2),'JN - M'!$B:$B,"<="&EOMONTH('JN - Q'!$B75,0)) -> 88 | F75: =AVERAGEIFS('JN - M'!H:H,'JN - M'!$B:$B,">="&EDATE('JN - Q'!$B75,-2),'JN - M'!$B:$B,"<="&EOMONTH('JN - Q'!$B75,0)) -> 84.008643 | G75: =AVERAGEIFS('JN - M'!D:D,'JN - M'!$B:$B,">="&EDATE('JN - Q'!$B75,-2),'JN - M'!$B:$B,"<="&EOMONTH('JN - Q'!$B75,0)) -> 102.90049 | H75: =AVERAGEIFS('JN - M'!E:E,'JN - M'!$B:$B,">="&EDATE('JN - Q'!$B75,-2),'JN - M'!$B:$B,"<="&EOMONTH('JN - Q'!$B75,0)) -> 106.28138 | I75: =AVERAGEIFS('JN - M'!F:F,'JN - M'!$B:$B,">="&EDATE('JN - Q'!$B75,-2),'JN - M'!$B:$B,"<="&EOMONTH('JN - Q'!$B75,0)) -> 106.28138 | J75: =AVERAGEIFS('JN - M'!K:K,'JN - M'!$B:$B,">="&EDATE('JN - Q'!$B75,-2),'JN - M'!$B:$B,"<="&EOMONTH('JN - Q'!$B75,0)) -> 3.6824482 | K75: =K76*S75/S76 -> 1.2373035 | L75: 0 | M75: ='CDM - Q'!P204/'CDM - Q'!O204*100 -> 95.308741 | N75: =AVERAGEIFS('JN - M'!I:I,'JN - M'!B:B,">="&EDATE('JN - Q'!B75,-2),'JN - M'!B:B,"<="&EOMONTH('JN - Q'!B75,0)) -> 0.43333333 | O75: =AVERAGEIFS('JN - M'!J:J,'JN - M'!$B:$B,">="&EDATE('JN - Q'!$B75,-2),'JN - M'!$B:$B,"<="&EOMONTH('JN - Q'!$B75,0)) -> 0.24922869 | S75: =(H75/H71-1)*100+2 -> 2.3480398
B76: 35947 | C76: ='CDM - Q'!M205 -> 485566.6 | D76: 541538.8 | E76: =AVERAGEIFS('JN - M'!G:G,'JN - M'!$B:$B,">="&EDATE('JN - Q'!$B76,-2),'JN - M'!$B:$B,"<="&EOMONTH('JN - Q'!$B76,0)) -> 79.1 | F76: =AVERAGEIFS('JN - M'!H:H,'JN - M'!$B:$B,">="&EDATE('JN - Q'!$B76,-2),'JN - M'!$B:$B,"<="&EOMONTH('JN - Q'!$B76,0)) -> 81.899891 | G76: =AVERAGEIFS('JN - M'!D:D,'JN - M'!$B:$B,">="&EDATE('JN - Q'!$B76,-2),'JN - M'!$B:$B,"<="&EOMONTH('JN - Q'!$B76,0)) -> 102.75282 | H76: =AVERAGEIFS('JN - M'!E:E,'JN - M'!$B:$B,">="&EDATE('JN - Q'!$B76,-2),'JN - M'!$B:$B,"<="&EOMONTH('JN - Q'!$B76,0)) -> 106.77538 | I76: =AVERAGEIFS('JN - M'!F:F,'JN - M'!$B:$B,">="&EDATE('JN - Q'!$B76,-2),'JN - M'!$B:$B,"<="&EOMONTH('JN - Q'!$B76,0)) -> 106.77538 | J76: =AVERAGEIFS('JN - M'!K:K,'JN - M'!$B:$B,">="&EDATE('JN - Q'!$B76,-2),'JN - M'!$B:$B,"<="&EOMONTH('JN - Q'!$B76,0)) -> 4.0776016 | K76: =K77*S76/S77 -> 1.2461577 | L76: 0 | M76: ='CDM - Q'!P205/'CDM - Q'!O205*100 -> 96.099448 | N76: =AVERAGEIFS('JN - M'!I:I,'JN - M'!B:B,">="&EDATE('JN - Q'!B76,-2),'JN - M'!B:B,"<="&EOMONTH('JN - Q'!B76,0)) -> 0.41666667 | O76: =AVERAGEIFS('JN - M'!J:J,'JN - M'!$B:$B,">="&EDATE('JN - Q'!$B76,-2),'JN - M'!$B:$B,"<="&EOMONTH('JN - Q'!$B76,0)) -> 0.16260766 | S76: =(H76/H72-1)*100+2 -> 2.3648425
B77: 36039 | C77: ='CDM - Q'!M206 -> 486201.9 | D77: 540269.1 | E77: =AVERAGEIFS('JN - M'!G:G,'JN - M'!$B:$B,">="&EDATE('JN - Q'!$B77,-2),'JN - M'!$B:$B,"<="&EOMONTH('JN - Q'!$B77,0)) -> 82.566667 | F77: =AVERAGEIFS('JN - M'!H:H,'JN - M'!$B:$B,">="&EDATE('JN - Q'!$B77,-2),'JN - M'!$B:$B,"<="&EOMONTH('JN - Q'!$B77,0)) -> 82.764945 | G77: =AVERAGEIFS('JN - M'!D:D,'JN - M'!$B:$B,">="&EDATE('JN - Q'!$B77,-2),'JN - M'!$B:$B,"<="&EOMONTH('JN - Q'!$B77,0)) -> 102.65877 | H77: =AVERAGEIFS('JN - M'!E:E,'JN - M'!$B:$B,">="&EDATE('JN - Q'!$B77,-2),'JN - M'!$B:$B,"<="&EOMONTH('JN - Q'!$B77,0)) -> 106.52838 | I77: =AVERAGEIFS('JN - M'!F:F,'JN - M'!$B:$B,">="&EDATE('JN - Q'!$B77,-2),'JN - M'!$B:$B,"<="&EOMONTH('JN - Q'!$B77,0)) -> 106.52838 | J77: =AVERAGEIFS('JN - M'!K:K,'JN - M'!$B:$B,">="&EDATE('JN - Q'!$B77,-2),'JN - M'!$B:$B,"<="&EOMONTH('JN - Q'!$B77,0)) -> 4.2504816 | K77: =K78*S77/S78 -> 1.1413207 | L77: 0 | M77: ='CDM - Q'!P206/'CDM - Q'!O206*100 -> 97.425077 | N77: =AVERAGEIFS('JN - M'!I:I,'JN - M'!B:B,">="&EDATE('JN - Q'!B77,-2),'JN - M'!B:B,"<="&EOMONTH('JN - Q'!B77,0)) -> 0.36333333 | O77: =AVERAGEIFS('JN - M'!J:J,'JN - M'!$B:$B,">="&EDATE('JN - Q'!$B77,-2),'JN - M'!$B:$B,"<="&EOMONTH('JN - Q'!$B77,0)) -> -0.0012620772 | S77: =(H77/H73-1)*100+2 -> 2.1658925
B78: 36130 | C78: ='CDM - Q'!M207 -> 490396.6 | D78: 545933.8 | E78: =AVERAGEIFS('JN - M'!G:G,'JN - M'!$B:$B,">="&EDATE('JN - Q'!$B78,-2),'JN - M'!$B:$B,"<="&EOMONTH('JN - Q'!$B78,0)) -> 81.466667 | F78: =AVERAGEIFS('JN - M'!H:H,'JN - M'!$B:$B,">="&EDATE('JN - Q'!$B78,-2),'JN - M'!$B:$B,"<="&EOMONTH('JN - Q'!$B78,0)) -> 82.348159 | G78: =AVERAGEIFS('JN - M'!D:D,'JN - M'!$B:$B,">="&EDATE('JN - Q'!$B78,-2),'JN - M'!$B:$B,"<="&EOMONTH('JN - Q'!$B78,0)) -> 102.72689 | H78: =AVERAGEIFS('JN - M'!E:E,'JN - M'!$B:$B,">="&EDATE('JN - Q'!$B78,-2),'JN - M'!$B:$B,"<="&EOMONTH('JN - Q'!$B78,0)) -> 106.91652 | I78: =AVERAGEIFS('JN - M'!F:F,'JN - M'!$B:$B,">="&EDATE('JN - Q'!$B78,-2),'JN - M'!$B:$B,"<="&EOMONTH('JN - Q'!$B78,0)) -> 106.91652 | J78: =AVERAGEIFS('JN - M'!K:K,'JN - M'!$B:$B,">="&EDATE('JN - Q'!$B78,-2),'JN - M'!$B:$B,"<="&EOMONTH('JN - Q'!$B78,0)) -> 4.4145176 | K78: =K79*S78/S79 -> 1.0539033 | L78: 0 | M78: ='CDM - Q'!P207/'CDM - Q'!O207*100 -> 88.907935 | N78: =AVERAGEIFS('JN - M'!I:I,'JN - M'!B:B,">="&EDATE('JN - Q'!B78,-2),'JN - M'!B:B,"<="&EOMONTH('JN - Q'!B78,0)) -> 0.21666667 | O78: =AVERAGEIFS('JN - M'!J:J,'JN - M'!$B:$B,">="&EDATE('JN - Q'!$B78,-2),'JN - M'!$B:$B,"<="&EOMONTH('JN - Q'!$B78,0)) -> -0.086000547 | S78: =(H78/H74-1)*100+2 -> 2
A79: 1999 | B79: 36220 | C79: ='CDM - Q'!M208 -> 483236.2 | D79: 534638 | E79: =AVERAGEIFS('JN - M'!G:G,'JN - M'!$B:$B,">="&EDATE('JN - Q'!$B79,-2),'JN - M'!$B:$B,"<="&EOMONTH('JN - Q'!$B79,0)) -> 87.633333 | F79: =AVERAGEIFS('JN - M'!H:H,'JN - M'!$B:$B,">="&EDATE('JN - Q'!$B79,-2),'JN - M'!$B:$B,"<="&EOMONTH('JN - Q'!$B79,0)) -> 83.653536 | G79: =AVERAGEIFS('JN - M'!D:D,'JN - M'!$B:$B,">="&EDATE('JN - Q'!$B79,-2),'JN - M'!$B:$B,"<="&EOMONTH('JN - Q'!$B79,0)) -> 102.80043 | H79: =AVERAGEIFS('JN - M'!E:E,'JN - M'!$B:$B,">="&EDATE('JN - Q'!$B79,-2),'JN - M'!$B:$B,"<="&EOMONTH('JN - Q'!$B79,0)) -> 106.38724 | I79: =AVERAGEIFS('JN - M'!F:F,'JN - M'!$B:$B,">="&EDATE('JN - Q'!$B79,-2),'JN - M'!$B:$B,"<="&EOMONTH('JN - Q'!$B79,0)) -> 106.38724 | J79: =AVERAGEIFS('JN - M'!K:K,'JN - M'!$B:$B,">="&EDATE('JN - Q'!$B79,-2),'JN - M'!$B:$B,"<="&EOMONTH('JN - Q'!$B79,0)) -> 4.6179154 | K79: =K80*S79/S80 -> 1.1063886 | L79: 0 | M79: ='CDM - Q'!P208/'CDM - Q'!O208*100 -> 85.317554 | N79: =AVERAGEIFS('JN - M'!I:I,'JN - M'!B:B,">="&EDATE('JN - Q'!B79,-2),'JN - M'!B:B,"<="&EOMONTH('JN - Q'!B79,0)) -> 0.16333333 | O79: =AVERAGEIFS('JN - M'!J:J,'JN - M'!$B:$B,">="&EDATE('JN - Q'!$B79,-2),'JN - M'!$B:$B,"<="&EOMONTH('JN - Q'!$B79,0)) -> -0.37396138 | S79: =(H79/H75-1)*100+2 -> 2.0996016
B80: 36312 | C80: ='CDM - Q'!M209 -> 485679 | D80: 535350.2 | E80: =AVERAGEIFS('JN - M'!G:G,'JN - M'!$B:$B,">="&EDATE('JN - Q'!$B80,-2),'JN - M'!$B:$B,"<="&EOMONTH('JN - Q'!$B80,0)) -> 81.766667 | F80: =AVERAGEIFS('JN - M'!H:H,'JN - M'!$B:$B,">="&EDATE('JN - Q'!$B80,-2),'JN - M'!$B:$B,"<="&EOMONTH('JN - Q'!$B80,0)) -> 84.59255 | G80: =AVERAGEIFS('JN - M'!D:D,'JN - M'!$B:$B,">="&EDATE('JN - Q'!$B80,-2),'JN - M'!$B:$B,"<="&EOMONTH('JN - Q'!$B80,0)) -> 102.72696 | H80: =AVERAGEIFS('JN - M'!E:E,'JN - M'!$B:$B,">="&EDATE('JN - Q'!$B80,-2),'JN - M'!$B:$B,"<="&EOMONTH('JN - Q'!$B80,0)) -> 106.84595 | I80: =AVERAGEIFS('JN - M'!F:F,'JN - M'!$B:$B,">="&EDATE('JN - Q'!$B80,-2),'JN - M'!$B:$B,"<="&EOMONTH('JN - Q'!$B80,0)) -> 106.84595 | J80: =AVERAGEIFS('JN - M'!K:K,'JN - M'!$B:$B,">="&EDATE('JN - Q'!$B80,-2),'JN - M'!$B:$B,"<="&EOMONTH('JN - Q'!$B80,0)) -> 4.7298769 | K80: =K81*S80/S81 -> 1.0887316 | L80: 0 | M80: ='CDM - Q'!P209/'CDM - Q'!O209*100 -> 87.676074 | N80: =AVERAGEIFS('JN - M'!I:I,'JN - M'!B:B,">="&EDATE('JN - Q'!B80,-2),'JN - M'!B:B,"<="&EOMONTH('JN - Q'!B80,0)) -> 0 | O80: =AVERAGEIFS('JN - M'!J:J,'JN - M'!$B:$B,">="&EDATE('JN - Q'!$B80,-2),'JN - M'!$B:$B,"<="&EOMONTH('JN - Q'!$B80,0)) -> -1.0343889 | S80: =(H80/H76-1)*100+2 -> 2.0660939
B81: 36404 | C81: ='CDM - Q'!M210 -> 488376 | D81: 534866.8 | E81: =AVERAGEIFS('JN - M'!G:G,'JN - M'!$B:$B,">="&EDATE('JN - Q'!$B81,-2),'JN - M'!$B:$B,"<="&EOMONTH('JN - Q'!$B81,0)) -> 86.3 | F81: =AVERAGEIFS('JN - M'!H:H,'JN - M'!$B:$B,">="&EDATE('JN - Q'!$B81,-2),'JN - M'!$B:$B,"<="&EOMONTH('JN - Q'!$B81,0)) -> 86.506657 | G81: =AVERAGEIFS('JN - M'!D:D,'JN - M'!$B:$B,">="&EDATE('JN - Q'!$B81,-2),'JN - M'!$B:$B,"<="&EOMONTH('JN - Q'!$B81,0)) -> 102.63052 | H81: =AVERAGEIFS('JN - M'!E:E,'JN - M'!$B:$B,">="&EDATE('JN - Q'!$B81,-2),'JN - M'!$B:$B,"<="&EOMONTH('JN - Q'!$B81,0)) -> 106.59895 | I81: =AVERAGEIFS('JN - M'!F:F,'JN - M'!$B:$B,">="&EDATE('JN - Q'!$B81,-2),'JN - M'!$B:$B,"<="&EOMONTH('JN - Q'!$B81,0)) -> 106.59895 | J81: =AVERAGEIFS('JN - M'!K:K,'JN - M'!$B:$B,">="&EDATE('JN - Q'!$B81,-2),'JN - M'!$B:$B,"<="&EOMONTH('JN - Q'!$B81,0)) -> 4.7360932 | K81: =K82*S81/S82 -> 1.0888124 | L81: 0 | M81: ='CDM - Q'!P210/'CDM - Q'!O210*100 -> 87.50361 | N81: =AVERAGEIFS('JN - M'!I:I,'JN - M'!B:B,">="&EDATE('JN - Q'!B81,-2),'JN - M'!B:B,"<="&EOMONTH('JN - Q'!B81,0)) -> 0 | O81: =AVERAGEIFS('JN - M'!J:J,'JN - M'!$B:$B,">="&EDATE('JN - Q'!$B81,-2),'JN - M'!$B:$B,"<="&EOMONTH('JN - Q'!$B81,0)) -> -0.66624818 | S81: =(H81/H77-1)*100+2 -> 2.0662471
B82: 36495 | C82: ='CDM - Q'!M211 -> 488083.5 | D82: 533984 | E82: =AVERAGEIFS('JN - M'!G:G,'JN - M'!$B:$B,">="&EDATE('JN - Q'!$B82,-2),'JN - M'!$B:$B,"<="&EOMONTH('JN - Q'!$B82,0)) -> 87.1 | F82: =AVERAGEIFS('JN - M'!H:H,'JN - M'!$B:$B,">="&EDATE('JN - Q'!$B82,-2),'JN - M'!$B:$B,"<="&EOMONTH('JN - Q'!$B82,0)) -> 88.111971 | G82: =AVERAGEIFS('JN - M'!D:D,'JN - M'!$B:$B,">="&EDATE('JN - Q'!$B82,-2),'JN - M'!$B:$B,"<="&EOMONTH('JN - Q'!$B82,0)) -> 102.60388 | H82: =AVERAGEIFS('JN - M'!E:E,'JN - M'!$B:$B,">="&EDATE('JN - Q'!$B82,-2),'JN - M'!$B:$B,"<="&EOMONTH('JN - Q'!$B82,0)) -> 106.74009 | I82: =AVERAGEIFS('JN - M'!F:F,'JN - M'!$B:$B,">="&EDATE('JN - Q'!$B82,-2),'JN - M'!$B:$B,"<="&EOMONTH('JN - Q'!$B82,0)) -> 106.74009 | J82: =AVERAGEIFS('JN - M'!K:K,'JN - M'!$B:$B,">="&EDATE('JN - Q'!$B82,-2),'JN - M'!$B:$B,"<="&EOMONTH('JN - Q'!$B82,0)) -> 4.6208338 | K82: =K83*S82/S83 -> 0.96694762 | L82: 0 | M82: ='CDM - Q'!P211/'CDM - Q'!O211*100 -> 85.514384 | N82: =AVERAGEIFS('JN - M'!I:I,'JN - M'!B:B,">="&EDATE('JN - Q'!B82,-2),'JN - M'!B:B,"<="&EOMONTH('JN - Q'!B82,0)) -> 0 | O82: =AVERAGEIFS('JN - M'!J:J,'JN - M'!$B:$B,">="&EDATE('JN - Q'!$B82,-2),'JN - M'!$B:$B,"<="&EOMONTH('JN - Q'!$B82,0)) -> -0.73936192 | S82: =(H82/H78-1)*100+2 -> 1.8349835
A83: 2000 | B83: 36586 | C83: ='CDM - Q'!M212 -> 497255.3 | D83: 542387.7 | E83: =AVERAGEIFS('JN - M'!G:G,'JN - M'!$B:$B,">="&EDATE('JN - Q'!$B83,-2),'JN - M'!$B:$B,"<="&EOMONTH('JN - Q'!$B83,0)) -> 93.366667 | F83: =AVERAGEIFS('JN - M'!H:H,'JN - M'!$B:$B,">="&EDATE('JN - Q'!$B83,-2),'JN - M'!$B:$B,"<="&EOMONTH('JN - Q'!$B83,0)) -> 89.302202 | G83: =AVERAGEIFS('JN - M'!D:D,'JN - M'!$B:$B,">="&EDATE('JN - Q'!$B83,-2),'JN - M'!$B:$B,"<="&EOMONTH('JN - Q'!$B83,0)) -> 102.56678 | H83: =AVERAGEIFS('JN - M'!E:E,'JN - M'!$B:$B,">="&EDATE('JN - Q'!$B83,-2),'JN - M'!$B:$B,"<="&EOMONTH('JN - Q'!$B83,0)) -> 106.17552 | I83: =AVERAGEIFS('JN - M'!F:F,'JN - M'!$B:$B,">="&EDATE('JN - Q'!$B83,-2),'JN - M'!$B:$B,"<="&EOMONTH('JN - Q'!$B83,0)) -> 106.17552 | J83: =AVERAGEIFS('JN - M'!K:K,'JN - M'!$B:$B,">="&EDATE('JN - Q'!$B83,-2),'JN - M'!$B:$B,"<="&EOMONTH('JN - Q'!$B83,0)) -> 4.8002897 | K83: =K84*S83/S84 -> 0.94903734 | L83: 0 | M83: ='CDM - Q'!P212/'CDM - Q'!O212*100 -> 87.593089 | N83: =AVERAGEIFS('JN - M'!I:I,'JN - M'!B:B,">="&EDATE('JN - Q'!B83,-2),'JN - M'!B:B,"<="&EOMONTH('JN - Q'!B83,0)) -> 0 | O83: =AVERAGEIFS('JN - M'!J:J,'JN - M'!$B:$B,">="&EDATE('JN - Q'!$B83,-2),'JN - M'!$B:$B,"<="&EOMONTH('JN - Q'!$B83,0)) -> -0.26456666 | S83: =(H83/H79-1)*100+2 -> 1.800995
B84: 36678 | C84: ='CDM - Q'!M213 -> 500296.7 | D84: 544166.8 | E84: =AVERAGEIFS('JN - M'!G:G,'JN - M'!$B:$B,">="&EDATE('JN - Q'!$B84,-2),'JN - M'!$B:$B,"<="&EOMONTH('JN - Q'!$B84,0)) -> 88.366667 | F84: =AVERAGEIFS('JN - M'!H:H,'JN - M'!$B:$B,">="&EDATE('JN - Q'!$B84,-2),'JN - M'!$B:$B,"<="&EOMONTH('JN - Q'!$B84,0)) -> 91.238881 | G84: =AVERAGEIFS('JN - M'!D:D,'JN - M'!$B:$B,">="&EDATE('JN - Q'!$B84,-2),'JN - M'!$B:$B,"<="&EOMONTH('JN - Q'!$B84,0)) -> 102.43401 | H84: =AVERAGEIFS('JN - M'!E:E,'JN - M'!$B:$B,">="&EDATE('JN - Q'!$B84,-2),'JN - M'!$B:$B,"<="&EOMONTH('JN - Q'!$B84,0)) -> 105.93708 | I84: =AVERAGEIFS('JN - M'!F:F,'JN - M'!$B:$B,">="&EDATE('JN - Q'!$B84,-2),'JN - M'!$B:$B,"<="&EOMONTH('JN - Q'!$B84,0)) -> 105.93708 | J84: =AVERAGEIFS('JN - M'!K:K,'JN - M'!$B:$B,">="&EDATE('JN - Q'!$B84,-2),'JN - M'!$B:$B,"<="&EOMONTH('JN - Q'!$B84,0)) -> 4.7008053 | K84: =K85*S84/S85 -> 0.60565578 | L84: 0 | M84: ='CDM - Q'!P213/'CDM - Q'!O213*100 -> 86.119481 | N84: =AVERAGEIFS('JN - M'!I:I,'JN - M'!B:B,">="&EDATE('JN - Q'!B84,-2),'JN - M'!B:B,"<="&EOMONTH('JN - Q'!B84,0)) -> 0 | O84: =AVERAGEIFS('JN - M'!J:J,'JN - M'!$B:$B,">="&EDATE('JN - Q'!$B84,-2),'JN - M'!$B:$B,"<="&EOMONTH('JN - Q'!$B84,0)) -> -0.1157783 | S84: =(H84/H80-1)*100+2 -> 1.1493574
B85: 36770 | C85: ='CDM - Q'!M214 -> 500070.9 | D85: 542139.6 | E85: =AVERAGEIFS('JN - M'!G:G,'JN - M'!$B:$B,">="&EDATE('JN - Q'!$B85,-2),'JN - M'!$B:$B,"<="&EOMONTH('JN - Q'!$B85,0)) -> 92.566667 | F85: =AVERAGEIFS('JN - M'!H:H,'JN - M'!$B:$B,">="&EDATE('JN - Q'!$B85,-2),'JN - M'!$B:$B,"<="&EOMONTH('JN - Q'!$B85,0)) -> 92.902715 | G85: =AVERAGEIFS('JN - M'!D:D,'JN - M'!$B:$B,">="&EDATE('JN - Q'!$B85,-2),'JN - M'!$B:$B,"<="&EOMONTH('JN - Q'!$B85,0)) -> 102.16846 | H85: =AVERAGEIFS('JN - M'!E:E,'JN - M'!$B:$B,">="&EDATE('JN - Q'!$B85,-2),'JN - M'!$B:$B,"<="&EOMONTH('JN - Q'!$B85,0)) -> 105.56238 | I85: =AVERAGEIFS('JN - M'!F:F,'JN - M'!$B:$B,">="&EDATE('JN - Q'!$B85,-2),'JN - M'!$B:$B,"<="&EOMONTH('JN - Q'!$B85,0)) -> 105.56238 | J85: =AVERAGEIFS('JN - M'!K:K,'JN - M'!$B:$B,">="&EDATE('JN - Q'!$B85,-2),'JN - M'!$B:$B,"<="&EOMONTH('JN - Q'!$B85,0)) -> 4.6611242 | K85: =K86*S85/S86 -> 0.54149346 | L85: 0 | M85: ='CDM - Q'!P214/'CDM - Q'!O214*100 -> 87.593432 | N85: =AVERAGEIFS('JN - M'!I:I,'JN - M'!B:B,">="&EDATE('JN - Q'!B85,-2),'JN - M'!B:B,"<="&EOMONTH('JN - Q'!B85,0)) -> 0.16666667 | O85: =AVERAGEIFS('JN - M'!J:J,'JN - M'!$B:$B,">="&EDATE('JN - Q'!$B85,-2),'JN - M'!$B:$B,"<="&EOMONTH('JN - Q'!$B85,0)) -> 0.05835459 | S85: =(H85/H81-1)*100+2 -> 1.027596
B86: 36861 | C86: ='CDM - Q'!M215 -> 505253.3 | D86: 546255.1 | E86: =AVERAGEIFS('JN - M'!G:G,'JN - M'!$B:$B,">="&EDATE('JN - Q'!$B86,-2),'JN - M'!$B:$B,"<="&EOMONTH('JN - Q'!$B86,0)) -> 91.933333 | F86: =AVERAGEIFS('JN - M'!H:H,'JN - M'!$B:$B,">="&EDATE('JN - Q'!$B86,-2),'JN - M'!$B:$B,"<="&EOMONTH('JN - Q'!$B86,0)) -> 93.058955 | G86: =AVERAGEIFS('JN - M'!D:D,'JN - M'!$B:$B,">="&EDATE('JN - Q'!$B86,-2),'JN - M'!$B:$B,"<="&EOMONTH('JN - Q'!$B86,0)) -> 101.93611 | H86: =AVERAGEIFS('JN - M'!E:E,'JN - M'!$B:$B,">="&EDATE('JN - Q'!$B86,-2),'JN - M'!$B:$B,"<="&EOMONTH('JN - Q'!$B86,0)) -> 105.32394 | I86: =AVERAGEIFS('JN - M'!F:F,'JN - M'!$B:$B,">="&EDATE('JN - Q'!$B86,-2),'JN - M'!$B:$B,"<="&EOMONTH('JN - Q'!$B86,0)) -> 105.32394 | J86: =AVERAGEIFS('JN - M'!K:K,'JN - M'!$B:$B,">="&EDATE('JN - Q'!$B86,-2),'JN - M'!$B:$B,"<="&EOMONTH('JN - Q'!$B86,0)) -> 4.7315239 | K86: =K87*S86/S87 -> 0.35477727 | L86: 0 | M86: ='CDM - Q'!P215/'CDM - Q'!O215*100 -> 89.020398 | N86: =AVERAGEIFS('JN - M'!I:I,'JN - M'!B:B,">="&EDATE('JN - Q'!B86,-2),'JN - M'!B:B,"<="&EOMONTH('JN - Q'!B86,0)) -> 0.25 | O86: =AVERAGEIFS('JN - M'!J:J,'JN - M'!$B:$B,">="&EDATE('JN - Q'!$B86,-2),'JN - M'!$B:$B,"<="&EOMONTH('JN - Q'!$B86,0)) -> -0.050441896 | S86: =(H86/H82-1)*100+2 -> 0.67326339
A87: 2001 | B87: 36951 | C87: ='CDM - Q'!M216 -> 508208 | D87: 550226.7 | E87: =AVERAGEIFS('JN - M'!G:G,'JN - M'!$B:$B,">="&EDATE('JN - Q'!$B87,-2),'JN - M'!$B:$B,"<="&EOMONTH('JN - Q'!$B87,0)) -> 95.733333 | F87: =AVERAGEIFS('JN - M'!H:H,'JN - M'!$B:$B,">="&EDATE('JN - Q'!$B87,-2),'JN - M'!$B:$B,"<="&EOMONTH('JN - Q'!$B87,0)) -> 91.555671 | G87: =AVERAGEIFS('JN - M'!D:D,'JN - M'!$B:$B,">="&EDATE('JN - Q'!$B87,-2),'JN - M'!$B:$B,"<="&EOMONTH('JN - Q'!$B87,0)) -> 101.70376 | H87: =AVERAGEIFS('JN - M'!E:E,'JN - M'!$B:$B,">="&EDATE('JN - Q'!$B87,-2),'JN - M'!$B:$B,"<="&EOMONTH('JN - Q'!$B87,0)) -> 105.15362 | I87: =AVERAGEIFS('JN - M'!F:F,'JN - M'!$B:$B,">="&EDATE('JN - Q'!$B87,-2),'JN - M'!$B:$B,"<="&EOMONTH('JN - Q'!$B87,0)) -> 105.15362 | J87: =AVERAGEIFS('JN - M'!K:K,'JN - M'!$B:$B,">="&EDATE('JN - Q'!$B87,-2),'JN - M'!$B:$B,"<="&EOMONTH('JN - Q'!$B87,0)) -> 4.7591107 | K87: =K88*S87/S88 -> 0.54673138 | L87: 0 | M87: ='CDM - Q'!P216/'CDM - Q'!O216*100 -> 89.721071 | N87: =AVERAGEIFS('JN - M'!I:I,'JN - M'!B:B,">="&EDATE('JN - Q'!B87,-2),'JN - M'!B:B,"<="&EOMONTH('JN - Q'!B87,0)) -> 0.18333333 | O87: =AVERAGEIFS('JN - M'!J:J,'JN - M'!$B:$B,">="&EDATE('JN - Q'!$B87,-2),'JN - M'!$B:$B,"<="&EOMONTH('JN - Q'!$B87,0)) -> -0.44268003 | S87: =(H87/H83-1)*100+2 -> 1.0375361
B88: 37043 | C88: ='CDM - Q'!M217 -> 504352.5 | D88: 542516.1 | E88: =AVERAGEIFS('JN - M'!G:G,'JN - M'!$B:$B,">="&EDATE('JN - Q'!$B88,-2),'JN - M'!$B:$B,"<="&EOMONTH('JN - Q'!$B88,0)) -> 87.1 | F88: =AVERAGEIFS('JN - M'!H:H,'JN - M'!$B:$B,">="&EDATE('JN - Q'!$B88,-2),'JN - M'!$B:$B,"<="&EOMONTH('JN - Q'!$B88,0)) -> 89.788743 | G88: =AVERAGEIFS('JN - M'!D:D,'JN - M'!$B:$B,">="&EDATE('JN - Q'!$B88,-2),'JN - M'!$B:$B,"<="&EOMONTH('JN - Q'!$B88,0)) -> 101.53779 | H88: =AVERAGEIFS('JN - M'!E:E,'JN - M'!$B:$B,">="&EDATE('JN - Q'!$B88,-2),'JN - M'!$B:$B,"<="&EOMONTH('JN - Q'!$B88,0)) -> 104.94924 | I88: =AVERAGEIFS('JN - M'!F:F,'JN - M'!$B:$B,">="&EDATE('JN - Q'!$B88,-2),'JN - M'!$B:$B,"<="&EOMONTH('JN - Q'!$B88,0)) -> 104.94924 | J88: =AVERAGEIFS('JN - M'!K:K,'JN - M'!$B:$B,">="&EDATE('JN - Q'!$B88,-2),'JN - M'!$B:$B,"<="&EOMONTH('JN - Q'!$B88,0)) -> 4.9094051 | K88: =K89*S88/S89 -> 0.56253362 | L88: 0 | M88: ='CDM - Q'!P217/'CDM - Q'!O217*100 -> 90.646881 | N88: =AVERAGEIFS('JN - M'!I:I,'JN - M'!B:B,">="&EDATE('JN - Q'!B88,-2),'JN - M'!B:B,"<="&EOMONTH('JN - Q'!B88,0)) -> 0 | O88: =AVERAGEIFS('JN - M'!J:J,'JN - M'!$B:$B,">="&EDATE('JN - Q'!$B88,-2),'JN - M'!$B:$B,"<="&EOMONTH('JN - Q'!$B88,0)) -> -1.2768296 | S88: =(H88/H84-1)*100+2 -> 1.0675241
B89: 37135 | C89: ='CDM - Q'!M218 -> 498415 | D89: 534275.7 | E89: =AVERAGEIFS('JN - M'!G:G,'JN - M'!$B:$B,">="&EDATE('JN - Q'!$B89,-2),'JN - M'!$B:$B,"<="&EOMONTH('JN - Q'!$B89,0)) -> 87.633333 | F89: =AVERAGEIFS('JN - M'!H:H,'JN - M'!$B:$B,">="&EDATE('JN - Q'!$B89,-2),'JN - M'!$B:$B,"<="&EOMONTH('JN - Q'!$B89,0)) -> 88.039931 | G89: =AVERAGEIFS('JN - M'!D:D,'JN - M'!$B:$B,">="&EDATE('JN - Q'!$B89,-2),'JN - M'!$B:$B,"<="&EOMONTH('JN - Q'!$B89,0)) -> 101.30544 | H89: =AVERAGEIFS('JN - M'!E:E,'JN - M'!$B:$B,">="&EDATE('JN - Q'!$B89,-2),'JN - M'!$B:$B,"<="&EOMONTH('JN - Q'!$B89,0)) -> 104.67673 | I89: =AVERAGEIFS('JN - M'!F:F,'JN - M'!$B:$B,">="&EDATE('JN - Q'!$B89,-2),'JN - M'!$B:$B,"<="&EOMONTH('JN - Q'!$B89,0)) -> 104.67673 | J89: =AVERAGEIFS('JN - M'!K:K,'JN - M'!$B:$B,">="&EDATE('JN - Q'!$B89,-2),'JN - M'!$B:$B,"<="&EOMONTH('JN - Q'!$B89,0)) -> 5.1135068 | K89: =K90*S89/S90 -> 0.61180126 | L89: 0 | M89: ='CDM - Q'!P218/'CDM - Q'!O218*100 -> 89.702019 | N89: =AVERAGEIFS('JN - M'!I:I,'JN - M'!B:B,">="&EDATE('JN - Q'!B89,-2),'JN - M'!B:B,"<="&EOMONTH('JN - Q'!B89,0)) -> 0 | O89: =AVERAGEIFS('JN - M'!J:J,'JN - M'!$B:$B,">="&EDATE('JN - Q'!$B89,-2),'JN - M'!$B:$B,"<="&EOMONTH('JN - Q'!$B89,0)) -> -1.7611091 | S89: =(H89/H85-1)*100+2 -> 1.1610197
B90: 37226 | C90: ='CDM - Q'!M219 -> 497326.7 | D90: 531827.4 | E90: =AVERAGEIFS('JN - M'!G:G,'JN - M'!$B:$B,">="&EDATE('JN - Q'!$B90,-2),'JN - M'!$B:$B,"<="&EOMONTH('JN - Q'!$B90,0)) -> 85.266667 | F90: =AVERAGEIFS('JN - M'!H:H,'JN - M'!$B:$B,">="&EDATE('JN - Q'!$B90,-2),'JN - M'!$B:$B,"<="&EOMONTH('JN - Q'!$B90,0)) -> 86.288561 | G90: =AVERAGEIFS('JN - M'!D:D,'JN - M'!$B:$B,">="&EDATE('JN - Q'!$B90,-2),'JN - M'!$B:$B,"<="&EOMONTH('JN - Q'!$B90,0)) -> 101.0399 | H90: =AVERAGEIFS('JN - M'!E:E,'JN - M'!$B:$B,">="&EDATE('JN - Q'!$B90,-2),'JN - M'!$B:$B,"<="&EOMONTH('JN - Q'!$B90,0)) -> 104.50641 | I90: =AVERAGEIFS('JN - M'!F:F,'JN - M'!$B:$B,">="&EDATE('JN - Q'!$B90,-2),'JN - M'!$B:$B,"<="&EOMONTH('JN - Q'!$B90,0)) -> 104.50641 | J90: =AVERAGEIFS('JN - M'!K:K,'JN - M'!$B:$B,">="&EDATE('JN - Q'!$B90,-2),'JN - M'!$B:$B,"<="&EOMONTH('JN - Q'!$B90,0)) -> 5.3569393 | K90: =K91*S90/S91 -> 0.64488523 | L90: 0 | M90: ='CDM - Q'!P219/'CDM - Q'!O219*100 -> 88.22877 | N90: =AVERAGEIFS('JN - M'!I:I,'JN - M'!B:B,">="&EDATE('JN - Q'!B90,-2),'JN - M'!B:B,"<="&EOMONTH('JN - Q'!B90,0)) -> 0 | O90: =AVERAGEIFS('JN - M'!J:J,'JN - M'!$B:$B,">="&EDATE('JN - Q'!$B90,-2),'JN - M'!$B:$B,"<="&EOMONTH('JN - Q'!$B90,0)) -> -1.8508285 | S90: =(H90/H86-1)*100+2 -> 1.2238034
A91: 2002 | B91: 37316 | C91: ='CDM - Q'!M220 -> 498587.7 | D91: 533964.8 | E91: =AVERAGEIFS('JN - M'!G:G,'JN - M'!$B:$B,">="&EDATE('JN - Q'!$B91,-2),'JN - M'!$B:$B,"<="&EOMONTH('JN - Q'!$B91,0)) -> 92.866667 | F91: =AVERAGEIFS('JN - M'!H:H,'JN - M'!$B:$B,">="&EDATE('JN - Q'!$B91,-2),'JN - M'!$B:$B,"<="&EOMONTH('JN - Q'!$B91,0)) -> 88.797289 | G91: =AVERAGEIFS('JN - M'!D:D,'JN - M'!$B:$B,">="&EDATE('JN - Q'!$B91,-2),'JN - M'!$B:$B,"<="&EOMONTH('JN - Q'!$B91,0)) -> 100.87393 | H91: =AVERAGEIFS('JN - M'!E:E,'JN - M'!$B:$B,">="&EDATE('JN - Q'!$B91,-2),'JN - M'!$B:$B,"<="&EOMONTH('JN - Q'!$B91,0)) -> 104.37016 | I91: =AVERAGEIFS('JN - M'!F:F,'JN - M'!$B:$B,">="&EDATE('JN - Q'!$B91,-2),'JN - M'!$B:$B,"<="&EOMONTH('JN - Q'!$B91,0)) -> 104.37016 | J91: =AVERAGEIFS('JN - M'!K:K,'JN - M'!$B:$B,">="&EDATE('JN - Q'!$B91,-2),'JN - M'!$B:$B,"<="&EOMONTH('JN - Q'!$B91,0)) -> 5.2837751 | K91: =K92*S91/S92 -> 0.66129277 | L91: 0 | M91: ='CDM - Q'!P220/'CDM - Q'!O220*100 -> 89.780165 | N91: =AVERAGEIFS('JN - M'!I:I,'JN - M'!B:B,">="&EDATE('JN - Q'!B91,-2),'JN - M'!B:B,"<="&EOMONTH('JN - Q'!B91,0)) -> 0 | O91: =AVERAGEIFS('JN - M'!J:J,'JN - M'!$B:$B,">="&EDATE('JN - Q'!$B91,-2),'JN - M'!$B:$B,"<="&EOMONTH('JN - Q'!$B91,0)) -> -1.5676374 | S91: =(H91/H87-1)*100+2 -> 1.2549401
B92: 37408 | C92: ='CDM - Q'!M221 -> 502166.1 | D92: 532359.5 | E92: =AVERAGEIFS('JN - M'!G:G,'JN - M'!$B:$B,">="&EDATE('JN - Q'!$B92,-2),'JN - M'!$B:$B,"<="&EOMONTH('JN - Q'!$B92,0)) -> 89.433333 | F92: =AVERAGEIFS('JN - M'!H:H,'JN - M'!$B:$B,">="&EDATE('JN - Q'!$B92,-2),'JN - M'!$B:$B,"<="&EOMONTH('JN - Q'!$B92,0)) -> 92.076423 | G92: =AVERAGEIFS('JN - M'!D:D,'JN - M'!$B:$B,">="&EDATE('JN - Q'!$B92,-2),'JN - M'!$B:$B,"<="&EOMONTH('JN - Q'!$B92,0)) -> 100.60839 | H92: =AVERAGEIFS('JN - M'!E:E,'JN - M'!$B:$B,">="&EDATE('JN - Q'!$B92,-2),'JN - M'!$B:$B,"<="&EOMONTH('JN - Q'!$B92,0)) -> 104.09765 | I92: =AVERAGEIFS('JN - M'!F:F,'JN - M'!$B:$B,">="&EDATE('JN - Q'!$B92,-2),'JN - M'!$B:$B,"<="&EOMONTH('JN - Q'!$B92,0)) -> 104.09765 | J92: =AVERAGEIFS('JN - M'!K:K,'JN - M'!$B:$B,">="&EDATE('JN - Q'!$B92,-2),'JN - M'!$B:$B,"<="&EOMONTH('JN - Q'!$B92,0)) -> 5.3906328 | K92: =K93*S92/S93 -> 0.62632166 | L92: 0 | M92: ='CDM - Q'!P221/'CDM - Q'!O221*100 -> 88.938508 | N92: =AVERAGEIFS('JN - M'!I:I,'JN - M'!B:B,">="&EDATE('JN - Q'!B92,-2),'JN - M'!B:B,"<="&EOMONTH('JN - Q'!B92,0)) -> 0 | O92: =AVERAGEIFS('JN - M'!J:J,'JN - M'!$B:$B,">="&EDATE('JN - Q'!$B92,-2),'JN - M'!$B:$B,"<="&EOMONTH('JN - Q'!$B92,0)) -> -1.6794576 | S92: =(H92/H88-1)*100+2 -> 1.1885751
B93: 37500 | C93: ='CDM - Q'!M222 -> 503711.3 | D93: 531843.7 | E93: =AVERAGEIFS('JN - M'!G:G,'JN - M'!$B:$B,">="&EDATE('JN - Q'!$B93,-2),'JN - M'!$B:$B,"<="&EOMONTH('JN - Q'!$B93,0)) -> 94.166667 | F93: =AVERAGEIFS('JN - M'!H:H,'JN - M'!$B:$B,">="&EDATE('JN - Q'!$B93,-2),'JN - M'!$B:$B,"<="&EOMONTH('JN - Q'!$B93,0)) -> 94.674455 | G93: =AVERAGEIFS('JN - M'!D:D,'JN - M'!$B:$B,">="&EDATE('JN - Q'!$B93,-2),'JN - M'!$B:$B,"<="&EOMONTH('JN - Q'!$B93,0)) -> 100.37603 | H93: =AVERAGEIFS('JN - M'!E:E,'JN - M'!$B:$B,">="&EDATE('JN - Q'!$B93,-2),'JN - M'!$B:$B,"<="&EOMONTH('JN - Q'!$B93,0)) -> 103.85921 | I93: =AVERAGEIFS('JN - M'!F:F,'JN - M'!$B:$B,">="&EDATE('JN - Q'!$B93,-2),'JN - M'!$B:$B,"<="&EOMONTH('JN - Q'!$B93,0)) -> 103.85921 | J93: =AVERAGEIFS('JN - M'!K:K,'JN - M'!$B:$B,">="&EDATE('JN - Q'!$B93,-2),'JN - M'!$B:$B,"<="&EOMONTH('JN - Q'!$B93,0)) -> 5.4300398 | K93: =K94*S93/S94 -> 0.64235632 | L93: 0 | M93: ='CDM - Q'!P222/'CDM - Q'!O222*100 -> 86.637525 | N93: =AVERAGEIFS('JN - M'!I:I,'JN - M'!B:B,">="&EDATE('JN - Q'!B93,-2),'JN - M'!B:B,"<="&EOMONTH('JN - Q'!B93,0)) -> 0 | O93: =AVERAGEIFS('JN - M'!J:J,'JN - M'!$B:$B,">="&EDATE('JN - Q'!$B93,-2),'JN - M'!$B:$B,"<="&EOMONTH('JN - Q'!$B93,0)) -> -1.809541 | S93: =(H93/H89-1)*100+2 -> 1.2190042
B94: 37591 | C94: ='CDM - Q'!M223 -> 504887.9 | D94: 531684.9 | E94: =AVERAGEIFS('JN - M'!G:G,'JN - M'!$B:$B,">="&EDATE('JN - Q'!$B94,-2),'JN - M'!$B:$B,"<="&EOMONTH('JN - Q'!$B94,0)) -> 93.3 | F94: =AVERAGEIFS('JN - M'!H:H,'JN - M'!$B:$B,">="&EDATE('JN - Q'!$B94,-2),'JN - M'!$B:$B,"<="&EOMONTH('JN - Q'!$B94,0)) -> 94.301005 | G94: =AVERAGEIFS('JN - M'!D:D,'JN - M'!$B:$B,">="&EDATE('JN - Q'!$B94,-2),'JN - M'!$B:$B,"<="&EOMONTH('JN - Q'!$B94,0)) -> 100.24326 | H94: =AVERAGEIFS('JN - M'!E:E,'JN - M'!$B:$B,">="&EDATE('JN - Q'!$B94,-2),'JN - M'!$B:$B,"<="&EOMONTH('JN - Q'!$B94,0)) -> 103.75702 | I94: =AVERAGEIFS('JN - M'!F:F,'JN - M'!$B:$B,">="&EDATE('JN - Q'!$B94,-2),'JN - M'!$B:$B,"<="&EOMONTH('JN - Q'!$B94,0)) -> 103.75702 | J94: =AVERAGEIFS('JN - M'!K:K,'JN - M'!$B:$B,">="&EDATE('JN - Q'!$B94,-2),'JN - M'!$B:$B,"<="&EOMONTH('JN - Q'!$B94,0)) -> 5.3380462 | K94: =K95*S94/S95 -> 0.67603709 | L94: 0 | M94: ='CDM - Q'!P223/'CDM - Q'!O223*100 -> 89.41677 | N94: =AVERAGEIFS('JN - M'!I:I,'JN - M'!B:B,">="&EDATE('JN - Q'!B94,-2),'JN - M'!B:B,"<="&EOMONTH('JN - Q'!B94,0)) -> 0 | O94: =AVERAGEIFS('JN - M'!J:J,'JN - M'!$B:$B,">="&EDATE('JN - Q'!$B94,-2),'JN - M'!$B:$B,"<="&EOMONTH('JN - Q'!$B94,0)) -> -1.8814633 | S94: =(H94/H90-1)*100+2 -> 1.2829205
A95: 2003 | B95: 37681 | C95: ='CDM - Q'!M224 -> 504307.3 | D95: 526783.8 | E95: =AVERAGEIFS('JN - M'!G:G,'JN - M'!$B:$B,">="&EDATE('JN - Q'!$B95,-2),'JN - M'!$B:$B,"<="&EOMONTH('JN - Q'!$B95,0)) -> 99.866667 | F95: =AVERAGEIFS('JN - M'!H:H,'JN - M'!$B:$B,">="&EDATE('JN - Q'!$B95,-2),'JN - M'!$B:$B,"<="&EOMONTH('JN - Q'!$B95,0)) -> 95.547704 | G95: =AVERAGEIFS('JN - M'!D:D,'JN - M'!$B:$B,">="&EDATE('JN - Q'!$B95,-2),'JN - M'!$B:$B,"<="&EOMONTH('JN - Q'!$B95,0)) -> 100.17688 | H95: =AVERAGEIFS('JN - M'!E:E,'JN - M'!$B:$B,">="&EDATE('JN - Q'!$B95,-2),'JN - M'!$B:$B,"<="&EOMONTH('JN - Q'!$B95,0)) -> 103.65483 | I95: =AVERAGEIFS('JN - M'!F:F,'JN - M'!$B:$B,">="&EDATE('JN - Q'!$B95,-2),'JN - M'!$B:$B,"<="&EOMONTH('JN - Q'!$B95,0)) -> 103.65483 | J95: =AVERAGEIFS('JN - M'!K:K,'JN - M'!$B:$B,">="&EDATE('JN - Q'!$B95,-2),'JN - M'!$B:$B,"<="&EOMONTH('JN - Q'!$B95,0)) -> 5.3721737 | K95: =K96*S95/S96 -> 0.69274195 | L95: 0 | M95: ='CDM - Q'!P224/'CDM - Q'!O224*100 -> 89.560513 | N95: =AVERAGEIFS('JN - M'!I:I,'JN - M'!B:B,">="&EDATE('JN - Q'!B95,-2),'JN - M'!B:B,"<="&EOMONTH('JN - Q'!B95,0)) -> 0 | O95: =AVERAGEIFS('JN - M'!J:J,'JN - M'!$B:$B,">="&EDATE('JN - Q'!$B95,-2),'JN - M'!$B:$B,"<="&EOMONTH('JN - Q'!$B95,0)) -> -1.5775864 | S95: =(H95/H91-1)*100+2 -> 1.3146214
B96: 37773 | C96: ='CDM - Q'!M225 -> 508468.4 | D96: 531416.1 | E96: =AVERAGEIFS('JN - M'!G:G,'JN - M'!$B:$B,">="&EDATE('JN - Q'!$B96,-2),'JN - M'!$B:$B,"<="&EOMONTH('JN - Q'!$B96,0)) -> 93.166667 | F96: =AVERAGEIFS('JN - M'!H:H,'JN - M'!$B:$B,">="&EDATE('JN - Q'!$B96,-2),'JN - M'!$B:$B,"<="&EOMONTH('JN - Q'!$B96,0)) -> 95.985215 | G96: =AVERAGEIFS('JN - M'!D:D,'JN - M'!$B:$B,">="&EDATE('JN - Q'!$B96,-2),'JN - M'!$B:$B,"<="&EOMONTH('JN - Q'!$B96,0)) -> 100.24326 | H96: =AVERAGEIFS('JN - M'!E:E,'JN - M'!$B:$B,">="&EDATE('JN - Q'!$B96,-2),'JN - M'!$B:$B,"<="&EOMONTH('JN - Q'!$B96,0)) -> 103.79108 | I96: =AVERAGEIFS('JN - M'!F:F,'JN - M'!$B:$B,">="&EDATE('JN - Q'!$B96,-2),'JN - M'!$B:$B,"<="&EOMONTH('JN - Q'!$B96,0)) -> 103.79108 | J96: =AVERAGEIFS('JN - M'!K:K,'JN - M'!$B:$B,">="&EDATE('JN - Q'!$B96,-2),'JN - M'!$B:$B,"<="&EOMONTH('JN - Q'!$B96,0)) -> 5.4304336 | K96: =K97*S96/S97 -> 0.8987147 | L96: 0 | M96: ='CDM - Q'!P225/'CDM - Q'!O225*100 -> 88.281089 | N96: =AVERAGEIFS('JN - M'!I:I,'JN - M'!B:B,">="&EDATE('JN - Q'!B96,-2),'JN - M'!B:B,"<="&EOMONTH('JN - Q'!B96,0)) -> 0 | O96: =AVERAGEIFS('JN - M'!J:J,'JN - M'!$B:$B,">="&EDATE('JN - Q'!$B96,-2),'JN - M'!$B:$B,"<="&EOMONTH('JN - Q'!$B96,0)) -> -1.25585 | S96: =(H96/H92-1)*100+2 -> 1.7054974
B97: 37865 | C97: ='CDM - Q'!M226 -> 509943.7 | D97: 530993.9 | E97: =AVERAGEIFS('JN - M'!G:G,'JN - M'!$B:$B,">="&EDATE('JN - Q'!$B97,-2),'JN - M'!$B:$B,"<="&EOMONTH('JN - Q'!$B97,0)) -> 96.5 | F97: =AVERAGEIFS('JN - M'!H:H,'JN - M'!$B:$B,">="&EDATE('JN - Q'!$B97,-2),'JN - M'!$B:$B,"<="&EOMONTH('JN - Q'!$B97,0)) -> 97.067589 | G97: =AVERAGEIFS('JN - M'!D:D,'JN - M'!$B:$B,">="&EDATE('JN - Q'!$B97,-2),'JN - M'!$B:$B,"<="&EOMONTH('JN - Q'!$B97,0)) -> 100.24326 | H97: =AVERAGEIFS('JN - M'!E:E,'JN - M'!$B:$B,">="&EDATE('JN - Q'!$B97,-2),'JN - M'!$B:$B,"<="&EOMONTH('JN - Q'!$B97,0)) -> 103.82515 | I97: =AVERAGEIFS('JN - M'!F:F,'JN - M'!$B:$B,">="&EDATE('JN - Q'!$B97,-2),'JN - M'!$B:$B,"<="&EOMONTH('JN - Q'!$B97,0)) -> 103.82515 | J97: =AVERAGEIFS('JN - M'!K:K,'JN - M'!$B:$B,">="&EDATE('JN - Q'!$B97,-2),'JN - M'!$B:$B,"<="&EOMONTH('JN - Q'!$B97,0)) -> 5.1598249 | K97: =K98*S97/S98 -> 1.0366206 | L97: 0 | M97: ='CDM - Q'!P226/'CDM - Q'!O226*100 -> 88.213368 | N97: =AVERAGEIFS('JN - M'!I:I,'JN - M'!B:B,">="&EDATE('JN - Q'!B97,-2),'JN - M'!B:B,"<="&EOMONTH('JN - Q'!B97,0)) -> 0 | O97: =AVERAGEIFS('JN - M'!J:J,'JN - M'!$B:$B,">="&EDATE('JN - Q'!$B97,-2),'JN - M'!$B:$B,"<="&EOMONTH('JN - Q'!$B97,0)) -> -0.74936227 | S97: =(H97/H93-1)*100+2 -> 1.9672024
B98: 37956 | C98: ='CDM - Q'!M227 -> 515100.9 | D98: 532355.6 | E98: =AVERAGEIFS('JN - M'!G:G,'JN - M'!$B:$B,">="&EDATE('JN - Q'!$B98,-2),'JN - M'!$B:$B,"<="&EOMONTH('JN - Q'!$B98,0)) -> 98.333333 | F98: =AVERAGEIFS('JN - M'!H:H,'JN - M'!$B:$B,">="&EDATE('JN - Q'!$B98,-2),'JN - M'!$B:$B,"<="&EOMONTH('JN - Q'!$B98,0)) -> 99.182644 | G98: =AVERAGEIFS('JN - M'!D:D,'JN - M'!$B:$B,">="&EDATE('JN - Q'!$B98,-2),'JN - M'!$B:$B,"<="&EOMONTH('JN - Q'!$B98,0)) -> 100.21007 | H98: =AVERAGEIFS('JN - M'!E:E,'JN - M'!$B:$B,">="&EDATE('JN - Q'!$B98,-2),'JN - M'!$B:$B,"<="&EOMONTH('JN - Q'!$B98,0)) -> 103.5867 | I98: =AVERAGEIFS('JN - M'!F:F,'JN - M'!$B:$B,">="&EDATE('JN - Q'!$B98,-2),'JN - M'!$B:$B,"<="&EOMONTH('JN - Q'!$B98,0)) -> 103.5867 | J98: =AVERAGEIFS('JN - M'!K:K,'JN - M'!$B:$B,">="&EDATE('JN - Q'!$B98,-2),'JN - M'!$B:$B,"<="&EOMONTH('JN - Q'!$B98,0)) -> 5.0363972 | K98: =K99*S98/S99 -> 0.96740438 | L98: 0 | M98: ='CDM - Q'!P227/'CDM - Q'!O227*100 -> 86.208146 | N98: =AVERAGEIFS('JN - M'!I:I,'JN - M'!B:B,">="&EDATE('JN - Q'!B98,-2),'JN - M'!B:B,"<="&EOMONTH('JN - Q'!B98,0)) -> 0 | O98: =AVERAGEIFS('JN - M'!J:J,'JN - M'!$B:$B,">="&EDATE('JN - Q'!$B98,-2),'JN - M'!$B:$B,"<="&EOMONTH('JN - Q'!$B98,0)) -> -0.88594259 | S98: =(H98/H94-1)*100+2 -> 1.8358503
A99: 2004 | B99: 38047 | C99: ='CDM - Q'!M228 -> 519507.8 | D99: 534931.8 | E99: =AVERAGEIFS('JN - M'!G:G,'JN - M'!$B:$B,">="&EDATE('JN - Q'!$B99,-2),'JN - M'!$B:$B,"<="&EOMONTH('JN - Q'!$B99,0)) -> 104.76667 | F99: =AVERAGEIFS('JN - M'!H:H,'JN - M'!$B:$B,">="&EDATE('JN - Q'!$B99,-2),'JN - M'!$B:$B,"<="&EOMONTH('JN - Q'!$B99,0)) -> 100.33834 | G99: =AVERAGEIFS('JN - M'!D:D,'JN - M'!$B:$B,">="&EDATE('JN - Q'!$B99,-2),'JN - M'!$B:$B,"<="&EOMONTH('JN - Q'!$B99,0)) -> 100.11049 | H99: =AVERAGEIFS('JN - M'!E:E,'JN - M'!$B:$B,">="&EDATE('JN - Q'!$B99,-2),'JN - M'!$B:$B,"<="&EOMONTH('JN - Q'!$B99,0)) -> 103.24607 | I99: =AVERAGEIFS('JN - M'!F:F,'JN - M'!$B:$B,">="&EDATE('JN - Q'!$B99,-2),'JN - M'!$B:$B,"<="&EOMONTH('JN - Q'!$B99,0)) -> 103.24607 | J99: =AVERAGEIFS('JN - M'!K:K,'JN - M'!$B:$B,">="&EDATE('JN - Q'!$B99,-2),'JN - M'!$B:$B,"<="&EOMONTH('JN - Q'!$B99,0)) -> 4.8669614 | K99: =K100*S99/S100 -> 0.84610117 | L99: 0 | M99: ='CDM - Q'!P228/'CDM - Q'!O228*100 -> 87.999144 | N99: =AVERAGEIFS('JN - M'!I:I,'JN - M'!B:B,">="&EDATE('JN - Q'!B99,-2),'JN - M'!B:B,"<="&EOMONTH('JN - Q'!B99,0)) -> 0 | O99: =AVERAGEIFS('JN - M'!J:J,'JN - M'!$B:$B,">="&EDATE('JN - Q'!$B99,-2),'JN - M'!$B:$B,"<="&EOMONTH('JN - Q'!$B99,0)) -> -1.1309563 | S99: =(H99/H95-1)*100+2 -> 1.6056523
B100: 38139 | C100: ='CDM - Q'!M229 -> 519128.9 | D100: 533633.3 | E100: =AVERAGEIFS('JN - M'!G:G,'JN - M'!$B:$B,">="&EDATE('JN - Q'!$B100,-2),'JN - M'!$B:$B,"<="&EOMONTH('JN - Q'!$B100,0)) -> 99 | F100: =AVERAGEIFS('JN - M'!H:H,'JN - M'!$B:$B,">="&EDATE('JN - Q'!$B100,-2),'JN - M'!$B:$B,"<="&EOMONTH('JN - Q'!$B100,0)) -> 102.07806 | G100: =AVERAGEIFS('JN - M'!D:D,'JN - M'!$B:$B,">="&EDATE('JN - Q'!$B100,-2),'JN - M'!$B:$B,"<="&EOMONTH('JN - Q'!$B100,0)) -> 100.0441 | H100: =AVERAGEIFS('JN - M'!E:E,'JN - M'!$B:$B,">="&EDATE('JN - Q'!$B100,-2),'JN - M'!$B:$B,"<="&EOMONTH('JN - Q'!$B100,0)) -> 103.04169 | I100: =AVERAGEIFS('JN - M'!F:F,'JN - M'!$B:$B,">="&EDATE('JN - Q'!$B100,-2),'JN - M'!$B:$B,"<="&EOMONTH('JN - Q'!$B100,0)) -> 103.04169 | J100: =AVERAGEIFS('JN - M'!K:K,'JN - M'!$B:$B,">="&EDATE('JN - Q'!$B100,-2),'JN - M'!$B:$B,"<="&EOMONTH('JN - Q'!$B100,0)) -> 4.7211913 | K100: =K101*S100/S101 -> 0.67343282 | L100: 0 | M100: ='CDM - Q'!P229/'CDM - Q'!O229*100 -> 90.368348 | N100: =AVERAGEIFS('JN - M'!I:I,'JN - M'!B:B,">="&EDATE('JN - Q'!B100,-2),'JN - M'!B:B,"<="&EOMONTH('JN - Q'!B100,0)) -> 0 | O100: =AVERAGEIFS('JN - M'!J:J,'JN - M'!$B:$B,">="&EDATE('JN - Q'!$B100,-2),'JN - M'!$B:$B,"<="&EOMONTH('JN - Q'!$B100,0)) -> -0.98923431 | S100: =(H100/H96-1)*100+2 -> 1.2779783
...

Sheet JN - M
C1: JN Headline | D1: JN Core CPI | E1: JN Core Core CPI | F1: Core Core CPI Forecst | G1: Labour Productivity Index: Manufacturing | H1: Labour Productivity Index: Manufacturing | I1: Interest | J1: SSR | K1: Unemployment Rate | O1: Core CPI History | P1: Core Core CPI History
B2: Date | D2: sa | G2: nsa | H2: sa | K2: sa
A3: =YEAR(B3) -> 1980 | B3: 29221 | D3: =D4*$O3/$O4 -> 77.001651 | E3: =E4*$P3/$P4 -> 77.435511 | F3: =E3 -> 77.435511 | I3: 8.0571 | K3: 1.926851 | O3: 77.099432 | P3: 76.281934
B4: 29252 | D4: =D5*$O4/$O5 -> 77.641118 | E4: =E5*$P4/$P5 -> 77.435511 | F4: =E4 -> 77.435511 | I4: 8.7396 | K4: 1.8360071 | O4: 77.739712 | P4: 76.281934
B5: 29281 | D5: =D6*$O5/$O6 -> 78.100384 | E5: =E6*$P5/$P6 -> 77.990206 | F5: =E5 -> 77.990206 | I5: 10.73 | J5: =J6*I5/I6 -> 11.365418 | K5: 1.886121 | O5: 78.199561 | P5: 76.828366
B6: 29312 | D6: =D7*$O6/$O7 -> 79.420005 | E6: =E7*$P6/$P7 -> 78.988658 | F6: =E6 -> 78.988658 | I6: 12.21 | J6: =J7*I6/I7 -> 12.933062 | K6: 1.9524317 | O6: 79.520858 | P6: 77.811944
B7: 29342 | D7: =D8*$O7/$O8 -> 80.073734 | E7: =E8*$P7/$P8 -> 80.208989 | F7: =E7 -> 80.208989 | I7: 12.5625 | J7: =J8*I7/I8 -> 13.306436 | K7: 1.9572954 | O7: 80.175417 | P7: 79.014095
B8: 29373 | D8: =D9*$O8/$O9 -> 80.539593 | E8: =E9*$P8/$P9 -> 80.652745 | F8: =E8 -> 80.652745 | I8: 12.6425 | J8: =J9*I8/I9 -> 13.391174 | K8: 1.9111662 | O8: 80.641867 | P8: 79.45124
B9: 29403 | D9: =D10*$O9/$O10 -> 80.986919 | E9: =E10*$P9/$P10 -> 80.874623 | F9: =E9 -> 80.874623 | I9: 12.7014 | J9: =J10*I9/I10 -> 13.453562 | K9: 2.0796616 | O9: 81.089761 | P9: 79.669813
B10: 29434 | D10: =D11*$O10/$O11 -> 81.139797 | E10: =E11*$P10/$P11 -> 80.430867 | F10: =E10 -> 80.430867 | I10: 12.0865 | J10: =J11*I10/I11 -> 12.802248 | K10: 2.0796616 | O10: 81.242834 | P10: 79.232668
B11: 29465 | D11: =D12*$O11/$O12 -> 81.352261 | E11: =E12*$P11/$P12 -> 81.31838 | F11: =E11 -> 81.31838 | I11: 11.4036 | J11: =J12*I11/I12 -> 12.078908 | K11: 2.0221558 | O11: 81.455568 | P11: 80.106959
B12: 29495 | D12: =D13*$O12/$O13 -> 81.823243 | E12: =E13*$P12/$P13 -> 81.873076 | F12: =E12 -> 81.873076 | I12: 11.0361 | J12: =J13*I12/I13 -> 11.689645 | K12: 2.0796616 | O12: 81.927148 | P12: 80.653391
B13: 29526 | D13: =D14*$O13/$O14 -> 82.140462 | E13: =E14*$P13/$P14 -> 82.094954 | F13: =E13 -> 82.094954 | I13: 9.5 | J13: =J14*I13/I14 -> 10.062579 | K13: 2.2378855 | O13: 82.244769 | P13: 80.871964
B14: 29556 | D14: =D15*$O14/$O15 -> 82.343751 | E14: =E15*$P14/$P15 -> 82.316832 | F14: =E14 -> 82.316832 | I14: 9.4884 | J14: =J15*I14/I15 -> 10.050292 | K14: 2.2026432 | O14: 82.448317 | P14: 81.090537
A15: =YEAR(B15) -> 1981 | B15: 29587 | D15: =D16*$O15/$O16 -> 82.68632 | E15: =E16*$P15/$P16 -> 82.316832 | F15: =E15 -> 82.316832 | I15: 8.9076 | J15: =J16*I15/I16 -> 9.4350974 | K15: 2.1089631 | O15: 82.791321 | P15: 81.090537
B16: 29618 | D16: =D17*$O16/$O17 -> 82.915602 | E16: =E17*$P16/$P17 -> 82.094954 | F16: =E16 -> 82.094954 | I16: 8.6033 | J16: =J17*I16/I17 -> 9.1127772 | K16: 2.2491653 | O16: 83.020894 | P16: 80.871964
B17: 29646 | D17: =D18*$O17/$O18 -> 83.042098 | E17: =E18*$P17/$P18 -> 82.427771 | F17: =E17 -> 82.427771 | I17: 8.035 | J17: =J18*I17/I18 -> 8.5108231 | K17: 2.1937522 | O17: 83.14755 | P17: 81.199824
B18: 29677 | D18: =D19*$O18/$O19 -> 83.072168 | E18: =E19*$P18/$P19 -> 83.093406 | F18: =E18 -> 83.093406 | I18: 7.185 | J18: =J19*I18/I19 -> 7.6104871 | K18: 2.240112 | O18: 83.177659 | P18: 81.855542
B19: 29707 | D19: =D20*$O19/$O20 -> 83.686463 | E19: =E20*$P19/$P20 -> 83.980919 | F19: =E19 -> 83.980919 | I19: 7.0573 | J19: =J20*I19/I20 -> 7.4752249 | K19: 2.3194518 | O19: 83.792734 | P19: 82.729834
B20: 29738 | D20: =D21*$O20/$O21 -> 83.935658 | E20: =E21*$P20/$P21 -> 84.202797 | F20: =E20 -> 84.202797 | I20: 7.1178 | J20: =J21*I20/I21 -> 7.5393076 | K20: 2.2643497 | O20: 84.042245 | P20: 82.948407
B21: 29768 | D21: =D22*$O21/$O22 -> 84.09309 | E21: =E22*$P21/$P22 -> 84.202797 | F21: =E21 -> 84.202797 | I21: 7.2593 | J21: =J22*I21/I22 -> 7.6891871 | K21: 2.207815 | O21: 84.199877 | P21: 82.948407
B22: 29799 | D22: =D23*$O22/$O23 -> 84.438966 | E22: =E23*$P22/$P23 -> 83.759041 | F22: =E22 -> 83.759041 | I22: 7.2356 | J22: =J23*I22/I23 -> 7.6640836 | K22: 2.084063 | O22: 84.546192 | P22: 82.511261
B23: 29830 | D23: =D24*$O23/$O24 -> 84.85071 | E23: =E24*$P23/$P24 -> 84.757493 | F23: =E23 -> 84.757493 | I23: 7.2578 | J23: =J24*I23/I24 -> 7.6875982 | K23: 2.1876094 | O23: 84.958459 | P23: 83.494839
B24: 29860 | D24: =D25*$O24/$O25 -> 85.04828 | E24: =E25*$P24/$P25 -> 85.201249 | F24: =E24 -> 85.201249 | I24: 7.0505 | J24: =J25*I24/I25 -> 7.4680222 | K24: 2.2222222 | O24: 85.15628 | P24: 83.931984
B25: 29891 | D25: =D26*$O25/$O26 -> 85.350793 | E25: =E26*$P25/$P26 -> 85.312189 | F25: =E25 -> 85.312189 | I25: 6.7989 | J25: =J26*I25/I26 -> 7.2015227 | K25: 2.1989529 | O25: 85.459177 | P25: 84.041271
B26: 29921 | D26: =D27*$O26/$O27 -> 85.565276 | E26: =E27*$P26/$P27 -> 85.534067 | F26: =E26 -> 85.534067 | I26: 6.7014 | J26: =J27*I26/I27 -> 7.0982489 | K26: 2.2311313 | O26: 85.673933 | P26: 84.259844
A27: =YEAR(B27) -> 1982 | B27: 29952 | D27: =D28*$O27/$O28 -> 85.703743 | E27: =E28*$P27/$P28 -> 85.201249 | F27: =E27 -> 85.201249 | I27: 6.5761 | J27: =J28*I27/I28 -> 6.9655288 | K27: 2.2164049 | O27: 85.812576 | P27: 83.931984
B28: 29983 | D28: =D29*$O28/$O29 -> 85.85453 | E28: =E29*$P28/$P29 -> 84.979371 | F28: =E28 -> 84.979371 | I28: 6.5761 | J28: =J29*I28/I29 -> 6.9655288 | K28: 2.2110028 | O28: 85.963553 | P28: 83.713412
B29: 30011 | D29: =D30*$O29/$O30 -> 85.880916 | E29: =E30*$P29/$P30 -> 85.201249 | F29: =E29 -> 85.201249 | I29: 6.6755 | J29: =J30*I29/I30 -> 7.0708151 | K29: 2.2727273 | O29: 85.989973 | P29: 83.931984
B30: 30042 | D30: =D31*$O30/$O31 -> 85.948238 | E30: =E31*$P30/$P31 -> 85.755945 | F30: =E30 -> 85.755945 | I30: 7.1625 | J30: =J31*I30/I31 -> 7.5866547 | K30: 2.3098298 | O30: 86.057381 | P30: 84.478417
B31: 30072 | D31: =D32*$O31/$O32 -> 86.241651 | E31: =E32*$P31/$P32 -> 86.532519 | F31: =E31 -> 86.532519 | I31: 7.1667 | J31: =J32*I31/I32 -> 7.5911034 | K31: 2.3030303 | O31: 86.351166 | P31: 85.243422
B32: 30103 | D32: =D33*$O32/$O33 -> 86.488381 | E32: =E33*$P32/$P33 -> 86.643458 | F32: =E32 -> 86.643458 | I32: 7.1875 | J32: =J33*I32/I33 -> 7.6131352 | K32: 2.4136135 | O32: 86.59821 | P32: 85.352708
B33: 30133 | D33: =D34*$O33/$O34 -> 86.672445 | E33: =E34*$P33/$P34 -> 86.532519 | F33: =E33 -> 86.532519 | I33: 7.1852 | J33: =J34*I33/I34 -> 7.610699 | K33: 2.3817803 | O33: 86.782507 | P33: 85.243422
B34: 30164 | D34: =D35*$O34/$O35 -> 86.963764 | E34: =E35*$P34/$P35 -> 86.088762 | F34: =E34 -> 86.088762 | I34: 7.1827 | J34: =J35*I34/I35 -> 7.6080509 | K34: 2.3413111 | O34: 87.074196 | P34: 84.806276
B35: 30195 | D35: =D36*$O35/$O36 -> 87.260681 | E35: =E36*$P35/$P36 -> 87.198154 | F35: =E35 -> 87.198154 | I35: 6.987 | J35: =J36*I35/I36 -> 7.4007618 | K35: 2.3904382 | O35: 87.37149 | P35: 85.89914
B36: 30225 | D36: =D37*$O36/$O37 -> 87.416242 | E36: =E37*$P36/$P37 -> 87.530971 | F36: =E36 -> 87.530971 | I36: 6.9175 | J36: =J37*I36/I37 -> 7.3271461 | K36: 2.4650922 | O36: 87.527249 | P36: 86.227
B37: 30256 | D37: =D38*$O37/$O38 -> 87.599166 | E37: =E38*$P37/$P38 -> 87.530971 | F37: =E37 -> 87.530971 | I37: 6.6849 | J37: =J38*I37/I38 -> 7.0807718 | K37: 2.4255978 | O37: 87.710405 | P37: 86.227
B38: 30286 | D38: =D39*$O38/$O39 -> 87.700608 | E38: =E39*$P38/$P39 -> 87.64191 | F38: =E38 -> 87.64191 | I38: 6.9213 | J38: =J39*I38/I39 -> 7.3311711 | K38: 2.4923182 | O38: 87.811976 | P38: 86.336286
A39: =YEAR(B39) -> 1983 | B39: 30317 | D39: =D40*$O39/$O40 -> 87.739866 | E39: =E40*$P39/$P40 -> 87.198154 | F39: =E39 -> 87.198154 | I39: 6.6413 | J39: =J40*I39/I40 -> 7.0345899 | K39: 2.7045416 | O39: 87.851284 | P39: 85.89914
B40: 30348 | D40: =D41*$O40/$O41 -> 87.665689 | E40: =E41*$P40/$P41 -> 86.976275 | F40: =E40 -> 86.976275 | I40: 6.5734 | J40: =J41*I40/I41 -> 6.9626689 | K40: 2.6705222 | O40: 87.777012 | P40: 85.680567
B41: 30376 | D41: =D42*$O41/$O42 -> 87.815718 | E41: =E42*$P41/$P42 -> 87.198154 | F41: =E41 -> 87.198154 | I41: 6.6923 | J41: =J42*I41/I42 -> 7.08861 | K41: 2.6400954 | O41: 87.927232 | P41: 85.89914
B42: 30407 | D42: =D43*$O42/$O43 -> 87.817598 | E42: =E43*$P42/$P43 -> 87.863788 | F42: =E42 -> 87.863788 | I42: 6.295 | J42: =J43*I42/I43 -> 6.6677824 | K42: 2.7247956 | O42: 87.929115 | P42: 86.554859
B43: 30437 | D43: =D44*$O43/$O44 -> 87.929802 | E43: =E44*$P43/$P44 -> 88.529423 | F43: =E43 -> 88.529423 | I43: 6.0807 | J43: =J44*I43/I44 -> 6.4407918 | K43: 2.66463 | O43: 88.041461 | P43: 87.210578
B44: 30468 | D44: =D45*$O44/$O45 -> 88.083919 | E44: =E45*$P44/$P45 -> 88.640362 | F44: =E44 -> 88.640362 | I44: 6.1971 | J44: =J45*I44/I45 -> 6.5640849 | K44: 2.5458248 | O44: 88.195774 | P44: 87.319864
B45: 30498 | D45: =D46*$O45/$O46 -> 88.265251 | E45: =E46*$P45/$P46 -> 88.529423 | F45: =E45 -> 88.529423 | I45: 6.387 | J45: =J46*I45/I46 -> 6.7652305 | K45: 2.5649737 | O45: 88.377337 | P45: 87.210578
B46: 30529 | D46: =D47*$O46/$O47 -> 88.041883 | E46: =E47*$P46/$P47 -> 87.863788 | F46: =E46 -> 87.863788 | I46: 6.4567 | J46: =J47*I46/I47 -> 6.8390581 | K46: 2.7631802 | O46: 88.153684 | P46: 86.554859
B47: 30560 | D47: =D48*$O47/$O48 -> 88.594307 | E47: =E48*$P47/$P48 -> 88.97318 | F47: =E47 -> 88.97318 | I47: 6.5326 | J47: =J48*I47/I48 -> 6.9194528 | K47: 2.6962862 | O47: 88.70681 | P47: 87.647723
B48: 30590 | D48: =D49*$O48/$O49 -> 88.828406 | E48: =E49*$P48/$P49 -> 89.305997 | F48: =E48 -> 89.305997 | I48: 6.4271 | J48: =J49*I48/I49 -> 6.8077052 | K48: 2.5914634 | O48: 88.941207 | P48: 87.975583
B49: 30621 | D49: =D50*$O49/$O50 -> 89.107178 | E49: =E50*$P49/$P50 -> 89.638814 | F49: =E49 -> 89.638814 | I49: 5.9864 | J49: =J50*I49/I50 -> 6.3409075 | K49: 2.6422764 | O49: 89.220332 | P49: 88.303442
B50: 30651 | D50: =D51*$O50/$O51 -> 89.087528 | E50: =E51*$P50/$P51 -> 89.638814 | F50: =E50 -> 89.638814 | I50: 6.4375 | J50: =J51*I50/I51 -> 6.8187211 | K50: 2.6311322 | O50: 89.200657 | P50: 88.303442
A51: =YEAR(B51) -> 1984 | B51: 30682 | D51: =D52*$O51/$O52 -> 89.13444 | E51: =E52*$P51/$P52 -> 89.305997 | F51: =E51 -> 89.305997 | I51: 6.0511 | J51: =J52*I51/I52 -> 6.4094389 | K51: 2.7418256 | O51: 89.247629 | P51: 87.975583
B52: 30713 | D52: =D53*$O52/$O53 -> 89.358684 | E52: =E53*$P52/$P53 -> 89.305997 | F52: =E52 -> 89.305997 | I52: 6.0417 | J52: =J53*I52/I53 -> 6.3994823 | K52: 2.7688126 | O52: 89.472158 | P52: 87.975583
B53: 30742 | D53: =D54*$O53/$O54 -> 89.509501 | E53: =E54*$P53/$P54 -> 89.305997 | F53: =E53 -> 89.305997 | I53: 6.4525 | J53: =J54*I53/I54 -> 6.8346093 | K53: 2.7109454 | O53: 89.623166 | P53: 87.975583
B54: 30773 | D54: =D55*$O54/$O55 -> 89.436727 | E54: =E55*$P54/$P55 -> 89.860693 | F54: =E54 -> 89.860693 | I54: 5.8832 | J54: =J55*I54/I55 -> 6.2315961 | K54: 2.6729826 | O54: 89.5503 | P54: 88.522015
B55: 30803 | D55: =D56*$O55/$O56 -> 90.063224 | E55: =E56*$P55/$P56 -> 90.970084 | F55: =E55 -> 90.970084 | I55: 5.7422 | J55: =J56*I55/I56 -> 6.0822462 | K55: 2.6903553 | O55: 90.177593 | P55: 89.614879
B56: 30834 | D56: =D57*$O56/$O57 -> 89.999867 | E56: =E57*$P56/$P57 -> 90.748206 | F56: =E56 -> 90.748206 | I56: 5.9075 | J56: =J57*I56/I57 -> 6.2573351 | K56: 2.7796496 | O56: 90.114155 | P56: 89.396306
B57: 30864 | D57: =D58*$O57/$O58 -> 90.162927 | E57: =E58*$P57/$P58 -> 90.748206 | F57: =E57 -> 90.748206 | I57: 6.03 | J57: =J58*I57/I58 -> 6.3870894 | K57: 2.7660651 | O57: 90.277422 | P57: 89.396306
B58: 30895 | D58: =D59*$O58/$O59 -> 89.977674 | E58: =E59*$P58/$P59 -> 90.082571 | F58: =E58 -> 90.082571 | I58: 6.113 | J58: =J59*I58/I59 -> 6.4750046 | K58: 2.7127211 | O58: 90.091934 | P58: 88.740588
B59: 30926 | D59: =D60*$O59/$O60 -> 90.586854 | E59: =E60*$P59/$P60 -> 91.081023 | F59: =E59 -> 91.081023 | I59: 6.3153 | J59: =J60*I59/I60 -> 6.6892845 | K59: 2.7149321 | O59: 90.701887 | P59: 89.724166
B60: 30956 | D60: =D61*$O60/$O61 -> 90.915336 | E60: =E61*$P60/$P61 -> 91.746658 | F60: =E60 -> 91.746658 | I60: 6.1525 | J60: =J61*I60/I61 -> 6.5168437 | K60: 2.7502935 | O60: 91.030787 | P60: 90.379884
B61: 30987 | D61: =D62*$O61/$O62 -> 91.079967 | E61: =E62*$P61/$P62 -> 91.857597 | F61: =E61 -> 91.857597 | I61: 6.1033 | J61: =J62*I61/I62 -> 6.4647301 | K61: 2.6682329 | O61: 91.195626 | P61: 90.489171
B62: 31017 | D62: =D63*$O62/$O63 -> 91.144477 | E62: =E63*$P62/$P63 -> 91.857597 | F62: =E62 -> 91.857597 | I62: 6.4075 | J62: =J63*I62/I63 -> 6.7869445 | K62: 2.6205275 | O62: 91.260218 | P62: 90.489171
A63: =YEAR(B63) -> 1985 | B63: 31048 | D63: =D64*$O63/$O64 -> 91.43244 | E63: =E64*$P63/$P64 -> 91.746658 | F63: =E63 -> 91.746658 | I63: 6.1676 | J63: =J64*I63/I64 -> 6.5328379 | K63: 2.4668569 | O63: 91.548547 | P63: 90.379884
B64: 31079 | D64: =D65*$O64/$O65 -> 91.373243 | E64: =E65*$P64/$P65 -> 91.635719 | F64: =E64 -> 91.635719 | I64: 6.1619 | J64: =J65*I64/I65 -> 6.5268004 | K64: 2.5993627 | O64: 91.489275 | P64: 90.270598
B65: 31107 | D65: =D66*$O65/$O66 -> 91.636263 | E65: =E66*$P65/$P66 -> 91.857597 | F65: =E65 -> 91.857597 | I65: 6.4167 | J65: =J66*I65/I66 -> 6.7966893 | K65: 2.6209677 | O65: 91.752629 | P65: 90.489171
B66: 31138 | D66: =D67*$O66/$O67 -> 91.800219 | E66: =E67*$P66/$P67 -> 92.412293 | F66: =E66 -> 92.412293 | I66: 6.0729 | J66: =J67*I66/I67 -> 6.4325299 | K66: 2.4689285 | O66: 91.916793 | P66: 91.035603
B67: 31168 | D67: =D68*$O67/$O68 -> 91.739111 | E67: =E68*$P67/$P68 -> 92.74511 | F67: =E67 -> 92.74511 | I67: 6.0052 | J67: =J68*I67/I68 -> 6.3608208 | K67: 2.54948 | O67: 91.855607 | P67: 91.363462
B68: 31199 | D68: =D69*$O68/$O69 -> 91.901195 | E68: =E69*$P68/$P69 -> 92.856049 | F68: =E68 -> 92.856049 | I68: 6.1276 | J68: =J69*I68/I69 -> 6.4904692 | K68: 2.6218487 | O68: 92.017897 | P68: 91.472749
B69: 31229 | D69: =D70*$O69/$O70 -> 92.048804 | E69: =E70*$P69/$P70 -> 92.74511 | F69: =E69 -> 92.74511 | I69: 6.1875 | J69: =J70*I69/I70 -> 6.5539164 | K69: 2.54948 | O69: 92.165693 | P69: 91.363462
B70: 31260 | D70: =D71*$O70/$O71 -> 92.131979 | E70: =E71*$P70/$P71 -> 92.634171 | F70: =E70 -> 92.634171 | I70: 6.1683 | J70: =J71*I70/I71 -> 6.5335794 | K70: 2.5339822 | O70: 92.248975 | P70: 91.254176
B71: 31291 | D71: =D72*$O71/$O72 -> 92.151833 | E71: =E72*$P71/$P72 -> 93.077927 | F71: =E71 -> 93.077927 | I71: 6.4063 | J71: =J72*I71/I72 -> 6.7856734 | K71: 2.6751379 | O71: 92.268854 | P71: 91.691322
B72: 31321 | D72: =D73*$O72/$O73 -> 92.143118 | E72: =E73*$P72/$P73 -> 93.299806 | F72: =E72 -> 93.299806 | I72: 6.5375 | J72: =J73*I72/I73 -> 6.9246429 | K72: 2.7252968 | O72: 92.260128 | P72: 91.909894
B73: 31352 | D73: =D74*$O73/$O74 -> 92.298982 | E73: =E74*$P73/$P74 -> 93.410745 | F73: =E73 -> 93.410745 | I73: 7.288 | J73: =J74*I73/I74 -> 7.7195867 | K73: 2.8093645 | O73: 92.41619 | P73: 92.019181
B74: 31382 | D74: =D75*$O74/$O75 -> 92.449745 | E74: =E75*$P74/$P75 -> 93.521684 | F74: =E74 -> 93.521684 | I74: 8.02 | J74: =J75*I74/I75 -> 8.4949348 | K74: 2.802954 | O74: 92.567144 | P74: 92.128467
A75: =YEAR(B75) -> 1986 | B75: 31413 | D75: =D76*$O75/$O76 -> 92.638653 | E75: =E76*$P75/$P76 -> 93.299806 | F75: =E75 -> 93.299806 | I75: 6.8438 | J75: =J76*I75/I76 -> 7.2490817 | K75: 2.6986507 | O75: 92.756292 | P75: 91.909894
B76: 31444 | D76: =D77*$O76/$O77 -> 92.84635 | E76: =E77*$P76/$P77 -> 93.299806 | F76: =E76 -> 93.299806 | I76: 5.7813 | J76: =J77*I76/I77 -> 6.1236617 | K76: 2.5974026 | O76: 92.964253 | P76: 91.909894
B77: 31472 | D77: =D78*$O77/$O78 -> 92.780499 | E77: =E78*$P77/$P78 -> 93.410745 | F77: =E77 -> 93.410745 | I77: 5.5339 | J77: =J78*I77/I78 -> 5.861611 | K77: 2.7310575 | O77: 92.898318 | P77: 92.019181
B78: 31503 | D78: =D79*$O78/$O79 -> 92.852073 | E78: =E79*$P78/$P79 -> 93.854501 | F78: =E78 -> 93.854501 | I78: 4.7031 | J78: =J79*I78/I79 -> 4.981612 | K78: 2.8599933 | O78: 92.969983 | P78: 92.456327
B79: 31533 | D79: =D80*$O79/$O80 -> 92.973277 | E79: =E80*$P79/$P80 -> 94.409197 | F79: =E79 -> 94.409197 | I79: 4.2135 | J79: =J80*I79/I80 -> 4.4630184 | K79: 2.670227 | O79: 93.091341 | P79: 93.002759
B80: 31564 | D80: =D81*$O80/$O81 -> 92.705498 | E80: =E81*$P80/$P81 -> 94.409197 | F80: =E80 -> 94.409197 | I80: 4.3906 | J80: =J81*I80/I81 -> 4.6506061 | K80: 2.7315123 | O80: 92.823222 | P80: 93.002759
B81: 31594 | D81: =D82*$O81/$O82 -> 92.616105 | E81: =E82*$P81/$P82 -> 94.298258 | F81: =E81 -> 94.298258 | I81: 4.5048 | J81: =J82*I81/I82 -> 4.7715689 | K81: 2.8983107 | O81: 92.733715 | P81: 92.893472
B82: 31625 | D82: =D83*$O82/$O83 -> 92.644288 | E82: =E83*$P82/$P83 -> 93.96544 | F82: =E82 -> 93.96544 | I82: 4.5521 | J82: =J83*I82/I83 -> 4.8216699 | K82: 2.8481537 | O82: 92.761934 | P82: 92.565613
B83: 31656 | D83: =D84*$O83/$O84 -> 92.611216 | E83: =E84*$P83/$P84 -> 94.409197 | F83: =E83 -> 94.409197 | I83: 4.6307 | J83: =J84*I83/I84 -> 4.9049245 | K83: 2.7851459 | O83: 92.72882 | P83: 93.002759
B84: 31686 | D84: =D85*$O84/$O85 -> 92.617357 | E84: =E85*$P84/$P85 -> 94.742014 | F84: =E84 -> 94.742014 | I84: 4.4089 | J84: =J85*I84/I85 -> 4.6699898 | K84: 2.7331456 | O84: 92.734969 | P84: 93.330618
B85: 31717 | D85: =D86*$O85/$O86 -> 92.535861 | E85: =E86*$P85/$P86 -> 94.742014 | F85: =E85 -> 94.742014 | I85: 3.7708 | J85: =J86*I85/I86 -> 3.9941023 | K85: 2.7681087 | O85: 92.653369 | P85: 93.330618
B86: 31747 | D86: =D87*$O86/$O87 -> 92.55474 | E86: =E87*$P86/$P87 -> 94.852953 | F86: =E86 -> 94.852953 | I86: 4.1825 | J86: =J87*I86/I87 -> 4.4301827 | K86: 2.8812717 | O86: 92.672272 | P86: 93.439905
A87: =YEAR(B87) -> 1987 | B87: 31778 | D87: =D88*$O87/$O88 -> 92.429286 | E87: =E88*$P87/$P88 -> 94.409197 | F87: =E87 -> 94.409197 | I87: 4.0863 | J87: =J88*I87/I88 -> 4.3282858 | K87: 2.9621049 | O87: 92.546659 | P87: 93.002759
B88: 31809 | D88: =D89*$O88/$O89 -> 92.685172 | E88: =E89*$P88/$P89 -> 94.409197 | F88: =E88 -> 94.409197 | I88: 4.0536 | J88: =J89*I88/I89 -> 4.2936494 | K88: 2.9621049 | O88: 92.802869 | P88: 93.002759
B89: 31837 | D89: =D90*$O89/$O90 -> 92.73633 | E89: =E90*$P89/$P90 -> 94.520136 | F89: =E89 -> 94.520136 | I89: 3.8542 | J89: =J90*I89/I90 -> 4.0824411 | K89: 2.9038113 | O89: 92.854093 | P89: 93.112045
B90: 31868 | D90: =D91*$O90/$O91 -> 92.935085 | E90: =E91*$P90/$P91 -> 94.963893 | F90: =E90 -> 94.963893 | I90: 3.519 | J90: =J91*I90/I91 -> 3.727391 | K90: 2.966381 | O90: 93.053101 | P90: 93.549191
B91: 31898 | D91: =D92*$O91/$O92 -> 92.769225 | E91: =E92*$P91/$P92 -> 94.963893 | F91: =E91 -> 94.963893 | I91: 3.1648 | J91: =J92*I91/I92 -> 3.3522157 | K91: 3.0956694 | O91: 92.88703 | P91: 93.549191
B92: 31929 | D92: =D93*$O92/$O93 -> 92.95633 | E92: =E93*$P92/$P93 -> 95.185771 | F92: =E92 -> 95.185771 | I92: 3.1615 | J92: =J93*I92/I93 -> 3.3487203 | K92: 2.9590663 | O92: 93.074372 | P92: 93.767764
B93: 31959 | D93: =D94*$O93/$O94 -> 93.07733 | E93: =E94*$P93/$P94 -> 95.074832 | F93: =E93 -> 95.074832 | I93: 3.1675 | J93: =J94*I93/I94 -> 3.3550756 | K93: 2.7347611 | O93: 93.195526 | P93: 93.658477
B94: 31990 | D94: =D95*$O94/$O95 -> 93.175556 | E94: =E95*$P94/$P95 -> 94.963893 | F94: =E94 -> 94.963893 | I94: 3.1901 | J94: =J95*I94/I95 -> 3.3790139 | K94: 2.7700377 | O94: 93.293877 | P94: 93.549191
B95: 32021 | D95: =D96*$O95/$O96 -> 93.0589 | E95: =E96*$P95/$P96 -> 95.185771 | F95: =E95 -> 95.185771 | I95: 3.3892 | J95: =J96*I95/I96 -> 3.5899044 | K95: 2.7550016 | O95: 93.177073 | P95: 93.767764
B96: 32051 | D96: =D97*$O96/$O97 -> 93.075181 | E96: =E97*$P96/$P97 -> 95.407649 | F96: =E96 -> 95.407649 | I96: 3.3725 | J96: =J97*I96/I97 -> 3.5722154 | K96: 2.7199738 | O96: 93.193375 | P96: 93.986337
B97: 32082 | D97: =D98*$O97/$O98 -> 93.083571 | E97: =E98*$P97/$P98 -> 95.407649 | F97: =E97 -> 95.407649 | I97: 3.3899 | J97: =J98*I97/I98 -> 3.5906458 | K97: 2.6625286 | O97: 93.201775 | P97: 93.986337
B98: 32112 | D98: =D99*$O98/$O99 -> 93.086411 | E98: =E99*$P98/$P99 -> 95.518588 | F98: =E98 -> 95.518588 | I98: 3.8125 | J98: =J99*I98/I99 -> 4.0382717 | K98: 2.6388663 | O98: 93.204618 | P98: 94.095623
A99: =YEAR(B99) -> 1988 | B99: 32143 | D99: =D100*$O99/$O100 -> 93.095949 | E99: =E100*$P99/$P100 -> 95.074832 | F99: =E99 -> 95.074832 | I99: 3.5446 | J99: =J100*I99/I100 -> 3.754507 | K99: 2.685984 | O99: 93.214169 | P99: 93.658477
B100: 32174 | D100: =D101*$O100/$O101 -> 93.107503 | E100: =E101*$P100/$P101 -> 94.963893 | F100: =E100 -> 94.963893 | I100: 3.3977 | J100: =J101*I100/I101 -> 3.5989077 | K100: 2.7238623 | O100: 93.225737 | P100: 93.549191
...

Sheet KR - Q
C1: GDP: 2022-23p: sa | D1: Unit Labour Cost: Nominal | E1: Unit Labour Cost: Nominal | F1: KR CPI Headline | G1: KR Core CPI (Excl Food & Energy) | H1: Unemployment | I1: Expectations | J1: Covid Stringency Index | K1: Import Price Deflator | L1: Interest | M1: CPI Core Forecast | N1: ImPl | O1: ImPl QOQ Annualised | R1: CPI Core Inflation | S1: Inflation Average
B2: Date | D2: NSA | E2: SA - don’t drag down
A3: 1960 | B3: 21976 | C3: ='CDM - Q'!Y52 -> 7530.1 | J3: 0 | K3: ='CDM - Q'!AD52/'CDM - Q'!AC52*100 -> 2.0297154
B4: 22068 | C4: ='CDM - Q'!Y53 -> 7878.4 | J4: 0 | K4: ='CDM - Q'!AD53/'CDM - Q'!AC53*100 -> 2.058319
B5: 22160 | C5: ='CDM - Q'!Y54 -> 7788.8 | J5: 0 | K5: ='CDM - Q'!AD54/'CDM - Q'!AC54*100 -> 2.5090123
B6: 22251 | C6: ='CDM - Q'!Y55 -> 7834.3 | J6: 0 | K6: ='CDM - Q'!AD55/'CDM - Q'!AC55*100 -> 2.5081327
A7: 1961 | B7: 22341 | C7: ='CDM - Q'!Y56 -> 8081.8 | J7: 0 | K7: ='CDM - Q'!AD56/'CDM - Q'!AC56*100 -> 3.3686917
B8: 22433 | C8: ='CDM - Q'!Y57 -> 8431.4 | J8: 0 | K8: ='CDM - Q'!AD57/'CDM - Q'!AC57*100 -> 3.3693182
B9: 22525 | C9: ='CDM - Q'!Y58 -> 8279.5 | J9: 0 | K9: ='CDM - Q'!AD58/'CDM - Q'!AC58*100 -> 3.5627689
B10: 22616 | C10: ='CDM - Q'!Y59 -> 8386.2 | J10: 0 | K10: ='CDM - Q'!AD59/'CDM - Q'!AC59*100 -> 3.5826904
A11: 1962 | B11: 22706 | C11: ='CDM - Q'!Y60 -> 8551.1 | J11: 0 | K11: ='CDM - Q'!AD60/'CDM - Q'!AC60*100 -> 3.4424441
B12: 22798 | C12: ='CDM - Q'!Y61 -> 8387.5 | J12: 0 | K12: ='CDM - Q'!AD61/'CDM - Q'!AC61*100 -> 3.4458107
B13: 22890 | C13: ='CDM - Q'!Y62 -> 8640.8 | J13: 0 | K13: ='CDM - Q'!AD62/'CDM - Q'!AC62*100 -> 3.4507678
B14: 22981 | C14: ='CDM - Q'!Y63 -> 8900.8 | J14: 0 | K14: ='CDM - Q'!AD63/'CDM - Q'!AC63*100 -> 3.4614607
A15: 1963 | B15: 23071 | C15: ='CDM - Q'!Y64 -> 9407.9 | J15: 0 | K15: ='CDM - Q'!AD64/'CDM - Q'!AC64*100 -> 3.852459
B16: 23163 | C16: ='CDM - Q'!Y65 -> 9176.4 | J16: 0 | K16: ='CDM - Q'!AD65/'CDM - Q'!AC65*100 -> 3.7383721
B17: 23255 | C17: ='CDM - Q'!Y66 -> 9492.5 | J17: 0 | K17: ='CDM - Q'!AD66/'CDM - Q'!AC66*100 -> 3.6063504
B18: 23346 | C18: ='CDM - Q'!Y67 -> 9509.9 | J18: 0 | K18: ='CDM - Q'!AD67/'CDM - Q'!AC67*100 -> 3.5410485
A19: 1964 | B19: 23437 | C19: ='CDM - Q'!Y68 -> 10057.1 | J19: 0 | K19: ='CDM - Q'!AD68/'CDM - Q'!AC68*100 -> 4.6710526
B20: 23529 | C20: ='CDM - Q'!Y69 -> 9762.3 | J20: 0 | K20: ='CDM - Q'!AD69/'CDM - Q'!AC69*100 -> 5.9135837
B21: 23621 | C21: ='CDM - Q'!Y70 -> 10436.9 | J21: 0 | K21: ='CDM - Q'!AD70/'CDM - Q'!AC70*100 -> 6.5434783
B22: 23712 | C22: ='CDM - Q'!Y71 -> 10873.6 | J22: 0 | K22: ='CDM - Q'!AD71/'CDM - Q'!AC71*100 -> 6.5518067
A23: 1965 | B23: 23802 | C23: ='CDM - Q'!Y72 -> 10988 | J23: 0 | K23: ='CDM - Q'!AD72/'CDM - Q'!AC72*100 -> 6.4353393
B24: 23894 | C24: ='CDM - Q'!Y73 -> 11002.3 | J24: 0 | K24: ='CDM - Q'!AD73/'CDM - Q'!AC73*100 -> 6.6961435
B25: 23986 | C25: ='CDM - Q'!Y74 -> 10936 | J25: 0 | K25: ='CDM - Q'!AD74/'CDM - Q'!AC74*100 -> 6.9300488
B26: 24077 | C26: ='CDM - Q'!Y75 -> 11211.8 | J26: 0 | K26: ='CDM - Q'!AD75/'CDM - Q'!AC75*100 -> 6.9222118
A27: 1966 | B27: 24167 | C27: ='CDM - Q'!Y76 -> 11868.1 | J27: 0 | K27: ='CDM - Q'!AD76/'CDM - Q'!AC76*100 -> 7.5138122
B28: 24259 | C28: ='CDM - Q'!Y77 -> 12604.9 | J28: 0 | K28: ='CDM - Q'!AD77/'CDM - Q'!AC77*100 -> 7.4035383
B29: 24351 | C29: ='CDM - Q'!Y78 -> 12400.5 | J29: 0 | K29: ='CDM - Q'!AD78/'CDM - Q'!AC78*100 -> 7.2914358
B30: 24442 | C30: ='CDM - Q'!Y79 -> 12564.7 | J30: 0 | K30: ='CDM - Q'!AD79/'CDM - Q'!AC79*100 -> 7.3129051
A31: 1967 | B31: 24532 | C31: ='CDM - Q'!Y80 -> 12971.7 | J31: 0 | K31: ='CDM - Q'!AD80/'CDM - Q'!AC80*100 -> 7.8503071
B32: 24624 | C32: ='CDM - Q'!Y81 -> 13256.5 | J32: 0 | K32: ='CDM - Q'!AD81/'CDM - Q'!AC81*100 -> 7.4029491
B33: 24716 | C33: ='CDM - Q'!Y82 -> 13823 | J33: 0 | K33: ='CDM - Q'!AD82/'CDM - Q'!AC82*100 -> 7.4199943
B34: 24807 | C34: ='CDM - Q'!Y83 -> 13911.3 | J34: 0 | K34: ='CDM - Q'!AD83/'CDM - Q'!AC83*100 -> 7.4903589
A35: 1968 | B35: 24898 | C35: ='CDM - Q'!Y84 -> 14750.8 | J35: 0 | K35: ='CDM - Q'!AD84/'CDM - Q'!AC84*100 -> 8.0490875
B36: 24990 | C36: ='CDM - Q'!Y85 -> 15011.8 | J36: 0 | K36: ='CDM - Q'!AD85/'CDM - Q'!AC85*100 -> 7.8126098
B37: 25082 | C37: ='CDM - Q'!Y86 -> 15831.9 | J37: 0 | K37: ='CDM - Q'!AD86/'CDM - Q'!AC86*100 -> 7.8239351
B38: 25173 | C38: ='CDM - Q'!Y87 -> 15503.5 | J38: 0 | K38: ='CDM - Q'!AD87/'CDM - Q'!AC87*100 -> 7.7929744
A39: 1969 | B39: 25263 | C39: ='CDM - Q'!Y88 -> 16266.5 | J39: 0 | K39: ='CDM - Q'!AD88/'CDM - Q'!AC88*100 -> 8.1166054
B40: 25355 | C40: ='CDM - Q'!Y89 -> 16883.4 | J40: 0 | K40: ='CDM - Q'!AD89/'CDM - Q'!AC89*100 -> 8.0552539
B41: 25447 | C41: ='CDM - Q'!Y90 -> 18296.3 | J41: 0 | K41: ='CDM - Q'!AD90/'CDM - Q'!AC90*100 -> 8.0888079
B42: 25538 | C42: ='CDM - Q'!Y91 -> 18566.2 | J42: 0 | K42: ='CDM - Q'!AD91/'CDM - Q'!AC91*100 -> 8.0773854
A43: 1970 | B43: 25628 | C43: ='CDM - Q'!Y92 -> 18254.5 | J43: 0 | K43: ='CDM - Q'!AD92/'CDM - Q'!AC92*100 -> 8.164116
B44: 25720 | C44: ='CDM - Q'!Y93 -> 19063.7 | J44: 0 | K44: ='CDM - Q'!AD93/'CDM - Q'!AC93*100 -> 8.3640524
B45: 25812 | C45: ='CDM - Q'!Y94 -> 19213.8 | J45: 0 | K45: ='CDM - Q'!AD94/'CDM - Q'!AC94*100 -> 8.8863623
B46: 25903 | C46: ='CDM - Q'!Y95 -> 20598.7 | J46: 0 | K46: ='CDM - Q'!AD95/'CDM - Q'!AC95*100 -> 9.7841402
A47: 1971 | B47: 25993 | C47: ='CDM - Q'!Y96 -> 20739.9 | J47: 0 | K47: ='CDM - Q'!AD96/'CDM - Q'!AC96*100 -> 8.876944
B48: 26085 | C48: ='CDM - Q'!Y97 -> 21485.5 | J48: 0 | K48: ='CDM - Q'!AD97/'CDM - Q'!AC97*100 -> 9.1599811
B49: 26177 | C49: ='CDM - Q'!Y98 -> 21525.4 | J49: 0 | K49: ='CDM - Q'!AD98/'CDM - Q'!AC98*100 -> 10.662068
B50: 26268 | C50: ='CDM - Q'!Y99 -> 21595.4 | J50: 0 | K50: ='CDM - Q'!AD99/'CDM - Q'!AC99*100 -> 10.67612
A51: 1972 | B51: 26359 | C51: ='CDM - Q'!Y100 -> 22003.9 | J51: 0 | K51: ='CDM - Q'!AD100/'CDM - Q'!AC100*100 -> 10.777449
B52: 26451 | C52: ='CDM - Q'!Y101 -> 22679.3 | J52: 0 | K52: ='CDM - Q'!AD101/'CDM - Q'!AC101*100 -> 11.127542
B53: 26543 | C53: ='CDM - Q'!Y102 -> 23012.1 | J53: 0 | K53: ='CDM - Q'!AD102/'CDM - Q'!AC102*100 -> 11.745015
B54: 26634 | C54: ='CDM - Q'!Y103 -> 23912.6 | J54: 0 | K54: ='CDM - Q'!AD103/'CDM - Q'!AC103*100 -> 11.70286
A55: 1973 | B55: 26724 | C55: ='CDM - Q'!Y104 -> 24863.1 | J55: 0 | K55: ='CDM - Q'!AD104/'CDM - Q'!AC104*100 -> 11.829307
B56: 26816 | C56: ='CDM - Q'!Y105 -> 25899.4 | J56: 0 | K56: ='CDM - Q'!AD105/'CDM - Q'!AC105*100 -> 13.551485
B57: 26908 | C57: ='CDM - Q'!Y106 -> 27124.3 | J57: 0 | K57: ='CDM - Q'!AD106/'CDM - Q'!AC106*100 -> 14.787569
B58: 26999 | C58: ='CDM - Q'!Y107 -> 27439.2 | J58: 0 | K58: ='CDM - Q'!AD107/'CDM - Q'!AC107*100 -> 16.37903
A59: 1974 | B59: 27089 | C59: ='CDM - Q'!Y108 -> 28845.8 | J59: 0 | K59: ='CDM - Q'!AD108/'CDM - Q'!AC108*100 -> 17.869518
B60: 27181 | C60: ='CDM - Q'!Y109 -> 28663.4 | J60: 0 | K60: ='CDM - Q'!AD109/'CDM - Q'!AC109*100 -> 20.468799
B61: 27273 | C61: ='CDM - Q'!Y110 -> 29042.4 | J61: 0 | K61: ='CDM - Q'!AD110/'CDM - Q'!AC110*100 -> 21.124109
B62: 27364 | C62: ='CDM - Q'!Y111 -> 28937.1 | J62: 0 | K62: ='CDM - Q'!AD111/'CDM - Q'!AC111*100 -> 22.432301
A63: 1975 | B63: 27454 | C63: ='CDM - Q'!Y112 -> 29533.3 | F63: =AVERAGEIFS('KR - M'!C:C,'KR - M'!$B:$B,">="&EDATE('KR - Q'!$B63,-2),'KR - M'!$B:$B,"<="&EOMONTH('KR - Q'!$B63,0)) -> 8.5360835 | G63: =G64*F63/F64 -> 9.2826759 | J63: 0 | K63: ='CDM - Q'!AD112/'CDM - Q'!AC112*100 -> 26.156044 | L63: =AVERAGEIFS('KR - M'!J:J,'KR - M'!B:B,">="&EDATE('KR - Q'!B63,-2),'KR - M'!B:B,"<="&EOMONTH('KR - Q'!B63,0)) -> 11 | M63: =G63 -> 9.2826759 | N63: =AVERAGE(VLOOKUP(EDATE($B63,-2),'KR - M'!B3:K706,10), VLOOKUP(EDATE($B63,-1),'KR - M'!B3:K706,10), VLOOKUP(EDATE($B63,0),'KR - M'!B3:K706,10)) -> 17.233811
B64: 27546 | C64: ='CDM - Q'!Y113 -> 30780 | F64: =AVERAGEIFS('KR - M'!C:C,'KR - M'!$B:$B,">="&EDATE('KR - Q'!$B64,-2),'KR - M'!$B:$B,"<="&EOMONTH('KR - Q'!$B64,0)) -> 9.1874728 | G64: =G65*F64/F65 -> 9.9910377 | J64: 0 | K64: ='CDM - Q'!AD113/'CDM - Q'!AC113*100 -> 25.209333 | L64: =AVERAGEIFS('KR - M'!J:J,'KR - M'!B:B,">="&EDATE('KR - Q'!B64,-2),'KR - M'!B:B,"<="&EOMONTH('KR - Q'!B64,0)) -> 11 | M64: =G64 -> 9.9910377 | N64: =AVERAGE(VLOOKUP(EDATE($B64,-2),'KR - M'!B4:K707,10), VLOOKUP(EDATE($B64,-1),'KR - M'!B4:K707,10), VLOOKUP(EDATE($B64,0),'KR - M'!B4:K707,10)) -> 16.631176 | O64: =(N64/N63-1)*400 -> -13.987264 | R64: =(G64/G63-1)*400 -> 30.524034
B65: 27638 | C65: ='CDM - Q'!Y114 -> 31660.5 | F65: =AVERAGEIFS('KR - M'!C:C,'KR - M'!$B:$B,">="&EDATE('KR - Q'!$B65,-2),'KR - M'!$B:$B,"<="&EOMONTH('KR - Q'!$B65,0)) -> 9.7889158 | G65: =G66*F65/F66 -> 10.645085 | J65: 0 | K65: ='CDM - Q'!AD114/'CDM - Q'!AC114*100 -> 23.72093 | L65: =AVERAGEIFS('KR - M'!J:J,'KR - M'!B:B,">="&EDATE('KR - Q'!B65,-2),'KR - M'!B:B,"<="&EOMONTH('KR - Q'!B65,0)) -> 11 | M65: =G65 -> 10.645085 | N65: =AVERAGE(VLOOKUP(EDATE($B65,-2),'KR - M'!B5:K708,10), VLOOKUP(EDATE($B65,-1),'KR - M'!B5:K708,10), VLOOKUP(EDATE($B65,0),'KR - M'!B5:K708,10)) -> 16.694134 | O65: =(N65/N64-1)*400 -> 1.5142201 | R65: =(G65/G64-1)*400 -> 26.185354
B66: 27729 | C66: ='CDM - Q'!Y115 -> 32674.9 | F66: =AVERAGEIFS('KR - M'!C:C,'KR - M'!$B:$B,">="&EDATE('KR - Q'!$B66,-2),'KR - M'!$B:$B,"<="&EOMONTH('KR - Q'!$B66,0)) -> 10.383707 | G66: =G67*F66/F67 -> 11.291898 | J66: 0 | K66: ='CDM - Q'!AD115/'CDM - Q'!AC115*100 -> 23.33021 | L66: =AVERAGEIFS('KR - M'!J:J,'KR - M'!B:B,">="&EDATE('KR - Q'!B66,-2),'KR - M'!B:B,"<="&EOMONTH('KR - Q'!B66,0)) -> 13 | M66: =G66 -> 11.291898 | N66: =AVERAGE(VLOOKUP(EDATE($B66,-2),'KR - M'!B6:K709,10), VLOOKUP(EDATE($B66,-1),'KR - M'!B6:K709,10), VLOOKUP(EDATE($B66,0),'KR - M'!B6:K709,10)) -> 16.735581 | O66: =(N66/N65-1)*400 -> 0.99308975 | R66: =(G66/G65-1)*400 -> 24.304674
A67: 1976 | B67: 27820 | C67: ='CDM - Q'!Y116 -> 33709.8 | F67: =AVERAGEIFS('KR - M'!C:C,'KR - M'!$B:$B,">="&EDATE('KR - Q'!$B67,-2),'KR - M'!$B:$B,"<="&EOMONTH('KR - Q'!$B67,0)) -> 10.459625 | G67: =G68*F67/F68 -> 11.374456 | I67: =I68*S67/S68 -> 33.417069 | J67: 0 | K67: ='CDM - Q'!AD116/'CDM - Q'!AC116*100 -> 23.728424 | L67: =AVERAGEIFS('KR - M'!J:J,'KR - M'!B:B,">="&EDATE('KR - Q'!B67,-2),'KR - M'!B:B,"<="&EOMONTH('KR - Q'!B67,0)) -> 14 | M67: =G67 -> 11.374456 | N67: =AVERAGE(VLOOKUP(EDATE($B67,-2),'KR - M'!B7:K710,10), VLOOKUP(EDATE($B67,-1),'KR - M'!B7:K710,10), VLOOKUP(EDATE($B67,0),'KR - M'!B7:K710,10)) -> 16.547038 | O67: =(N67/N66-1)*400 -> -4.5064003 | R67: =(G67/G66-1)*400 -> 2.9245124 | S67: =AVERAGE(R64:R67) -> 20.984644
B68: 27912 | C68: ='CDM - Q'!Y117 -> 35174.8 | F68: =AVERAGEIFS('KR - M'!C:C,'KR - M'!$B:$B,">="&EDATE('KR - Q'!$B68,-2),'KR - M'!$B:$B,"<="&EOMONTH('KR - Q'!$B68,0)) -> 10.756926 | G68: =G69*F68/F69 -> 11.69776 | I68: =I69*S68/S69 -> 25.791376 | J68: 0 | K68: ='CDM - Q'!AD117/'CDM - Q'!AC117*100 -> 24.042134 | L68: =AVERAGEIFS('KR - M'!J:J,'KR - M'!B:B,">="&EDATE('KR - Q'!B68,-2),'KR - M'!B:B,"<="&EOMONTH('KR - Q'!B68,0)) -> 14 | M68: =G68 -> 11.69776 | N68: =AVERAGE(VLOOKUP(EDATE($B68,-2),'KR - M'!B8:K711,10), VLOOKUP(EDATE($B68,-1),'KR - M'!B8:K711,10), VLOOKUP(EDATE($B68,0),'KR - M'!B8:K711,10)) -> 17.05467 | O68: =(N68/N67-1)*400 -> 12.271247 | R68: =(G68/G67-1)*400 -> 11.369457 | S68: =AVERAGE(R65:R68) -> 16.196
B69: 28004 | C69: ='CDM - Q'!Y118 -> 35942.9 | F69: =AVERAGEIFS('KR - M'!C:C,'KR - M'!$B:$B,">="&EDATE('KR - Q'!$B69,-2),'KR - M'!$B:$B,"<="&EOMONTH('KR - Q'!$B69,0)) -> 11.146228 | G69: =G70*F69/F70 -> 12.121112 | I69: =I70*S69/S70 -> 21.129858 | J69: 0 | K69: ='CDM - Q'!AD118/'CDM - Q'!AC118*100 -> 24.752291 | L69: =AVERAGEIFS('KR - M'!J:J,'KR - M'!B:B,">="&EDATE('KR - Q'!B69,-2),'KR - M'!B:B,"<="&EOMONTH('KR - Q'!B69,0)) -> 14 | M69: =G69 -> 12.121112 | N69: =AVERAGE(VLOOKUP(EDATE($B69,-2),'KR - M'!B9:K712,10), VLOOKUP(EDATE($B69,-1),'KR - M'!B9:K712,10), VLOOKUP(EDATE($B69,0),'KR - M'!B9:K712,10)) -> 17.700216 | O69: =(N69/N68-1)*400 -> 15.14063 | R69: =(G69/G68-1)*400 -> 14.476333 | S69: =AVERAGE(R66:R69) -> 13.268744
B70: 28095 | C70: ='CDM - Q'!Y119 -> 36353.6 | F70: =AVERAGEIFS('KR - M'!C:C,'KR - M'!$B:$B,">="&EDATE('KR - Q'!$B70,-2),'KR - M'!$B:$B,"<="&EOMONTH('KR - Q'!$B70,0)) -> 11.339686 | G70: =G71*F70/F71 -> 12.33149 | I70: =I71*S70/S71 -> 14.217758 | J70: 0 | K70: ='CDM - Q'!AD119/'CDM - Q'!AC119*100 -> 25.435378 | L70: =AVERAGEIFS('KR - M'!J:J,'KR - M'!B:B,">="&EDATE('KR - Q'!B70,-2),'KR - M'!B:B,"<="&EOMONTH('KR - Q'!B70,0)) -> 14 | M70: =G70 -> 12.33149 | N70: =AVERAGE(VLOOKUP(EDATE($B70,-2),'KR - M'!B10:K713,10), VLOOKUP(EDATE($B70,-1),'KR - M'!B10:K713,10), VLOOKUP(EDATE($B70,0),'KR - M'!B10:K713,10)) -> 18.019343 | O70: =(N70/N69-1)*400 -> 7.2118186 | R70: =(G70/G69-1)*400 -> 6.9425351 | S70: =AVERAGE(R67:R70) -> 8.9282096
A71: 1977 | B71: 28185 | C71: ='CDM - Q'!Y120 -> 36753.8 | F71: =AVERAGEIFS('KR - M'!C:C,'KR - M'!$B:$B,">="&EDATE('KR - Q'!$B71,-2),'KR - M'!$B:$B,"<="&EOMONTH('KR - Q'!$B71,0)) -> 11.560413 | G71: =G72*F71/F72 -> 12.571523 | I71: =I72*S71/S72 -> 16.15319 | J71: 0 | K71: ='CDM - Q'!AD120/'CDM - Q'!AC120*100 -> 25.082076 | L71: =AVERAGEIFS('KR - M'!J:J,'KR - M'!B:B,">="&EDATE('KR - Q'!B71,-2),'KR - M'!B:B,"<="&EOMONTH('KR - Q'!B71,0)) -> 14 | M71: =G71 -> 12.571523 | N71: =AVERAGE(VLOOKUP(EDATE($B71,-2),'KR - M'!B11:K714,10), VLOOKUP(EDATE($B71,-1),'KR - M'!B11:K714,10), VLOOKUP(EDATE($B71,0),'KR - M'!B11:K714,10)) -> 17.435565 | O71: =(N71/N70-1)*400 -> -12.958927 | R71: =(G71/G70-1)*400 -> 7.7860206 | S71: =AVERAGE(R68:R71) -> 10.143587
B72: 28277 | C72: ='CDM - Q'!Y121 -> 38566.5 | F72: =AVERAGEIFS('KR - M'!C:C,'KR - M'!$B:$B,">="&EDATE('KR - Q'!$B72,-2),'KR - M'!$B:$B,"<="&EOMONTH('KR - Q'!$B72,0)) -> 11.825575 | G72: =G73*F72/F73 -> 12.859877 | I72: =I73*S72/S73 -> 15.279481 | J72: 0 | K72: ='CDM - Q'!AD121/'CDM - Q'!AC121*100 -> 25.119234 | L72: =AVERAGEIFS('KR - M'!J:J,'KR - M'!B:B,">="&EDATE('KR - Q'!B72,-2),'KR - M'!B:B,"<="&EOMONTH('KR - Q'!B72,0)) -> 14 | M72: =G72 -> 12.859877 | N72: =AVERAGE(VLOOKUP(EDATE($B72,-2),'KR - M'!B12:K715,10), VLOOKUP(EDATE($B72,-1),'KR - M'!B12:K715,10), VLOOKUP(EDATE($B72,0),'KR - M'!B12:K715,10)) -> 17.441697 | O72: =(N72/N71-1)*400 -> 0.1406939 | R72: =(G72/G71-1)*400 -> 9.1748336 | S72: =AVERAGE(R69:R72) -> 9.5949307
B73: 28369 | C73: ='CDM - Q'!Y122 -> 40925.7 | F73: =AVERAGEIFS('KR - M'!C:C,'KR - M'!$B:$B,">="&EDATE('KR - Q'!$B73,-2),'KR - M'!$B:$B,"<="&EOMONTH('KR - Q'!$B73,0)) -> 12.204804 | G73: =G74*F73/F74 -> 13.272274 | I73: =I74*S73/S74 -> 14.623022 | J73: 0 | K73: ='CDM - Q'!AD122/'CDM - Q'!AC122*100 -> 25.702264 | L73: =AVERAGEIFS('KR - M'!J:J,'KR - M'!B:B,">="&EDATE('KR - Q'!B73,-2),'KR - M'!B:B,"<="&EOMONTH('KR - Q'!B73,0)) -> 14 | M73: =G73 -> 13.272274 | N73: =AVERAGE(VLOOKUP(EDATE($B73,-2),'KR - M'!B13:K716,10), VLOOKUP(EDATE($B73,-1),'KR - M'!B13:K716,10), VLOOKUP(EDATE($B73,0),'KR - M'!B13:K716,10)) -> 17.565082 | O73: =(N73/N72-1)*400 -> 2.8296333 | R73: =(G73/G72-1)*400 -> 12.82741 | S73: =AVERAGE(R70:R73) -> 9.1826998
B74: 28460 | C74: ='CDM - Q'!Y123 -> 42409.5 | F74: =AVERAGEIFS('KR - M'!C:C,'KR - M'!$B:$B,">="&EDATE('KR - Q'!$B74,-2),'KR - M'!$B:$B,"<="&EOMONTH('KR - Q'!$B74,0)) -> 12.529129 | G74: =G75*F74/F75 -> 13.624966 | I74: =I75*S74/S75 -> 16.090825 | J74: 0 | K74: ='CDM - Q'!AD123/'CDM - Q'!AC123*100 -> 25.571748 | L74: =AVERAGEIFS('KR - M'!J:J,'KR - M'!B:B,">="&EDATE('KR - Q'!B74,-2),'KR - M'!B:B,"<="&EOMONTH('KR - Q'!B74,0)) -> 14 | M74: =G74 -> 13.624966 | N74: =AVERAGE(VLOOKUP(EDATE($B74,-2),'KR - M'!B14:K717,10), VLOOKUP(EDATE($B74,-1),'KR - M'!B14:K717,10), VLOOKUP(EDATE($B74,0),'KR - M'!B14:K717,10)) -> 17.579413 | O74: =(N74/N73-1)*400 -> 0.32635796 | R74: =(G74/G73-1)*400 -> 10.62943 | S74: =AVERAGE(R71:R74) -> 10.104424
